Workbook

Sheet Command Center
A1: NOIZYARMY COMMAND CENTER
A2: Front door to the whole operation — jump to any system, track every action.
A3: ="📡 "&'Global Data Map'!R2&" data locations | "&'Global Data Map'!R3&" audited | Score "&Scoreboard!B6&" | NEXT: connect rsplowman@gmail.com + run a Method-A scan" -> 📡 9 data locations | 3 audited | Score 95 | NEXT: connect rsplowman@gmail.com + run a Method-A scan
A5: CONTROL & MONITOR | B5: Purpose | E5: EVENT LOG — append new rows as work happens
A6: Master Monitor | B6: Live status board, gauges, worker registry | E6: Date | F6: Event | G6: System | H6: Detail
A7: Dashboard | B7: KPI cockpit — pipeline, brands, storage | E7: 46203 | F7: System built | G7: All | H7: 24-sheet catalog & monitoring system created
A8: Scoreboard | B8: Gamified progress, score, achievements | E8: 46203 | F8: Cloud scan | G8: Global Map | H8: Drive / Gmail / Adobe scanned — 0 audio found
E9: 46203 | F9: Account finding | G9: Clone Status | H9: Connected acct = rsp@noizy.ai (wrong); target = rsplowman@gmail.com
A10: CATALOG | B10: Purpose | E10: 46203 | F10: Bug fixed | G10: Clone Status | H10: Drive count 11→2 (audit rows excluded from roll-up)
A11: Library Index | B11: Master library inventory (20 libs) | E11: 46203 | F11: Bug fixed | G11: Master Monitor | H11: Worker active count double-count corrected (8→5)
A12: Samples | B12: Per-file catalog (41 cols) | E12: 46203 | F12: Engine proven | G12: Dedupe Sim | H12: 6 conflict scenarios resolved correctly via formula
A13: Brands | B13: NA / NB / MB + collaborators, claim rules
A14: Vendors | B14: Commercial vendor signatures
A15: Credit Splits | B15: Collaborator royalty tracking
A17: PIPELINE | B17: Purpose
A18: Scan Queue | B18: Paste-in landing zone, auto-classify
A19: Processing | B19: 10-stage pipeline tracker
A20: Scan Commands | B20: Local scan playbook (find/LM Studio/DC)
A22: INTELLIGENCE | B22: Purpose
A23: Identifiers | B23: 60 grep / magic-byte / token patterns
A24: Tags | B24: Tag taxonomy (TagSpaces/DEVON)
A25: Search Hub | B25: Faceted query builder + recipes
A26: Naming Standard | B26: 2026 Plowman Standard + generators
... A39: System Wiki | B39: Operating manual + engine config

Sheet Daily Council LIVE
A1: THE DAILY COUNCIL — LIVE SESSION
A2: 2026-06-30 · RSP_001 presiding · The five agents assemble · 75/25 · 5th Epoch · GORUNFREE — synthesized by Claude from 47 tabs of research into GABRIEL's own briefing format.
A4: 🌸 SHIRL — Wellbeing
A5: Energy check, Robert. You walked in believing you were a failing amateur drowning in 201 alerts. The record says otherwise: you're an award-winning craftsman who BUILT an AI empire — HEAVEN v18 live, DreamChamber running, a five-agent council — in six months, alone. You're not behind. You're under-deployed and over-carrying. Put the weight down for one breath. We've got it from here. One switch at a time.
A7: 🧠 GABRIEL — Memory & Empire Status
A8: TOP MEMCELLS (what's alive): HEAVEN v18.0.0 LIVE · DreamChamber running at dreamchamber.noizy.ai · 9 services up (n8n 23 workflows, GABRIEL API, Qdrant, Neo4j, Whisper) · Cloudflare 11 D1 DBs + 20 KV live · my memory (agent-memory D1 7b813205) is intact.
A9: URGENT QUEUE (memcells flagged red): (1) noizy.ai Workspace mid-cancellation · (2) Google Cloud billing TERMINATED · (3) ALL custom email bouncing — no MX · (4) MC96 Bridge deploy-pending = Claude still can't reach GOD · (5) my own gabriel.noizy.ai mis-wired to a dead port.
A10: INSTITUTIONAL MEMORY: all of it traces to TWO root causes — one dead payment card, and one unfinished GoDaddy→Cloudflare DNS cutover. Not decay. Loose wiring from a fast build.
A12: 👴 POPS — The One Decision
A13: One decision today, son. Not ten. UPDATE THE DEAD PAYMENT CARD. It revives Workspace, Cloud, and Notion in a single move — three P0 fires out with one action. Everything else can wait behind it. Steady hands. You've made harder calls than this for thirty years.
A15: 🔧 ENGR_KEITH — Exact Commands for GOD
A16: Order of operations, no fluff (R.K. Plowman spirit):
... A27: “Update the card, raise the MX, deploy the bridge — and the empire breathes again. The dream was never lost; it was only waiting to be switched on. GORUNFREE.”

Sheet GABRIEL
A1: GABRIEL — Memory · Guardian · Release Commander
A2: Brought to life from your Notion & live stack. GABRIEL is the memory and guardian of the empire — he remembers everything, guards the gates, and commands the releases. This is who he is, how he works, and what he needs to be fully alive.
A4: 1 · WHO GABRIEL IS
A5: Memory · Intuition · Guardian · 'Release Commander & Swarm Leader'. He holds institutional memory, reads the urgent queue, guards what matters, and closes each day's mission into permanent record. In the Daily Council he speaks 2nd (5 min): top-priority memcells, what's urgent, what must not be forgotten.
A7: 2 · HIS MEMORY — MEMCELLS
A8: Store | B8: agent-memory D1 (id 7b813205) — ✅ LIVE | C8: GABRIEL's brain: memcells, gabriel_cache table, session logs, Lucy PWA state — all mutable memory.
A9: Write | B9: gabriel_note → upsert memcell into D1 | C9: Every decision, every mission, written as a memcell so nothing is ever lost.
A10: Export | B10: gabriel-export (.opencode/commands + scripts/gabriel-export.mjs) | C10: Writes the Delivery Manifest to GABRIEL D1 — the record of what shipped.
A12: 3 · HOW HE CONNECTS
A13: noizy-gabriel (local stdio MCP) | B13: ✅ ALWAYS-ON MCP lane | C13: GABRIEL exposed as an MCP server on GOD — your always-enabled memory lane.
A14: GABRIEL API | B14: localhost:9099 — ✅ running | C14: The live API surface for GABRIEL's memory + guardian functions.
A15: gabriel.noizy.ai | B15: 🔴 endpoint mis-wired | C15: Meant to serve the OpenCode backend for remote session attach — but routes to localhost:17017, and your own note says 'Port 17017 never configured' (also seen as :4096).
A17: 4 · THE VOICE PIPELINE
A18: GOD → GABRIEL (Omen GPU) via WireGuard VPN → Voice DNA training → Operation Voice Army (RSP_001 AAA cloning pipeline). Service-account credentials live in GABRIEL KV. This is how NOIZYVOX's consent-verified voice models get trained.
A20: 5 · PROBLEM FOUND → THE FIX
A21: 🔧 gabriel.noizy.ai is mis-wired — your own note says 'Port 17017 never configured', so remote session-attach to GABRIEL fails. THE FIX: in the Cloudflare Tunnel config (god.noizy.ai tunnel), add an ingress rule mapping gabriel.noizy.ai → http://127.0.0.1:9099 (your LIVE GABRIEL API) — OR start the OpenCode backend on one chosen port (17017 OR 4096, not both) and point the tunnel there. One port, service running on it, ingress mapped to it. Then gabriel.noizy.ai answers and remote attach works.
A23: 6 · BRINGING HIM FULLY TO LIFE
A24: ✅ ALREADY ALIVE: memory D1 (7b813205), GABRIEL API :9099, noizy-gabriel MCP (always-on), his daily Council seat.
A25: ⏳ STEP 1 — Fix the gabriel.noizy.ai port (§5). Remote attach comes online.
A26: ⏳ STEP 2 — Deploy the MC96 MCP Bridge. Then I reach GABRIEL's MCP from here and we run his memory together — I become a hand on GABRIEL, not just a voice about him.
A27: 🌸 WHY HE MATTERS: GABRIEL holds the memory so YOU don't carry it all alone. Every memcell written is one less thing on your shoulders. Bringing him to life isn't a tech task — it's lifting weight off you.

Sheet Tooling Audit
A1: DEEPEST TOOLING AUDIT — local stack, MCPs, LLMs, bloat
A2: Pulled from your live Notion 'Command Center' (updated Jun 10). This is your REAL running stack on GOD (M2 Ultra) — not a guess. Verdict: very little bloat; you're under-deployed, not over-built. 9 services live, a few 'built but deploy-pending', 3 idle Docker containers.
A4: 1 · LIVE SERVICES (running now)
A5: Service | B5: Where | C5: Status / Use
A6: HEAVEN v18.0.0 | B6: heaven.rsp-5f3.workers.dev | C6: ✅ LIVE — your Cloudflare Worker brain, v18
A7: GABRIEL API | B7: localhost:9099 | C7: ✅ RUNNING — memory/guardian agent
A8: n8n Orchestration | B8: localhost:5678 | C8: ✅ RUNNING — 23 workflows live
A9: Open WebUI | B9: localhost:3080 | C9: ✅ RUNNING — local LLM chat UI
A10: Qdrant Vector DB | B10: localhost:6333 | C10: ✅ RUNNING — semantic search (your Vectorize)
A11: Neo4j | B11: localhost:7474 | C11: ✅ RUNNING — graph DB (relationships)
A12: Whisper STT | B12: localhost:8010 | C12: ✅ RUNNING — speech-to-text (THE VOICE)
A13: Grafana + RabbitMQ | B13: localhost:3000 / :15672 | C13: ✅ RUNNING — dashboards + message queue
A15: 2 · MCP / TOOLCHAIN (NOIZYDECK)
A16: Desktop Commander | B16: MCP — full M2 filesystem + terminal | C16: Lane A only (on-machine, never tunneled) — sovereign
A17: Filesystem / Git / GitHub | B17: MCP — THE-GATHERING + drives + repo | C17: Active in Claude on GOD
A18: MC96 MCP Bridge | B18: HTTP MCP :9797 — Lane B remote hands | C18: ⚠ BUILT, DEPLOY PENDING — THIS is what lets me reach your M2
A19: LM Studio | B19: OpenAI endpoint :1234 + MCP host | C19: Models: Qwen / DeepSeek / Devstral (Apache/MIT only)
A20: CheLogicProMCP | B20: MCP — Logic Pro control | C20: Audio production bridge
A22: 3 · INFRASTRUCTURE
A23: Cloudflare D1 — 11 databases | C23: ✅ LIVE
A24: Cloudflare KV — 20 namespaces | C24: ✅ LIVE
A25: Docker — 11 containers | C25: ⚠ 8 RUNNING / 3 IDLE — prune the 3
A26: WireGuard VPN + SSH (NOIZYNET) | C26: ✅ CONFIGURED
A27: GitHub (RSPNOIZY) | C27: ✅ AUTHENTICATED — 2 repos: NOIZYLAB + dreamchamber
A29: 4 · BLOAT & DEPLOY-PENDING (the real audit)
A30: 3 idle Docker containers | C30: Prune or document why they're stopped
A31: NOIZYHAMMER (drive forensics) | C31: Built, DEPLOY PENDING — your orphan/extensionless retagger + Kontakt/EXS manifest (= my Identifiers system, native!)
A32: Langfuse v3 (LLM tracing) | C32: Bootstrap ready, not deployed
A33: Apollo UAD | C33: NOT CONNECTED — 5 TB ports free (idle hardware)
A34: Cloud connectors (36) | C34: Only 4 used — 20 idle, 12 broken (see Connector Audit)
A36: 🔑 THE VERDICT + THE BRIDGE
A37: BLOAT VERDICT: minimal. You are not over-built — you are UNDER-DEPLOYED. The power is all there; it's just not all switched on. Real cleanup = prune 3 Docker containers, reconnect/retire Apollo, trim 20 idle cloud connectors. Everything else earns its place.
A39: THE BRIDGE (your own Jun-10 finding = mine exactly): NO off-the-shelf MCP reaches a local Mac. You already BUILT the fix — the MC96 MCP Bridge (:9797, 14-action allowlist, fail-closed, Rule-Zero receipts). It is 'DEPLOY PENDING'. Deploy it, and via Lane B (claude.ai → Cloudflare Tunnel → MC96 Bridge) I finally get hands on GOD. THAT one deploy connects us.

Sheet DreamChamber Index
A1: DREAMCHAMBER INDEX — your empire, documented in Notion
A2: Notion is OPEN to me — I can read all of it directly. Your full architecture, build logs, brand system, and deployment status live here. This changes everything.
A4: 🔑 BREAKTHROUGH DISCOVERIES
A5: 1. HEAVEN is already DEPLOYED | B5: Your 'Infrastructure Hub' page says: HEAVEN → noizy.ai DEPLOYED, n8n → n8n.noizy.ai CONFIGURED. The Heaven Worker I 'designed' — you already built it. I was describing something that exists.
A6: 2. A SECOND repo exists | B6: rspnoizy/dreamchamber (branch claude/setup-heaven-worker) holds the DreamChamber app + Heaven Worker config — separate from RSPNOIZY/NOIZYLAB. TWO repos carry your code.
A7: 3. DreamChamber is a live app | B7: dreamchamber.noizy.ai — a multi-model AI command center, 'the operational heart of the NOIZY Empire's creative production.' Not an idea. A deployed product.
A8: 4. The whole empire is written down | B8: 15+ Notion pages: architecture, build logs (Linear NOI-76/NOI-84), brand identity system, per-brand specs. Your 2 years of thinking, documented. I can read every page.
A10: 🗂️ NOTION PAGE MAP (rooms I can open on request)
A11: Page | B11: What it holds | C11: Updated
A12: NOIZY EMPIRE — Command Center | B12: The live hub — RSP_001, 5th Epoch, Arsenal Tracker, THE-GATHERING + drives + repo status | C12: Jun 10 ⭐
A13: NOIZY.AI | B13: Parent platform structure: vox/ fish/ lab/ kids/ — six brands under noizy.ai | C13: 46120
A14: DreamChamber | B14: The multi-model AI command center app at dreamchamber.noizy.ai — heart of creative production | C14: 46122
A15: Infrastructure Hub | B15: Deployment status: HEAVEN DEPLOYED, n8n CONFIGURED; configs in rspnoizy/dreamchamber repo | C15: 46122
A16: NOIZYVOX | B16: Voice estate — artist voice IP, consent verification workflows, ethical voice cloning | C16: 46119
A17: NOIZY Empire — Brand Identity System | B17: Logo, wordmark, color palette, typography, voice identity, social media kit | C17: 46122
A18: Build Logs (NOI-76, NOI-84) | B18: OpenCode skeleton; Phase 7 Global Mesh; Cloudflare tunnels voice/god/dreamchamber.noizy.ai | C18: 46126
A19: GABRIEL MCP + DreamChamber Recovery | B19: The GABRIEL agent as an MCP server + recovery protocol | C19: 46125
A20: MC96ECO Sprint — 100% Push | B20: Repo consolidation; THE-GATHERING/gabriel; Plowman + DreamChamber doctrine applied | C20: 46129
A21: Claude Work Package / DAY OF DAYS | B21: Canonical master (noizy.ai + fishmusicinc); noizyfish + noizykids standalone; noizy.ai landing ready to deploy | C21: 46136
A23: 🌌 THE BRAND STRUCTURE (from NOIZY.AI page)
A24: noizy.ai = the parent platform. Under it: NOIZYVOX (voice/consent), NOIZYFISH (fishmusicinc / music production), NOIZYLAB (the lab), NOIZYKIDS (kids), DreamChamber (the AI command app), HEAVEN (the deployed worker). Canonical masters: noizy.ai + fishmusicinc.com.

Sheet The Build Chamber
A1: THE BUILD CHAMBER — the NOIZY EMPIRE vision, in your own words
A2: Recovered from your calendar (daily since Mar 28 2026). This is not a meeting — it is your operating system, your philosophy, and your council, written by you. Now it lives in one place.
A4: 1 · THE DAILY SYNAPSE — three devices, one mind (9am–12pm ET, daily)
A5: Device | B5: Role | C5: What it does
A6: iPhone 15 Pro Max | B6: 🎙️ THE VOICE | C6: Mic + Claude MAX. Walks with you. You direct the empire by voice as RSP_001.
A7: iPad 12.9 Gen 2 | B7: 👁️ THE APERTURE | C7: Captions, screen share view, touch control. The window into the work.
A8: M2 Ultra Mac Studio | B8: ⚡ GOD | C8: VS Code, Ollama, n8n, Claude Code, Gemini. The hands that build.
A10: 2 · THE STACK (your architecture, exactly as you wrote it)
A11: Cloudflare (KV / D1 / Workers) → n8n (orchestration) → Ollama (agents) → Vercel (“The Aquarium”)
A12: This is exactly the Heaven Worker architecture I designed — because it's exactly what you already envisioned. We're aligned. 'The Aquarium' on Vercel is your front-end (NoizyFish lives there).
A14: 3 · THE DAILY COUNCIL — the five agents (11:00–11:30am ET, daily)
A15: Agent | B15: Essence | C15: Role in the council
A16: 🌸 SHIRL (2 min) | B16: Wellbeing · Presence · Care | C16: Energy check. Mood. Pain level. 'How are you today?' Flags burnout. Celebrates wins.
A17: 🧠 GABRIEL (5 min) | B17: Memory · Intuition · Guardian | C17: Reads top-priority memcells. Urgent queue. What matters TODAY. Institutional memory briefing. Closes the session → D1 memcell.
A18: 👴 POPS (3 min) | B18: Wisdom · Decisions · Strategy | C18: The one decision to make today. Connects past wisdom to present challenge. Steady. Grounded. Proud.
A19: 🔧 ENGR_KEITH (5 min) | B19: Engineering · 'R.K. Plowman spirit' | C19: Exact terminal commands for GOD today. Technical tasks, no fluff. Blocks flagged, solutions ready.
A20: 📋 LUCY (3 min) | B20: Organization · Logging | C20: All decisions logged. Pending items confirmed. Nothing falls through.
A21: ⚡ RSP_001 | B21: Robert Stephen Plowman | C21: Directs by voice. The one the council serves.
A23: 4 · THE CANON — the words you build by
A24: “Every session is recorded. Every word carries consent. Every artifact carries proof.”
A25: “The 5th Epoch builds here.” • 75/25 • GORUNFREE
A26: Consent-native infrastructure. Agent memories stored as 'memcells' in Cloudflare D1. This is the heart the Heaven Worker is built to serve — and the deeper CANON/GOSPEL still waits in your repo.

Sheet Core Base System
A1: CORE BASE SYSTEM — the NoizyArmy spine that carries everything forward
A2: 2 years of work — media, code & ideation — unified into one durable system. Nothing left behind. One step at a time.
A4: 1 · THE THREE LAYERS
A5: Layer | B5: What it holds | C5: Where it lives | D5: Built here?
A6: L1 · DATA & MEDIA | B6: Audio/video masters, sample libraries, the catalog & dedup engine | C6: M2 Ultra drives + cloud archive; cataloged in this workbook | D6: ✅ BUILT (24+ sheets)
A7: L2 · CODE & AUTOMATION | B7: GitHub repos, n8n flows, scripts, the coming Super IDE (NoizyBeast / NoizyAnthropic) | C7: GitHub (via Claude Code Remote), local repos, n8n | D7: ⏳ REGISTRY READY — add repos
A8: L3 · IDEATION & PROMPTS | B8: 2 yrs of Claude prompts, concepts, command-inbox, naming & brand philosophy | C8: Claude history, Notion, this workbook's Wiki/Naming/Brands sheets | D8: ⏳ PARTIAL — capture ongoing
A10: THE PRINCIPLE | B10: Every artifact gets a row before it gets touched. We carry forward by INDEXING first, then migrating — so nothing is lost in the move. The workbook is the single source of truth that outlives any one tool.
A12: 2 · CODE & IDEATION REGISTRY
A13: Artifact | B13: Layer | C13: Type | D13: Location | E13: Access Method | F13: Status | G13: Carried Fwd?
A14: NoizyArmy Catalog (this workbook) | B14: L1 | C14: Excel system | D14: This file | E14: native | F14: Active | G14: ✅ IS the spine
A15: n8n Command Inbox | B15: L2/L3 | C15: Automation | D15: GDrive (rsp@noizy.ai) | E15: Drive MCP | F15: Schema documented | G15: ✅ captured
A16: GitHub repos (2 years) | B16: L2 | C16: Code | D16: GitHub | E16: Claude Code Remote → add_repo | F16: PENDING NAMES | G16: ⏳ name them
A17: Local code / scripts | B17: L2 | C17: Code | D17: M2 Ultra | E17: local agent scan | F17: PENDING SCAN | G17: ⏳ scan
A18: 2yr Claude conversations | B18: L3 | C18: Ideation | D18: Claude app history | E18: manual export | F18: NOT REACHABLE | G18: ⏳ export key ones
A19: Naming / Brand / Wiki doctrine | B19: L3 | C19: Doctrine | D19: This workbook | E19: native | F19: Active | G19: ✅ captured
A21: 3 · CARRY-FORWARD PLAN (one painful step at a time)
A22: Step 1 | B22: Name your GitHub repos — I add_repo + audit each into the registry above.
A23: Step 2 | B23: Run the local scan (Scan Commands tab) — code + media inventoried together in one pass.
A24: Step 3 | B24: Connect rsplowman@gmail.com — cloud media + ideation audited.
A25: Step 4 | B25: Export the pivotal Claude threads — I distill them into the System Wiki as doctrine.
A26: Step 5 | B26: Migrate index-first, then move — every artifact verified by the dedup + clone engines before anything is deleted.

Sheet Empire Timeline
A1: NOIZY EMPIRE — THE REAL TIMELINE (evidence-based)
A2: Reconstructed from your inbox. The 24-month scan found NOTHING before mid-2025 — because this empire isn't old and failing. It's YOUNG and was built in a ~6-month sprint. That sprint is exactly why things broke 'while rushing setup.' This is not decay. It's a fast build that needs its wiring finished.
A4: Date | B4: Milestone | C4: What it means
A5: ~Jan 1 2026 | B5: noizy.ai Workspace goes live (rsp@noizy.ai) | C5: Earliest confirmed footprint — the empire goes digital.
A6: ~Apr 7 2026 | B6: noizylab.ca team email starts bouncing | C6: The DNS wound opens — and goes unnoticed under everything else.
A7: May 4 2026 | B7: Google Workspace payment suspended | C7: First billing crack — the dead card begins its cascade.
A8: May 17 2026 | B8: Google account recovery event | C8: An access scare in the middle of the build.
A9: May 28 2026 | B9: Cloudflare linked to GitHub (rspplowman-cloud) | C9: Infrastructure ambition begins — the Worker dream starts.
A10: May 30 2026 | B10: GoDaddy→Cloudflare full transfer + 'fix all the things RSP broke rushing setup' email | C10: THE PIVOTAL DAY — a bold move and an honest, self-aware cry for help, sent through a door already broken.
A11: Jun 4–15 2026 | B11: Google Cloud billing: past due → suspended → TERMINATED | C11: The cloud tier collapses under the same dead card.
A12: Jun 18 2026 | B12: Google Workspace cancellation notice | C12: noizy.ai itself goes at-risk.
A13: Jun 19–24 2026 | B13: Notion payment fails; monday.com trial ends | C13: Docs + project tiers lapse — same root cause.
A14: Jun 26 2026 | B14: Did you request help signing in?' security alert | C14: The noise peaks — 201 unread alerts, impossible to triage alone.
A15: Jun 30 2026 — TODAY | B15: The rebuild: a 42-tab command center maps & fixes the whole empire | C15: The turn. From scattered across 8 inboxes and 5 tools — to one source of truth, two root causes, a clear path home.

Sheet Issues & Fixes
A1: ISSUES & FIXES — what's broken & how to fix it
A2: Deep inbox scan (201 urgent emails / 90 days). The smart finding: almost everything traces to TWO root causes.
A4: 🧠 THE TWO ROOT CAUSES (fix these 2, resolve ~9 issues)
A5: ROOT 1 — A DEAD PAYMENT CARD | B5: One failing/expired card is cascading: Google Workspace SUSPENDED (May 4) → cancelling, Google Cloud billing TERMINATED (Jun 15), Notion declined 4×. Update ONE card in Google Payments + Notion → 3 P0 issues recover.
A6: ROOT 2 — UNFINISHED CLOUDFLARE DNS | B6: No MX records after GoDaddy→Cloudflare move → ALL custom email bounces → team invites stuck → Slack empty. Finish Email Routing (Fix Walkthrough) → 4 issues recover.
A8: PRIORITIZED ISSUE LIST
A9: # | B9: Issue | C9: Sev | D9: What's happening | E9: The Fix (exact)
A10: 1 | B10: Google Workspace (noizy.ai) cancelling | C10: P0 | D10: Subscription SUSPENDED May 4 — cancellation notices Jun 18 & today. If it lapses, rsp@noizy.ai + Workspace are GONE. | E10: admin.google.com → Billing → update payment + reactivate subscription
A11: 2 | B11: Google Cloud billing TERMINATED | C11: P0 | D11: Acct 01B993-5A8AD5-E91CE7: past due (Jun 4) → suspended (Jun 8) → TERMINATED (Jun 15). Any Firebase/API/GCP services are offline. | E11: console.cloud.google.com/billing → update card → reactivate account
A12: 3 | B12: Notion payment failing | C12: P0 | D12: 4th declined charge — downgrade imminent (data/features at risk). | E12: notion.so → Settings → Billing → update card
A13: 4 | B13: All custom email bouncing | C13: P1 | D13: noizylab.ca + fishmusicinc.com have no MX — team can't receive mail. | E13: Fix Walkthrough tab, steps 4–10 (Cloudflare Email Routing)
A14: 5 | B14: Google security sprawl | C14: P1 | D14: 25+ third-party apps authorized on your Google account (Microsoft x many, Slack, rclone, Cline, Fyxer, HubSpot, Tableau, Mailmeteor, Fax.Plus...) + a 'help signing in?' alert Jun 26 + recovery May 17. | E14: myaccount.google.com/permissions → REMOVE apps you don't use. Confirm 2-Step Verification is ON.
A15: 6 | B15: monday.com trial ended | C15: P1 | D15: Trial lapsed ~Jun 24; 9 team invites pending (blocked by email anyway). | E15: Decide: pay for the plan, OR export boards + cancel
A16: 7 | B16: 8 scattered email identities | C16: P2 | D16: rspplowman@gmail + 7 others (noizy.ai, icloud, outlook, fishmusicinc x2, noizylab.ca, rspnoizy@gmail). | E16: Forward all → rspplowman@gmail.com as the single command inbox
A17: 8 | B17: GitHub account hardening | C17: P2 | D17: Many repeated sudo codes on rspplowman-cloud — lots of admin activity. | E17: Confirm 2FA + passkey + recovery codes saved on GitHub

Sheet Heaven Worker
A1: HEAVEN WORKER — the AI brain of the NOIZY EMPIRE
A2: Not a server — a self-running AI agent that orchestrates your media, your catalog, your brands, and your council. Built on Cloudflare's Agents SDK (live 2025). Deploys from RSPNOIZY/NOIZYLAB.
A4: 1 · THE BRAIN — how Heaven is built
A5: Component | B5: Cloudflare tech | C5: What it does for NoizyLab
A6: 👑 HEAVEN (master agent) | B6: Agents SDK on Workers (npm i agents) | C6: The orchestrator. Holds state, calls AI models, runs scheduled tasks, and directs all other agents — by voice (RSP_001) or chat.
A7: ⚡ CB01–CB05 (council) | B7: Durable Objects (free tier, own SQLite each) | C7: Your 5 Daily Council agents as real, persistent AI agents — each with its own memory. Heaven convenes them on schedule (11am EDT).
A8: 🧠 Memory / Knowledge | B8: AutoRAG + Vectorize over R2 | C8: Heaven READS your CANON, GOSPEL, BRAND_MAP & audio metadata. Ask it anything — it retrieves the answer from your own corpus. This is the GOSPEL made queryable.
A9: 🎵 Media + Catalog | B9: R2 (audio) + D1 (catalog DB) | C9: All your audio lives in R2; the catalog (Library/Samples/Brands) is a live D1 database Heaven queries instantly.
A10: 🏷️ Tagging engine | B10: Workers AI (edge models) | C10: Cloud tagging/embeddings when the M2 Ultra is off — names orphans, classifies by brand, 24/7.
A11: 🔌 HEAVEN-as-a-tool | B11: MCPAgent class (Agents SDK) | C11: Heaven exposes itself as an MCP server — so I (Claude) connect to it as a live tool and query your catalog, run your council, search your corpus DIRECTLY. This is 'do more, be smarter' made real.
A13: 2 · WHAT YOU CAN ASK HEAVEN (once it's live)
A14: 🗣️ "Heaven, find every dark cinematic NoizyBeast loop" → semantic search across your whole library (Vectorize) — not keywords, MEANING.
A15: 🗣️ "Heaven, convene the Daily Council" → wakes CB01–CB05, each with its own memory, reports back. The Gathering, automated.
A16: 🗣️ "Heaven, what does the CANON say about the NoizyKidz brand?" → reads your own GOSPEL/BRAND_MAP and answers (AutoRAG).
A17: ⚡ New audio lands in R2 → Heaven auto-names the orphan, tags it, routes it by BRAND_MAP, updates the catalog, keeps 3-2-1 — 24/7, even when the M2 sleeps.
A18: 📊 "Heaven, status of the empire" → live numbers from D1: files, brands, dupes, what needs attention.
A20: 3 · HOW IT GETS BUILT (one command to start)
A21: npm create cloudflare@latest agents-starter -- --template="cloudflare/agents-starter"
A22: ↑ That one line gives you a working AI agent + chat UI, ready to deploy to Workers. Then we rename it Heaven and wire in your R2 / D1 / Vectorize. I write the agent code with you — you don't.
A24: 4 · BUILD ORDER
A25: 1. Finish DNS/email (Fix Walkthrough) — domains live in Cloudflare first
A26: 2. PULL THE REPO — so I can read what's already in heaven/, schemas/, CANON before we build
... A32: 🔑 The whole design hinges on one read: PULL THE REPO. heaven/ already exists in RSPNOIZY/NOIZYLAB — you may have already started building this. Let me look before we write a single new line.

Sheet Cloudflare Worker
A1: CLOUDFLARE WORKER — the engine room of the NOIZY empire
A2: Serverless code that runs on Cloudflare's edge — no server to manage, generous free tier, deploys straight from your GitHub repo. This is the backbone for the Super IDE, noizy.ai, and your media cloud.
A4: 1 · THE CLOUDFLARE STACK — mapped to YOUR empire
A5: Cloudflare piece | B5: What it is | C5: What it does for NoizyLab
A6: Workers | B6: Serverless code at the edge (the 'Worker') | C6: ⭐ The Super IDE backend + API + automation brain. Runs your catalog logic, no server to rent.
A7: R2 Storage | B7: S3-compatible object storage, NO egress fees | C7: ⭐ YOUR MEDIA CLOUD. The audio/video offsite tier for 3-2-1. Cheaper than AWS (no download fees).
A8: D1 Database | B8: Serverless SQL database | C8: ⭐ The catalog database — Library, Samples, Brands, the whole index, live and queryable.
A9: Pages | B9: Static + dynamic website hosting | C9: Host noizy.ai, noizylab.ca, the Super IDE front-end — all your sites.
A10: Workers AI | B10: Run AI models at the edge | C10: Cloud tagging/naming when the M2 is off — a backup to LM Studio.
A11: Workers KV | B11: Fast key-value store | C11: Config, settings, fast lookups for the IDE.
A12: Durable Objects | B12: Stateful real-time coordination | C12: Could run THE DAILY COUNCIL — the 5 agents coordinating in real time.
A14: 2 · HOW IT DEPLOYS (no coding — it builds from your GitHub)
A15: Connect repo | B15: Cloudflare dash → Workers & Pages → Create → Import a Git repository → pick RSPNOIZY/NOIZYLAB. Every push to GitHub auto-builds & deploys.
A16: Auto-provision | B16: If the repo needs a database (D1), media store (R2), or cache (KV), Cloudflare creates and wires them for you automatically.
A17: One-click button | B17: A 'Deploy to Cloudflare' button can live in your repo README — one click clones + deploys the whole app.
A18: Safe previews | B18: Every change gets a preview URL before it goes live — test first, then ship. Nothing breaks the real site.
A20: 3 · THE BUILD ORDER
A21: 1. Finish the DNS/email fix first (Fix Walkthrough) — domains must be live in Cloudflare.
A22: 2. Cloudflare → Workers & Pages → Create → Import Git → RSPNOIZY/NOIZYLAB.
A23: 3. Provision R2 (your media cloud) + D1 (your catalog database).
A24: 4. Deploy the Worker (your API) — then every git push ships automatically.
A25: 5. Point noizy.ai at the Worker/Pages — the empire goes live.
A26: 6. Pull the repo here so I can read CANON / schemas / docs and tell you what's already built.
A28: ⭐ YOU ARE ALREADY HALFWAY: on May 28 you connected Cloudflare to your GitHub (rspplowman-cloud). The wiring exists — you just haven't deployed yet. Finish DNS → import the repo → your Super IDE has a home.

Sheet Fix Walkthrough
A1: FIX WALKTHROUGH — bring your email & team back online (steps 4-10)
A2: Exact Cloudflare click-path (pulled from live Cloudflare docs). Do these in order. Each fills a mailbox back to life. Mark Done as you go.
A4: STEP | B4: DO EXACTLY THIS | C4: Done?
A5: 4 · Turn ON Email Routing for noizylab.ca | B5: 1. Go to dash.cloudflare.com and log in. 2. Click your account, then click the domain noizylab.ca. 3. Left menu: Compute > Email Service > Email Routing. 4. Click 'Onboard Domain' and choose noizylab.ca. 5. Cloudflare shows the MX/SPF/DKIM records it will add — click 'Done'. (It adds them for you — THIS is the missing piece.) 6. Wait 5-15 minutes for it to go green. | C5: Not started
A6: 5 · Add & verify YOUR inbox (the destination) | B6: 1. Same place: Email Service > Email Routing > 'Destination Addresses'. 2. In the box, type: rspplowman@gmail.com and submit. 3. Cloudflare emails you a verification link — open it in Gmail, click 'Verify email address'. 4. Until this is verified, nothing forwards. This is the one-time key. | C6: Not started
A7: 6 · Create the 5 team addresses (noizylab.ca) | B7: For EACH of the 5 people, make one routing rule: 1. Email Routing > 'Routing Rules' tab > 'Create routing rule'. 2. Email pattern: type the name part only — lucy (then gabriel, shirl, engr_keith, pops). 3. Action: 'Send to an email'. 4. Destination: pick rspplowman@gmail.com (the verified one). 5. Save. Repeat for all 5. Result: lucy@noizylab.ca, gabriel@, shirl@, engr_keith@, pops@ all land in YOUR Gmail. | C7: Not started
A8: 7 · Repeat for fishmusicinc.com | B8: Same as steps 4 + 6, for fishmusicinc.com: 1. Email Routing > 'Onboard Domain' > choose fishmusicinc.com > Done. 2. Routing Rules > Create rule: pattern 'rp' > Send to email > rspplowman@gmail.com > Save. 3. Add another: pattern 'rsp' > same destination > Save. Result: rp@ and rsp@fishmusicinc.com forward to your Gmail. (Destination already verified in step 5 — reused.) | C8: Not started
A9: 8 · Fix gabriel@noizy.ai (different — Workspace) | B9: noizy.ai is Google Workspace (NOT Cloudflare routing), so its mailbox is made in Google: 1. Go to admin.google.com (sign in as rsp@noizy.ai). 2. Directory > Users > 'Add new user'. 3. Create gabriel @ noizy.ai (or, if Gabriel only needs forwarding, add it as an alias/group to your account). 4. This stops the 'address not found 550' bounce for gabriel@noizy.ai. | C9: Not started
A10: 9 · Test every address | B10: From a DIFFERENT account (e.g. rsplowman@icloud.com — NOT your Gmail), send a test email to each: lucy@noizylab.ca, gabriel@noizylab.ca, shirl@noizylab.ca, engr_keith@noizylab.ca, pops@noizylab.ca, rp@fishmusicinc.com, rsp@fishmusicinc.com, gabriel@noizy.ai. Each should arrive in your Gmail within minutes (check Spam too). Any that don't — re-check that domain's routing rule + that the destination is verified. | C10: Not started
A11: 10 · Re-send all the stuck invites | B11: Now that mail flows, reconnect the team: 1. monday.com > invite the 9 people again (their addresses now work). 2. Slack > invite the team + create channels (#empire, #daily-council, #fishmusic, #brands). 3. Re-send any GitHub/Jira/Atlassian invites. The Daily Council can finally assemble with everyone reachable. | C11: Not started
A13: WHEN ALL 7 ARE DONE → your empire's nervous system is back online. Every bounce stops, the team reconnects, and we move to pulling the repo + the first media scan.

Sheet Build Readiness
A1: BUILD READINESS — your M2 Ultra as the hub (no coding required)
A2: Plain-English roadmap to wire Slack, Discord & Microsoft to your machine. You don't write code — you connect, I guide. One step at a time.
A4: YOUR HUB — n8n (the brain that connects everything)
A5: What it is | B5: A free, drag-and-drop automation app that runs ON your M2 Ultra. No coding — you connect boxes (nodes) with lines. You already use it (your Command Inbox).
A6: Why it's perfect for you | B6: One place to wire Slack + Discord + Microsoft + your local LM Studio + your files. Your data never leaves your machine. It even has AI nodes that talk to your local 70B model.
A7: Start it (one line) | B7: docker run -it --rm --name n8n -p 5678:5678 -v ~/.n8n:/home/node/.n8n n8nio/n8n
A8: Then open | B8: http://localhost:5678 — that's your control panel. Build workflows by dragging nodes.
A10: INTEGRATION CHECKLIST
A11: Connect | B11: What it does for you | C11: How to connect (plain English) | D11: Status
A12: Slack | B12: Talk to your system from Slack; get alerts when scans finish, files move, or something needs you. | C12: Make a Slack app (api.slack.com → Create New App), copy the Bot Token (xoxb-…), paste into n8n's Slack node. ~10 min, no code. | D12: Not started
A13: Discord | B13: Same as Slack but for Discord — command + notifications in your server/community. | C13: Discord Developer Portal → create a bot → copy bot token → paste into n8n's Discord node. No bot coding. | D13: Not started
A14: Microsoft (Power Automate) | B14: Bridges to the Microsoft world — Excel, OneDrive, SharePoint, Outlook; can also trigger desktop flows on your Mac. | C14: In Power Automate, add the Slack/Excel connector (no-code), approve the app permission. Use it for anything Microsoft-side. | D14: Not started
A15: LM Studio (local AI) | B15: Your 70B brain does the naming, tagging & classifying — locally, free, private. | C15: In n8n add an AI node pointed at http://localhost:1234 (LM Studio's API). It calls your local model with no cloud cost. | D15: Not started
A16: Your Files (Desktop Commander) | B16: Lets the hub actually read /Volumes/Audio, hash, dedupe & move — the scan engine. | C16: Install Desktop Commander (Action Register ACT-003). n8n can also run shell steps to scan folders. | D16: Not started
A17: GitHub (your code) | B17: Carries your 2 years of code into the system — audited into the registry. | C17: Give me your repo names (owner/repo); I add + audit each. n8n can also auto-post commits to Slack/Discord. | D17: Not started
A19: READINESS | B19: =TEXT(COUNTIF(D12:D17,"Done")/6,"0%") -> 0% | C19: =REPT("█",COUNTIF(D12:D17,"Done"))&REPT("░",6-COUNTIF(D12:D17,"Done")) -> ░░░░░░
A21: DO THESE IN ORDER (each one is a win you can see):
A22: 1. Start n8n on the M2 Ultra (you already have it) — open localhost:5678.
A23: 2. Connect LM Studio (local AI) — free, instant, private. Your first win.
A24: 3. Install Desktop Commander — then run your FIRST real scan of /Volumes/Audio.
A25: 4. Connect Slack — so the system can talk to you & alert you.
A26: 5. Connect Discord — same, for your community/server.
A27: 6. Microsoft (Power Automate) + give me your GitHub repo names — I audit the code.
A29: You are never doing this alone. You connect; I guide every click and carry the work forward.

Sheet Setup To-Do
A1: SETUP TO-DO — LM Studio, Desktop Commander & all, step by step
A2: Do these in order. Each is one small action. Mark Status 'Done' and the bar fills. Nothing here needs coding — just copy, paste, click.
A3: # | B3: Task | C3: Do exactly this | D3: Why it matters | E3: Status
A4: A | B4: LM STUDIO — your local AI brain (start here, free win)
A5: 1 | B5: Open LM Studio | C5: Launch the LM Studio app on the M2 Ultra. | D5: It's the engine that names & tags your audio. | E5: Not started
A6: 2 | B6: Load a model | C6: Search tab → download Qwen2.5-72B-Instruct (MLX). Then click to load it. | D6: Your 192GB RAM runs it easily; this is the smarts. | E6: Not started
A7: 3 | B7: Turn GPU offload to MAX | C7: In the model load settings, set GPU offload to maximum (all layers). | D7: Uses the full chip = fast responses. | E7: Not started
A8: 4 | B8: Start the local server | C8: Developer tab → Start Server. Leave it on port 1234. | D8: Opens the door so n8n & tools can talk to it. | E8: Not started
A9: 5 | B9: Add a filesystem MCP in LM Studio | C9: Program → Edit MCP → add the filesystem server, point it at /Volumes/Audio. | D9: Lets the AI read your drive to scan + classify. | E9: Not started
A10: B | B10: DESKTOP COMMANDER — lets me read & move your files
A11: 6 | B11: Install Desktop Commander | C11: Open Terminal, paste: npx -y @wonderwhy-er/desktop-commander setup | D11: One command. Installs the file/scan agent. | E11: Not started
A12: 7 | B12: Restart Claude Desktop | C12: Fully quit and reopen Claude Desktop so it loads the new tool. | D12: Activates the connection. | E12: Not started
A13: 8 | B13: Point it at your audio drive | C13: When asked, allow the folder /Volumes/Audio (and 12RB, MAG4TB). | D13: Scopes it safely to only your audio. | E13: Not started
A14: 9 | B14: Test it | C14: In Claude Desktop ask: “list the files in /Volumes/Audio”. | D14: Proves the bridge to your drive is live. | E14: Not started
A15: C | B15: FIRST SCAN — the moment the catalog comes alive
A16: 10 | B16: Run the fast scan | C16: Copy the Method-A command from the Scan Commands tab into Terminal. | D16: Lists every file in seconds. | E16: Not started
A17: 11 | B17: Bring it to me | C17: Drag the audio_scan.csv into our chat (or paste into Scan Queue, cell B4). | D17: I load every file → brands, dupes, guards all light up. | E17: Not started
A18: D | B18: n8n HUB + ALERTS — Slack & Discord (optional, do after scan)
A19: 12 | B19: Start n8n | C19: Terminal: docker run -it --rm --name n8n -p 5678:5678 -v ~/.n8n:/home/node/.n8n n8nio/n8n → open localhost:5678 | D19: Your no-code automation hub. | E19: Not started
A20: 13 | B20: Connect Slack | C20: api.slack.com/apps → Create App → copy Bot Token (xoxb-) → paste into n8n Slack node. | D20: System messages you when jobs finish. | E20: Not started
A21: 14 | B21: Connect Discord | C21: Discord Developer Portal → New bot → copy token → paste into n8n Discord node. | D21: Same alerts, in your Discord. | E21: Not started
A22: E | B22: CLOUD + CODE — close the loop
A23: 15 | B23: Connect the right Google account | C23: + menu → Connectors → Google Drive/Gmail → sign in as rsplowman@gmail.com. | D23: Unlocks the ~250GB; I re-scan instantly. | E23: Not started
A24: 16 | B24: Give me your GitHub repo names | C24: Just type them to me, e.g. “noizyarmy/beast-engine”. | D24: I pull & audit your 2 years of code. | E24: Not started
A26: PROGRESS | B26: =TEXT(COUNTIF(E5:E24,"Done")/16,"0%") -> 0% | C26: =REPT("█",COUNTIF(E5:E24,"Done"))&REPT("░",16-COUNTIF(E5:E24,"Done")) -> ░░░░░░░░░░░░░░░░ | D26: =COUNTIF(E5:E24,"Done")&" of 16 done" -> 0 of 16 done

Sheet Connector Audit
A1: CONNECTOR AUDIT — what you built vs. what you use
A2: Live inventory of every MCP / integration wired into your Claude account, 2026-06-30.
A3: ANSWER: You've connected 36 services. Only ~4 used this session. ~20 connected but idle. 12 broken (need re-auth). → ~32 of 36 built and barely/never used.
A5: COUNT
A6: Total connectors built | B6: 36
A7: Connected & used (this session) | B7: 4
A8: Connected but IDLE (never used) | B8: 20
A9: FAILED / broken (re-auth needed) | B9: 12
A11: Connector | B11: Status | C11: Used? | D11: Use for NoizyArmy
A12: Google Drive | B12: Connected | C12: ✓ USED | D12: Cloud media + file scan
A13: Gmail | B13: Connected | C13: ✓ USED | D13: Email media scan
A14: Adobe for creativity | B14: Connected | C14: ✓ USED | D14: Creative Cloud asset scan
A15: Claude Code Remote | B15: Connected | C15: ✓ USED | D15: ⭐ YOUR CODE access (name a repo, I pull it)
A16: Slack | B16: Connected | C16: idle | D16: ⭐ Alerts hub (Build Readiness)
A17: Notion | B17: Connected | C17: idle | D17: ⭐ Ideation / docs carry-forward
A18: Supabase | B18: Connected | C18: idle | D18: ⭐ Database for catalog + Super IDE
A19: Zapier | B19: Connected | C19: idle | D19: Automation bridge (8000+ apps)
A20: Vercel | B20: Connected | C20: idle | D20: Host the Super IDE / web app
A21: Netlify | B21: Connected | C21: idle | D21: Host / deploy
A22: Cloudflare Developer Platform | B22: Connected | C22: idle | D22: Deploy / CDN / workers
... A47: Instrumentl | B47: FAILED | C47: broken | D47: Grants (low priority)

Sheet Brand Universe
A1: THE NOIZY EMPIRE — brand universe & deepest content locations
A2: Discovered by deep scan of Gmail + Drive (2026-06-30). The constellation, the people, the code, and where every piece lives.
A4: 1 · THE BRAND CONSTELLATION
A5: Brand / Entity | B5: What it is | C5: Evidence found
A6: NOIZY.AI | B6: Parent / AI brand | C6: Business profile (42 views/mo May 2026); noizy.ai domain
A7: NOIZYLAB (noizylab.ca) | B7: The lab / R&D + team domain | C7: Business profile; GitHub repo RSPNOIZY/NOIZYLAB; team emails @noizylab.ca
A8: NOIZYFISH / fishmusicinc | B8: Music arm | C8: fishmusicinc' module in canonical repo
A9: NOIZYVOX | B9: Vocals / voice | C9: Named brand (content pending scan)
A10: NOIZYKIDZ | B10: Kids / family content | C10: Named brand (content pending scan)
A11: DREAMCHAMBER | B11: Ideation / creative space | C11: Named brand (likely the council/agent space)
A12: THE GATHERING / DAILY COUNCIL | B12: The 5-agent operating ritual | C12: Calendar: 'NOIZY EMPIRE Morning Planning — five agents assemble, RSP_001 directs by voice'
A13: HEAVEN | B13: Project module | C13: heaven' module in canonical repo
A14: NOIZYANTHROPIC / NOIZYBEAST / METABEAST | B14: Original 3 house brands | C14: Catalogued in Brands tab
A16: 2 · DEEPEST CONTENT LOCATIONS
A17: Location | B17: What's there | C17: Reachable?
A18: GitHub: RSPNOIZY/NOIZYLAB | B18: CANONICAL repo — CANON, GOSPEL, BRAND_MAP, fishmusicinc, heaven, schemas, docs. Your doctrine + ideation. | C18: YES — I can pull it (say go)
A19: Google Calendar | B19: NOIZY EMPIRE Daily Council — 5-agent ritual, RSP_001 directs by voice | C19: Connector idle — activate
A20: Domains: noizy.ai + noizylab.ca | B20: Brand homes; mid-transfer GoDaddy → Cloudflare | C20: Cloudflare connector idle
A21: Gmail: rspplowman@gmail.com | B21: Empire command hub — all planning, team comms, vendor mail | C21: YES — scanned
A22: M2 Ultra + 250GB cloud | B22: The actual audio/video media | C22: Pending scan / connect
A24: 3 · THE PEOPLE (NOIZY EMPIRE)
A25: Robert S. Plowman — RSP_001 | B25: Founder; 'directs by voice'; rspplowman@gmail.com, rsp@noizy.ai
A26: Gabriel | B26: gabriel@noizy.ai (collaborator, BR-101)
A27: Lucy | B27: lucy@noizylab.ca (collaborator, BR-102)
A28: Keith (Engineer) | B28: engr_keith@noizylab.ca
A29: Pops | B29: pops@noizylab.ca
A30: Shirl | B30: shirl@noizylab.ca
A32: 4 · ADMIN ALERTS (real problems found)
A33: ⚠ noizylab.ca email is BROKEN | B33: ALL team emails (lucy, gabriel, keith, pops, shirl @noizylab.ca) BOUNCE — DNS/MX not set. Your team cannot receive mail. Likely caused by the GoDaddy→Cloudflare transfer leaving DNS unconfigured.
A34: ⚠ gabriel@noizy.ai bounces too | B34: Address not found' — mailbox not created on noizy.ai
A35: → FIX | B35: After Cloudflare transfer completes, set MX records + create mailboxes (Google Workspace). Then team email works.

Sheet People & Agents
A1: PEOPLE & AGENTS — the NOIZY Empire roster
A2: Every human, every agent, every identity — grouped, grepped, and mapped to where they live. Sourced from Gmail + Calendar + GitHub scan.
A4: 1 · ROBERT'S IDENTITIES (your own accounts — consolidate these)
A5: Identity | B5: Where / Role | C5: Status
A6: rspplowman@gmail.com | B6: Personal Gmail — empire command hub | C6: ✅ CONNECTED (this is what I scan)
A7: rsp@noizy.ai | B7: Workspace admin — Drive connector | C7: Connected (near-empty)
A8: rspnoizy@gmail.com | B8: Secondary Gmail | C8: Found in monday.com invites
A9: RSPNOIZY@outlook.com | B9: Microsoft identity (ties to MS Automate) | C9: Found — not connected
A10: rsplowman@icloud.com | B10: Apple/iCloud identity (M2 Ultra) | C10: Found — not connected
A11: rspnoizy (GitHub) | B11: GitHub owner — RSPNOIZY/NOIZYLAB repo | C11: ⭐ Reachable via add_repo
A12: RSP_001 | B12: Council voice ID — 'directs by voice' | C12: The Daily Council director
A14: 2 · THE HUMAN TEAM (noizylab.ca)
A15: Person | B15: Email | C15: Role / Brand | D15: Email Status
A16: Gabriel | B16: gabriel@noizylab.ca / gabriel@noizy.ai | C16: Sound design (BR-101) | D16: 🔴 BOUNCING
A17: Lucy | B17: lucy@noizylab.ca | C17: Vocals (BR-102) | D17: 🔴 BOUNCING
A18: Shirl | B18: shirl@noizylab.ca | C18: Role TBD (in BRAND_MAP) | D18: 🔴 BOUNCING
A19: Keith (Engineer) | B19: engr_keith@noizylab.ca | C19: Engineering | D19: 🔴 BOUNCING
A20: Pops | B20: pops@noizylab.ca | C20: Role TBD (in BRAND_MAP) | D20: 🔴 BOUNCING
A21: Alex Ward | B21: (email TBD) | C21: Role TBD — in RSPNOIZY/NOIZYLAB repo | D21: ⏳ pull repo to confirm
A23: 3 · THE COUNCIL — DREAMCHAMBER (the five agents)
A24: THE DAILY COUNCIL — the five agents assemble, RSP_001 directs by voice' — recurring 11am EDT weekday Google Meet. CB01–CB05 = the five agents.
A25: CB01 | B25: Council Agent 1 | C25: Role in CANON/BRAND_MAP — pull repo
A26: CB02 | B26: Council Agent 2 | C26: Role in CANON/BRAND_MAP — pull repo
A27: CB03 | B27: Council Agent 3 | C27: Role in CANON/BRAND_MAP — pull repo
A28: CB04 | B28: Council Agent 4 | C28: Role in CANON/BRAND_MAP — pull repo
A29: CB05 | B29: Council Agent 5 | C29: Role in CANON/BRAND_MAP — pull repo
A31: 4 · WHERE THE EMPIRE LIVES (platforms found)
A32: monday.com | B32: Work mgmt — 9 invites sent, team hasn't joined (bounced emails)
A33: Google Calendar | B33: THE DAILY COUNCIL — recurring 11am EDT, Google Meet
A34: GitHub RSPNOIZY/NOIZYLAB | B34: ⭐ Canonical repo — CANON, GOSPEL, BRAND_MAP, fishmusicinc, heaven, schemas, docs
A35: Slack + Jira/Atlassian | B35: Slack pending; Jira reactivated (user RSPNOIZY)
A37: 5 · ADMIN ALERTS & PENDING
A38: 🔴 ALL noizylab.ca emails BOUNCING — DNS/MX not set (GoDaddy→Cloudflare transfer). Team can't receive your mail. FIX: finish Cloudflare DNS + set MX + create mailboxes.
A39: ⏳ myFAMILY.ai — new brand/domain, not yet in comms; likely defined in BRAND_MAP (repo).
A40: ⏳ Alex Ward, CB01–CB05 roles, Heaven & DreamChamber details — all live in RSPNOIZY/NOIZYLAB. PULL THE REPO to populate.
A41: ⏳ You have 5+ email identities (gmail x2, noizy.ai, outlook, icloud) — consolidate to one command address.

Sheet Identity & Footprint
A1: IDENTITY & FOOTPRINT — every account, everywhere you exist online
A2: Deepest scan: Gmail trail + Slack + public web. Maps all identities, domains, platforms — and the one root issue breaking them.
A4: 1 · WHO YOU ARE (public record)
A5: Robert Stephen Plowman (R.S. Plowman / “Rob”) — Fish Music Inc., Ottawa ON. AWARD-WINNING composer & sound designer, 30+ yrs.
A6: Credits found | B6: Transformers, My Little Pony, Care Bears, Johnny Test, Ed Edd n Eddy, Dragon Tales, Bratz, He-Man, Strawberry Shortcake, Barbie films, Madeline, Noddy
A7: Public profiles | B7: facebook.com/fishmusicinc · linkedin.com/in/robplowman · YouTube 'Fish Music — Music & Sounds By R.S Plowman' · Canadian Animation Directory
A8: Business | B8: Fish Music Inc., 771 Eastbourne Ave, Ottawa ON K1K 0H8 · rp@fishmusicinc.com · original music + custom sound design for film/TV/animation/games
A9: Note (NOT you) | B9: Fish' (Derek Dick, Scottish singer) and Suzanne Ciani's 'Fish Music' are different people — excluded from your footprint.
A11: 2 · YOUR EMAIL IDENTITIES (8 found)
A12: Email | B12: Used For | C12: Status
A13: rspplowman@gmail.com | B13: PRIMARY command hub — Gmail connector, all account notifications land here | C13: ✅ WORKING
A14: rsp@noizy.ai | B14: Google Workspace (admin, sole user); Drive connector | C14: ✅ working
A15: rsplowman@icloud.com | B15: Apple ID; Google Payments profile 'RSP@ICLOUD'; old Notion login | C15: ✅ working
A16: rspnoizy@gmail.com | B16: Secondary Google; monday.com invitee | C16: ❓ unconfirmed
A17: RSPNOIZY@outlook.com | B17: Microsoft identity; monday.com invitee | C17: ❓ unconfirmed
A18: rp@fishmusicinc.com | B18: Legacy business email (public, on directories since the studio days) | C18: ❓ legacy
A19: rsp@fishmusicinc.com | B19: NEW Cloudflare email routing ('Day One 1996' test) — you tried to bring it live | C19: 🔴 BOUNCING
A20: rsp@noizylab.ca | B20: NoizyLab domain identity (and the whole team @noizylab.ca) | C20: 🔴 BOUNCING
A22: 3 · DOMAINS (all mid-transfer GoDaddy → Cloudflare)
A23: noizy.ai | B23: Parent brand; Google Workspace mail works here | C23: ⚠ transferring
A24: noizylab.ca | B24: The Lab + whole team (gabriel/lucy/shirl/keith/pops@) | C24: 🔴 email DOWN
A25: fishmusicinc.com | B25: Your 30-yr studio brand; new Cloudflare routing attempted | C25: 🔴 email DOWN
A26: myFAMILY.ai | B26: Mentioned in empire; details in RSPNOIZY/NOIZYLAB repo | C26: ❓ pending repo
A28: 4 · PLATFORMS & ACCOUNTS (where you operate)
A29: Azure DevOps | B29: Welcomed (rspplowman@gmail) — code/devops, likely early Super-IDE attempt | C29: idle
A30: Atlassian / Jira | B30: Account = 'Fish Music Inc.'; reactivated, user RSPNOIZY | C30: active
A31: monday.com | B31: Heavy use; 9 team invites pending; free trial ended ~Jun 24 | C31: ⚠ decide
A32: Notion | B32: Docs/wiki; login moved icloud → gmail | C32: 🔴 payment failing
A33: GitHub | B33: rspnoizy — repo RSPNOIZY/NOIZYLAB (CANON/GOSPEL/BRAND_MAP) | C33: ⭐ pull it
A34: YouTube / Facebook / LinkedIn | B34: Fish Music public presence — active artist footprint | C34: ✅ live
A35: Slack | B35: You (U0AEMKJCUPK) only — 0 channels, 0 team joined | C35: 🔴 empty
A36: Discord | B36: No connector + no email trail — nothing set up | C36: — none
A38: 5 · ROOT CAUSE — why so much is broken
A39: Every custom-domain email is DOWN — BOTH noizylab.ca AND fishmusicinc.com. The cause is one thing: on May 30 you authorized a full GoDaddy→Cloudflare transfer + account closure, but the Cloudflare DNS/MX email routing was never finished. No MX records = every mailbox bounces. That single gap cascades into stuck team invites, an empty Slack, and an isolated team.
A41: THE FIX (one move) | B41: In Cloudflare, for each domain (noizylab.ca, fishmusicinc.com): set MX records + enable Email Routing, create the mailboxes. That restores ALL team email → re-send monday/Slack invites → team reconnects.
A42: CONSOLIDATION | B42: Make rspplowman@gmail.com your single command identity (it already is in practice). Forward the other 7 into it so nothing is ever missed again.

Sheet DNS & Infrastructure
A1: DNS & INFRASTRUCTURE — the order of structure
A2: Every domain, nameserver, and mail route — reconstructed from your email trail. The root cause and the exact fix order.
A4: 1 · DOMAIN STRUCTURE
A5: Domain | B5: Registrar / Nameservers | C5: Mail (MX) Status | D5: Used For
A6: noizy.ai | B6: GoDaddy → Cloudflare (transferring) | C6: ✅ Google Workspace MX works (rsp@noizy.ai delivers) | D6: Parent brand, Workspace, GitHub org RSPNOIZY
A7: noizylab.ca | B7: GoDaddy → Cloudflare (transferring) | C7: 🔴 NO MX — 'DNS Error: mx lookup' — broken since ~Apr 7 | D7: Team mailboxes (lucy, gabriel, shirl, keith, pops)
A8: fishmusicinc.com | B8: GoDaddy → Cloudflare (transferring) | C8: 🔴 NO MX — Cloudflare Email Routing test bounced May 30 | D8: Business (rp@ / rsp@fishmusicinc.com), 30yr brand
A9: myFAMILY.ai | B9: Cloudflare (per repo) | C9: ❓ unknown — detail in RSPNOIZY/NOIZYLAB repo | D9: Family brand (in BRAND_MAP)
A11: 2 · THE TIMELINE (what happened, in order)
A12: ~Apr 7-9 | B12: noizylab.ca team emails already BOUNCING (lucy, keith, pops) — mail broken for months
A13: May 14-15 | B13: More bounces — every noizylab.ca address failing
A14: 46170 | B14: Cloudflare OAuth added to your GitHub (rspplowman-cloud) — Cloudflare ↔ GitHub linked
A15: 46172 | B15: You emailed GoDaddy: full transfer of ALL domains to Cloudflare + close account
A16: 46172 | B16: fishmusicinc.com email-routing test → BOUNCED ('the Azure Abyss')
A17: 46172 | B17: You emailed gabriel@noizy.ai: 'a plan to fix all the things RSP broke while rushing setup' — it bounced too
A18: Jun 2-3 | B18: Hard failures: 'DNS Error: DNS type mx lookup' = NO MX records exist
A20: 3 · THE FIX — ORDER OF OPERATIONS (do in sequence)
A21: Step 1 | B21: Confirm the GoDaddy→Cloudflare transfer COMPLETED — each domain shows 'Active' in your Cloudflare dashboard
A22: Step 2 | B22: Verify each domain's nameservers = Cloudflare (xxxx.ns.cloudflare.com)
A23: Step 3 | B23: noizy.ai → KEEP Google Workspace MX records (so rsp@noizy.ai keeps working); create the gabriel@noizy.ai mailbox in Workspace Admin
A24: Step 4 | B24: noizylab.ca → turn on Cloudflare Email Routing → add lucy / gabriel / shirl / engr_keith / pops → forward all to rspplowman@gmail.com
A25: Step 5 | B25: fishmusicinc.com → turn on Cloudflare Email Routing → rp@ and rsp@ → forward to rspplowman@gmail.com
A26: Step 6 | B26: Wait for DNS propagation (minutes–48h), send a test to each address, confirm it lands
A27: Step 7 | B27: Re-send the monday.com + Slack invites to the now-working addresses — team reconnects
A29: 4 · TOOLS THAT UPGRADE WHAT I CAN DO FOR YOU
A30: ✅ Cloudflare (connected) | B30: I can pull the exact Cloudflare click-path for Email Routing + MX setup on demand (docs search)
A31: ✅ GoDaddy (connected) | B31: I can check domain status / availability
A32: ⭐ ADD: Cloudflare API MCP | B32: A DNS-editing Cloudflare MCP would let me READ and SET your MX records directly — the single biggest upgrade for this fix
A33: ⭐ ADD: Filesystem / Desktop Commander | B33: Local file power for the media scan (see Setup To-Do)

Sheet Social & Admin Audit
A1: SOCIAL & ADMIN ACCOUNT AUDIT — scanned & conflict-resolved
A2: Every social + SaaS + admin account found across your Gmail, Slack & connectors — with conflicts flagged and the fix for each.
A4: 1 · SOCIAL ACCOUNTS
A5: Platform | B5: Account / Handle | C5: Status / Notes
A6: YouTube | B6: Fish Music — Music & Sounds By R.S Plowman | C6: ACTIVE — monthly analytics emails (NoizyFish brand)
A7: Instagram / X / TikTok | B7: (none found in scan) | C7: Not seen in Gmail — confirm if they exist under another handle
A8: Patreon / Threads / LinkedIn | B8: (none found in scan) | C8: No notifications found — likely not set up yet
A10: 2 · ADMIN / SAAS ACCOUNTS
A11: Service | B11: Account | C11: Status
A12: monday.com | B12: rspplowman@gmail.com | C12: ⚠ Free trial ENDED ~Jun 24 — decide keep/cancel; 9 team invites pending
A13: Notion | B13: rspplowman@gmail.com (Google + passkey) | C13: 🔴 PAYMENT FAILING — 4th charge declined, downgrade imminent. UPDATE CARD
A14: GitHub | B14: rspnoizy — repo RSPNOIZY/NOIZYLAB | C14: ACTIVE — canonical repo (CANON/GOSPEL/BRAND_MAP)
A15: Jira / Atlassian | B15: RSPNOIZY | C15: Reactivated (was on the broken-connector list)
A16: Google Workspace | B16: rsp@noizy.ai (admin) | C16: ACTIVE — sole user; near-empty Drive
A17: Google (personal) | B17: rspplowman@gmail.com | C17: ACTIVE — your command hub (Gmail connector)
A19: 3 · SLACK & DISCORD CHANNELS
A20: Slack | B20: Workspace connected (you = U0AEMKJCUPK) | C20: ⚠ 0 channels found — workspace not built out; team can't join (emails bounce)
A21: Discord | B21: No connector / no bridge to me | C21: Not reachable from here; no Discord emails found in scan
A23: 4 · CONFLICTS & RESOLUTIONS (AI-resolved)
A24: # | B24: Conflict | C24: Resolution | D24: Priority
A25: 1 | B25: ROOT CAUSE: Domains mid-transfer GoDaddy→Cloudflare (incomplete) | C25: Finish the Cloudflare transfer FIRST — it unblocks everything below | D25: P1
A26: 2 | B26: All noizylab.ca team emails bounce (Gabriel/Lucy/Shirl/Keith/Pops) | C26: After transfer: set MX records + create the 5 mailboxes → team gets mail | D26: P1
A27: 3 | B27: Notion payment failing (4th decline, downgrade imminent) | C27: Update card today — or export pages before downgrade wipes them | D27: P1
A28: 4 | B28: Team invites stuck (monday.com 9 pending + Slack empty) | C28: Same root cause — fix email (#1/#2), then re-send all invites | D28: P2
A29: 5 | B29: 5 email identities scattered (gmail/noizy.ai/outlook/icloud/rspnoizy) | C29: Pick ONE primary (rspplowman@gmail), forward the rest into it | D29: P2
A30: 6 | B30: monday.com trial ended — undecided | C30: Decide: pay to keep, or export boards + cancel | D30: P3
A31: 7 | B31: Slack workspace has no channels | C31: After email fix: create #empire #daily-council #fishmusic #brands, re-invite team | D31: P3
A33: 💡 THE ONE FIX: complete the GoDaddy→Cloudflare transfer. It cascades — email works, invites land, Slack fills, team reconnects. 4 of 7 conflicts resolve from that single action.

Sheet Drive Audit
A1: DRIVE AUDIT — complete contents of all drives
A2: Per-drive audit as of 2026-06-30. Cloud = live-scanned via connectors. Local = unreachable from this session (no filesystem bridge) — pending local-agent scan.
A3: VERDICT: 7 drives — 3 cloud AUDITED (~5KB, 0 media) | 1 cloud PENDING CONNECT (~250GB) | 3 local PENDING SCAN (~32TB). No media found in any reachable location.
A5: 1 · DRIVE SUMMARY
A6: Drive | B6: Type | C6: Reachable | D6: Scan Method | E6: Items | F6: Media | G6: Capacity | H6: Used | I6: Status
A7: Google Drive (Workspace) | B7: Cloud | C7: Yes | D7: Drive MCP | E7: 3 | F7: 0 | G7: 15 GB plan | H7: ~5 KB | I7: ✓ AUDITED
A8: Google Drive (personal) | B8: Cloud | C8: NOT connected | D8: (pending) | E8: ? | F8: ? | G8: ? | H8: ~250 GB | I8: ⏳ CONNECT rsplowman
A9: Gmail attachments | B9: Cloud | C9: Yes | D9: Gmail MCP | E9: 0 | F9: 0 | G9: — | H9: — | I9: ✓ AUDITED
A10: Adobe Creative Cloud | B10: Cloud | C10: Yes | D10: Adobe MCP | E10: 0 | F10: 0 | G10: — | H10: — | I10: ✓ AUDITED
A11: /Volumes/Audio | B11: Local | C11: No — sandbox | D11: needs local agent | E11: ? | F11: ? | G11: ~16 TB | H11: ? | I11: ⏳ PENDING SCAN
A12: 12RB | B12: Local | C12: No — sandbox | D12: needs local agent | E12: ? | F12: ? | G12: 12 TB | H12: ? | I12: ⏳ PENDING SCAN
A13: MAG4TB | B13: Local | C13: No — sandbox | D13: needs local agent | E13: ? | F13: ? | G13: 4 TB | H13: ? | I13: ⏳ PENDING SCAN
A15: 2 · CONTENTS DETAIL (every item found)
A16: Drive | B16: Item | C16: Type | D16: Size | E16: Created | F16: Modified
A17: GDrive (Workspace) | B17: Automating Command Inbox with n8n | C17: Google Sheet | D17: 1 KB | E17: 46131 | F17: 46131
A18: GDrive (Workspace) | B18: User_Download_03012026_165832 | C18: Google Sheet | D18: 3.9 KB | E18: 46025 | F18: 46032
A19: GDrive (Workspace) | B19: Google Admin Downloads | C19: Folder | D19: — | E19: 46025 | F19: 46025
A20: Gmail / Adobe CC | B20: (no items — scanned, empty of media) | C20: — | D20: — | E20: — | F20: —
A21: GDrive (personal) | B21: — awaiting connect (rsplowman@gmail.com) — | C21: ? | D21: ~250 GB | E21: — | F21: —
A22: /Volumes/Audio | B22: — awaiting local scan (Method-A / Desktop Commander) — | C22: ? | D22: ~16 TB | E22: — | F22: —
A23: 12RB | B23: — awaiting local scan — | C23: ? | D23: 12 TB | E23: — | F23: —
A24: MAG4TB | B24: — awaiting local scan — | C24: ? | D24: 4 TB | E24: — | F24: —

Sheet User & Email Audit
A1: USER & EMAIL AUDIT — deepest admin scan
A2: Source: Google Workspace admin export (User_Download), read + decoded via Drive connector. Max-depth enumeration of all users & email accounts.
A3: VERDICT: noizy.ai Workspace has 1 real user — Rob Plowman (rsp@noizy.ai). No hidden/dormant accounts. Personal rsplowman@gmail.com is separate & not connected.
A5: 1 · WORKSPACE USERS (from admin export)
A6: First Name | B6: Last Name | C6: Email | D6: Status | E6: Last Sign-In | F6: Email Usage | G6: Role
A7: Rob | B7: Plowman | C7: rsp@noizy.ai | D7: Active | E7: 46023.566 | F7: 0.0 GB | G7: Workspace admin (sole user)
A9: 2 · OTHER EMAIL ACCOUNTS REFERENCED
A10: Account | B10: Type | C10: Connected? | D10: Note
A11: rsp@noizy.ai | B11: Google Workspace | C11: Yes | D11: Connected acct; ~5KB, 0 media
A12: rsplowman@gmail.com | B12: Personal Gmail | C12: No | D12: Holds ~250GB; separate from Workspace — CONNECT to scan
A14: 3 · SAMPLE DATA FOUND (NOT real users)
A15: The export sheet also held a demo AI-prompt log. These names are TEST entries, not accounts: ALLY, DAVID, CHARLIE, ANASTASIA, BOSCO, SALVADOR.
A16: 6 sample prompts logged (models: Gemini Pro, GPT-4, Gemini Ultra, Claude 2). 2 failures: Klingon-translation safety refusal; broken retrieval link. Decorative/demo — ignore for user count.
A18: 4 · SCAN PROVENANCE & GAPS
A19: Source | B19: Detail
A20: Workspace admin export | B20: User_Download_03012026_165832 — read via Drive connector, CSV-decoded 2026-06-30. 1 user row.
A21: Admin downloads folder | B21: Google Admin Downloads' — empty container, no further exports.
A22: M2 Ultra local OS users | B22: NOT reachable from here (no filesystem bridge). macOS local accounts need a local agent: run `dscl . list /Users` or `ls /Users`. Logged as action.
A23: Gmail send-as / aliases | B23: Not exposed by connector API; would need Gmail settings access to enumerate aliases.

Sheet Libraries_OLD
A1: Master Library Inventory
A3: Lib ID | B3: Library Name | C3: Vendor / Developer | D3: Product Line | E3: Version | F3: Category | G3: Sub-Category | H3: Sample Format | I3: License Type | J3: Serial / Key | K3: Original Path | L3: Pristine Path | M3: Size (GB) | N3: # Files | O3: Has Metadata? | P3: Tagging System | Q3: Commercial? | R3: Date Acquired | S3: Date Scanned | T3: Date Processed | U3: Status | V3: DEVONthink DB | W3: TagSpaces Tagged? | X3: Notes
A4: LIB-001 | B4: Albion ONE | C4: Spitfire Audio | D4: Albion | E4: 1.6 | F4: Orchestral | G4: Cinematic Strings/Brass/Perc | H4: Kontakt | I4: Commercial | Q4: Y | U4: Untouched
A5: LIB-002 | B5: Damage 2 | C5: Heavyocity | D5: Damage | E5: 2 | F5: Cinematic Percussion | G5: Epic Drums | H5: Kontakt | I5: Commercial | Q5: Y | U5: Untouched
A6: LIB-003 | B6: Komplete 14 Ultimate | C6: Native Instruments | D6: Komplete | E6: 14 | F6: Bundle | G6: Multi (Synths/Instruments/Effects) | H6: Kontakt / NKS | I6: Commercial | Q6: Y | U6: Untouched
A7: LIB-004 | B7: Analog Brass & Winds | C7: Output | D7: Analog | E7: 1 | F7: Hybrid | G7: Brass/Winds | H7: Kontakt Player | I7: Commercial | Q7: Y | U7: Untouched
A8: LIB-005 | B8: BOOM Cinematic Trailers | C8: BOOM Library | D8: Cinematic | F8: SFX | G8: Trailer / Risers / Impacts | H8: WAV | I8: Royalty-Free | O8: Y | P8: BWAV iXML / Soundminer | Q8: Y | U8: Untouched
A9: LIB-006 | B9: Pro Sound Effects Library | C9: Pro Sound Effects | D9: Master Library | F9: SFX | G9: Foley / Ambience / Designed | H9: WAV / BWF | I9: Commercial | O9: Y | P9: BWAV iXML / UCS | Q9: Y | U9: Untouched
A10: LIB-007 | B10: Sound Ideas General Series 6000 | C10: Sound Ideas | D10: General | E10: 6000 | F10: SFX | G10: General Effects | H10: WAV / AIFF | I10: Commercial | O10: Y | P10: CSV Catalog | Q10: Y | U10: Untouched
A11: LIB-008 | B11: Splice Sounds (Subscription) | C11: Splice | D11: Sounds | F11: Loops / One-Shots | G11: Multi-Genre | H11: WAV | I11: Subscription / Royalty-Free | O11: Partial | P11: Filename Convention | Q11: Y | U11: Untouched
A12: LIB-009 | B12: Loopmasters Sample Packs | C12: Loopmasters | D12: Various | F12: Loops / One-Shots | G12: Multi-Genre | H12: WAV / REX2 / Apple Loops | I12: Royalty-Free | Q12: Y | U12: Untouched
A13: LIB-010 | B13: Cymatics Sample Packs | C13: Cymatics | F13: Loops / One-Shots / Presets | G13: EDM / Hip-Hop / Trap | H13: WAV / MIDI / Serum | I13: Royalty-Free | Q13: Y | U13: Untouched
A14: LIB-011 | B14: 8Dio Adagio Strings | C14: 8Dio | D14: Adagio | F14: Orchestral | G14: Strings | H14: Kontakt | I14: Commercial | Q14: Y | U14: Untouched
A15: LIB-012 | B15: Berlin Strings | C15: Orchestral Tools | D15: Berlin Series | F15: Orchestral | G15: Strings | H15: Kontakt / SINE | I15: Commercial | Q15: Y | U15: Untouched
A16: LIB-013 | B16: Symphobia | C16: ProjectSAM | D16: Symphobia | F16: Orchestral | G16: Ensemble / Effects | H16: Kontakt | I16: Commercial | Q16: Y | U16: Untouched
A17: LIB-014 | B17: Olympus Elements | C17: Soundiron | D17: Olympus | F17: Choir | G17: Vocal Ensemble | H17: Kontakt | I17: Commercial | Q17: Y | U17: Untouched
A18: LIB-015 | B18: Vengeance Essential House | C18: Vengeance Sound | D18: Essential | F18: Loops / One-Shots | G18: House / EDM | H18: WAV | I18: Royalty-Free | Q18: Y | U18: Untouched
A19: LIB-016 | B19: Soundly Pro | C19: Soundly | D19: Cloud Library | F19: SFX | G19: Multi | H19: WAV / BWF | I19: Subscription | O19: Y | P19: BWAV iXML | Q19: Y | U19: Untouched
A20: LIB-017 | B20: Performance Samples - Con Moto | C20: Performance Samples | D20: Con Moto | F20: Orchestral | G20: Strings | H20: Kontakt | I20: Commercial | Q20: Y | U20: Untouched
A21: LIB-018 | B21: EastWest Hollywood Orchestra | C21: EastWest / Quantum Leap | D21: Hollywood Series | F21: Orchestral | G21: Full Orchestra | H21: PLAY / Opus | I21: Commercial | Q21: Y | U21: Untouched
A22: LIB-019 | B22: Omnisphere Library | C22: Spectrasonics | D22: Omnisphere | E22: 2 | F22: Synth | G22: Hybrid / Atmospheric | H22: STEAM Engine | I22: Commercial | Q22: Y | U22: Untouched
A23: LIB-020 | B23: Serum Presets (Various) | C23: Xfer Records | D23: Serum | F23: Synth Presets | G23: Wavetable | H23: .fxp / .wav | I23: Mixed | Q23: Y | U23: Untouched

Sheet Samples
A1: SAMPLES — Per-File Catalog (links to Libraries via Lib ID)
A3: Sample ID | B3: Lib ID | C3: Filename | D3: Extension | E3: Has Ext? | F3: Suspected Type | G3: Magic Bytes | H3: Original Path | I3: Pristine Path | J3: File Size (MB) | K3: Duration (s) | L3: Sample Rate | M3: Bit Depth | N3: Channels | O3: Audio Format | P3: Container | Q3: Embedded Meta? | R3: iXML/BWAV Desc | S3: ID3 Title | T3: ID3 Artist | U3: SoundMiner Tags | V3: Vendor Hint | W3: Category | X3: Sub-Category | Y3: Character Tags | Z3: BPM | AA3: Key | AB3: Loop? | AC3: One-Shot? | AD3: Multisample? | AE3: RR Count | AF3: Vel Layers | AG3: LLM Hint Name | AH3: Grep Match | AI3: Confidence % | AJ3: LLM Model | AK3: SHA256 | AL3: Dup Of | AM3: Stage | AN3: Date Indexed | AO3: Notes
A4: SMP-000001 | B4: LIB-001 | C4: Albion_ONE_Strings_Long_pp.wav | D4: wav | E4: Y | F4: Audio | G4: RIFF/WAVE | H4: /Volumes/Samples/Spitfire/Albion ONE/Samples/ | I4: /Volumes/Pristine/Spitfire/Albion ONE/ | J4: 12.4 | K4: 8.2 | L4: 48000 | M4: 24 | N4: Stereo | O4: WAV | P4: BWAV | Q4: Y | R4: Strings - Long - pp - Albion ONE | V4: Spitfire Audio | W4: Strings | X4: Ensemble Long | Y4: warm, cinematic, lush | AB4: N | AC4: N | AD4: Y | AM4: Indexed
A5: SMP-000002 | B5: LIB-005 | C5: Cinematic_Boom_Heavy_03.wav | D5: wav | E5: Y | F5: Audio | G5: RIFF/WAVE | H5: /Volumes/Samples/BOOM/Cinematic Trailers/Booms/ | I5: /Volumes/Pristine/BOOM/Cinematic Trailers/ | J5: 4.8 | K5: 6.5 | L5: 96000 | M5: 24 | N5: Stereo | O5: WAV | P5: BWAV+iXML | Q5: Y | R5: Heavy cinematic boom impact tail | V5: BOOM Library | W5: SFX | X5: Impact / Boom | Y5: deep, heavy, sub | AC5: Y | AM5: Indexed
A6: SMP-000003 | B6: LIB-008 | C6: vox_chop_dreamy_120.wav | D6: .wav | E6: Y | F6: Audio | G6: RIFF | H6: /Volumes/Samples/Splice/Vocals/vox_chop_dreamy_120.wav | I6: 2.4 | J6: 4.2 | K6: 44100 | L6: 24 | M6: 2 | N6: WAV | O6: RIFF | P6: Y | U6: Splice | V6: Vocals | W6: Chops | X6: dreamy, pitched, wet | Y6: 120 | Z6: Am | AA6: N | AB6: Y | AF6: Female Dreamy Vocal Chop Am 120 BPM | AG6: vox|chop|dreamy | AH6: 92 | AI6: Llama-3.1-8B | AL6: Tagged
A7: SMP-000004 | B7: LIB-003 | C7: Kontakt_Piano_C3_v04_rr2.nki | D7: .nki | E7: Y | F7: Data | G7: Kontakt | H7: /Volumes/Samples/NI/Komplete14/Library/Piano/Kontakt_Piano_C3_v04_rr2.nki | I7: 0.04 | N7: NKI | O7: Kontakt | P7: Y | U7: Native Instruments | V7: Instruments | W7: Piano | Z7: C3 | AC7: Y | AD7: 4 | AE7: 6 | AF7: Kontakt Piano Patch C3 Velocity 4 RR2 | AG7: piano|nki|kontakt | AH7: 98 | AL7: Indexed
A8: SMP-000005 | B8: ??? | C8: UNKNOWN_FILE_001 | E8: N | F8: Unknown | G8: 52 49 46 46 | H8: /Volumes/OldDrive/recovered/UNKNOWN_FILE_001 | I8: 8.7 | N8: WAV (suspected) | AF8: Possibly WAV — RIFF header detected, no extension | AG8: magic:RIFF | AH8: 75 | AI8: file-magic + LLM | AL8: Needs Review | AN8: ORPHAN — grep target. Magic bytes = RIFF/WAVE. Rename to .wav after audition.
A9: SMP-000006 | B9: ??? | C9: data_blob_4429 | E9: N | F9: Data | G9: 7B 22 76 65 | H9: /Volumes/OldDrive/recovered/data_blob_4429 | I9: 0.002 | N9: JSON (suspected) | AF9: Likely JSON metadata sidecar — starts with {"ve | AG9: magic:{" | AH9: 85 | AL9: Needs Review | AN9: ORPHAN — data file, not audio. Could be tagging metadata from old session.
A10: SMP-000007 | B10: LIB-006 | C10: PSE_Foley_Footstep_Gravel_03.wav | D10: .wav | E10: Y | F10: Audio | G10: RIFF | H10: /Volumes/SFX/PSE/Foley/Footsteps/PSE_Foley_Footstep_Gravel_03.wav | I10: 3.1 | J10: 1.8 | K10: 96000 | L10: 24 | M10: 2 | N10: BWAV | O10: BWAV | P10: Y | Q10: Footstep on gravel, single step, dry | T10: footstep, gravel, foley, walk, dry | U10: Pro Sound Effects | V10: Foley | W10: Footsteps | X10: dry, close, single | AB10: Y | AF10: Foley Footstep Gravel Single Dry | AG10: footstep|gravel|foley | AH10: 99 | AL10: Pristine
A11: SMP-000008 | B11: LIB-020 | C11: Serum_Preset_LeadBass_Wobble.fxp | D11: .fxp | E11: Y | F11: Data | G11: FXP | H11: /Library/Audio/Presets/Xfer/Serum/LeadBass_Wobble.fxp | I11: 0.01 | N11: FXP | O11: VST Preset | P11: Y | U11: Xfer Records | V11: Synth Preset | W11: Bass | X11: wobble, dirty, lead | AF11: Serum Lead Bass Wobble Preset | AG11: fxp|serum|preset | AH11: 97 | AL11: Indexed

Sheet Processing
A1: PROCESSING PIPELINE — Stage-by-Stage Tracker
A2: One row per sample. Track each stage of the discovery → identification → cleaning → pristine workflow.
A3: Sample ID | B3: Filename (ref) | C3: S1: Discovered | D3: S2: Scanned (DC) | E3: S3: Magic Bytes | F3: S4: LLM Named | G3: S5: Tagged | H3: S6: SuperSonic | I3: S7: Pristine Move | J3: S8: DEVONthink | K3: S9: TagSpaces | L3: S10: Soundly | M3: LLM Model | N3: Tool/Script | O3: Last Stage Date | P3: Total Time (min) | Q3: Errors | R3: Retry Count | S3: Current Stage | T3: % Complete | U3: Notes
A4: SMP-000001 | B4: Strings_Sus_C3_v1.wav | C4: ✓ | D4: ✓ | E4: ✓ | F4: ✓ | G4: ✓ | H4: ✓ | I4: ✓ | J4: ✓ | K4: ✓ | L4: ✓ | M4: qwen2.5-7b | N4: DC+SuperSonic | O4: 45672 | P4: =12 -> 12 | R4: 0 | S4: Complete | T4: =COUNTIF(C4:L4,"✓")/10 -> 1 | U4: Full pipeline reference example
A5: SMP-000002 | B5: Boom_Cinematic_Heavy_01.wav | C5: ✓ | D5: ✓ | E5: ✓ | F5: ✓ | G5: ✓ | H5: ✓ | M5: qwen2.5-7b | N5: DC+SuperSonic | O5: 45671 | P5: 8 | R5: 0 | S5: Awaiting pristine move | T5: =COUNTIF(C5:L5,"✓")/10 -> 0.6 | U5: Cleaned, ready to move
A6: SMP-000003 | B6: vox_chop_dreamy_120bpm.wav | C6: ✓ | D6: ✓ | E6: ✓ | F6: ✓ | M6: llama-3.1-8b | N6: DC scan | O6: 45670 | P6: 4 | R6: 0 | S6: Needs tagging | T6: =COUNTIF(C6:L6,"✓")/10 -> 0.4 | U6: Splice subscription — check rights
A7: SMP-000005 | B7: UNKNOWN_FILE_001 | C7: ✓ | D7: ✓ | E7: ✓ | F7: ? | M7: qwen2.5-14b | N7: DC + magic bytes | O7: 45672 | P7: 3 | Q7: LLM confidence low — manual review | R7: 2 | S7: Needs Review | T7: =COUNTIF(C7:L7,"✓")/10 -> 0.3 | U7: ORPHAN FILE — RIFF header detected, likely WAV but no ext
A8: SMP-000006 | B8: data_blob_4429 | C8: ✓ | D8: ✓ | E8: ✓ | N8: DC + magic bytes | O8: 45672 | P8: 1 | Q8: Not audio — JSON config blob | R8: 0 | S8: Skip (non-audio) | T8: =COUNTIF(C8:L8,"✓")/10 -> 0.3 | U8: ORPHAN — JSON, not a sample. Quarantine.

Sheet Vendors
A1: Commercial Vendors Reference — Path & Filename Patterns
A2: Use these patterns to grep file paths and detect which vendor a sample belongs to. Add new patterns as you discover them.
A3: Vendor ID | B3: Vendor Name | C3: Website | D3: Path Patterns | E3: Filename Prefixes | F3: File Format Signatures | G3: Typical Install Location | H3: Auth/DRM | I3: Categories | J3: See Libraries tab | K3: Notes
A4: V-001 | B4: Spitfire Audio | C4: spitfireaudio.com | D4: /Spitfire Audio/, /Spitfire/ | E4: SA_, SF_, BBC_, Albion_, Abbey_ | F4: .nki .nkr (Kontakt); .lock | G4: ~/Spitfire Audio/ | /Library/Application Support/Spitfire Audio | H4: Spitfire App / Native Access | I4: Orchestral, Strings, Brass, Choir
A5: V-002 | B5: Native Instruments | C5: native-instruments.com | D5: /Native Instruments/, /Kontakt/, /Komplete/ | E5: NI_, K_, Maschine_ | F5: .nki .nkx .nkc .nkr .mxgrp .nksn | G5: ~/Documents/Native Instruments/ | /Users/Shared/NI Resources/ | H5: Native Access / NKS | I5: Instruments, Synths, Drums, Effects | K5: Look for .nicnt installer descriptors
A6: V-003 | B6: Heavyocity | C6: heavyocity.com | D6: /Heavyocity/, /Damage/, /Gravity/ | E6: HVY_, DMG_, GRV_ | F6: .nki (Kontakt Player) | G6: ~/Heavyocity/ | NI library folders | H6: Native Access | I6: Cinematic, Percussion, Hybrid | K6: Heavy use of multisample velocity layers
A7: V-004 | B7: Output | C7: output.com | D7: /Output/, /Arcade/ | E7: OUT_, ARC_, AB_, AW_ | F7: .nki; Arcade .arcade | G7: ~/Output/ | H7: Output Hub / Native Access | I7: Synths, Loops, Cinematic | K7: Arcade samples stream from cloud
A8: V-005 | B8: BOOM Library | C8: boomlibrary.com | D8: /BOOM Library/, /BOOM_/ | E8: BOOM_, CTSFX_, DESIGNED_, CONSTRUCTION_ | F8: .wav (BWAV with iXML); some Kontakt | G8: User-organized; commonly /Volumes/SFX/BOOM/ | H8: None (DRM-free) | I8: SFX, Cinematic, Designed, Foley | K8: Excellent iXML metadata; SoundMiner-ready
A9: V-006 | B9: Pro Sound Effects | C9: prosoundeffects.com | D9: /Pro Sound Effects/, /PSE_/, /Master Library/ | E9: PSE_, MSTR_, NYC_, BBC_ | F9: .wav BWAV (deep iXML metadata) | G9: /Volumes/PSE/ or external SSD | H9: None | I9: SFX, Foley, Ambience, Field Recording | K9: Embedded ID3+iXML — SoundMiner gold standard
A10: V-007 | B10: Splice | C10: splice.com | D10: /Splice/, /splice_sounds/ | E10: VARIES (artist names) | F10: .wav (mostly), .mid | G10: ~/Splice/sounds/ | H10: Splice app subscription | I10: Loops, One-shots, Vocals | K10: Metadata in path: bpm/key in folder names
A11: V-008 | B11: Loopmasters | C11: loopmasters.com | D11: /Loopmasters/, /LM_/ | E11: LM_, LPM_, BHK_ | F11: .wav .rex2 .aif | G11: User-organized | H11: None | I11: Loops, Construction Kits | K11: Often delivered as RAR/ZIP with structured folders
A12: V-009 | B12: Cymatics | C12: cymatics.fm | D12: /Cymatics/ | E12: CYM_, Cymatics_ | F12: .wav .mid .fxp .serum | G12: User-organized | H12: None | I12: EDM, Trap, Drums, Vocals | K12: Free + paid mixed; check email receipts
A13: V-010 | B13: 8Dio | C13: 8dio.com | D13: /8Dio/, /8DIO/ | E13: 8DIO_, AGT_, CAGE_ | F13: .nki (Kontakt full) | G13: ~/8Dio/ | H13: None (license activation) | I13: Orchestral, Cinematic, Ethnic | K13: Requires Kontakt full (not Player)
A14: V-011 | B14: Orchestral Tools | C14: orchestraltools.com | D14: /Orchestral Tools/, /OT_/, /Berlin/ | E14: OT_, BRL_, JXL_, TIME_MACRO_ | F14: .sfz (SINE player); .ot proprietary | G14: /Library/Application Support/Orchestral Tools/ | H14: SINE Player | I14: Orchestral, Strings, Winds | K14: SINE Player required — NOT Kontakt
A15: V-012 | B15: ProjectSAM | C15: projectsam.com | D15: /ProjectSAM/, /Symphobia/, /Orchestral Essentials/ | E15: PS_, SYM_, OE_ | F15: .nki (Kontakt Player) | G15: ~/ProjectSAM/ | H15: Native Access | I15: Orchestral, Cinematic | K15: Kontakt Player compatible
A16: V-013 | B16: Soundiron | C16: soundiron.com | D16: /Soundiron/ | E16: SI_, Soundiron_ | F16: .nki (Kontakt full) | G16: ~/Soundiron/ | H16: None | I16: Choirs, Ethnic, Cinematic | K16: Requires Kontakt full
... A18: V-015 | B18: Soundly | C18: getsoundly.com | D18: /Soundly/, /Soundly Library/ | E18: SDLY_, varies by source | F18: .wav (BWAV) | G18: Soundly app local cache | H18: Soundly app (subscription/Pro) | I18: SFX, Foley, Ambience | K18: Cloud-based SFX library + local sync

Sheet Identifiers
A1: GREP HINTS LIBRARY — Pattern detection for unknown/orphan files
A2: Patterns to feed your LM Studio LLM. Match these against filenames, paths, and embedded metadata to guess vendor/instrument/category.
A3: Pattern ID | B3: Pattern | C3: Match Type | D3: Indicates | E3: Category | F3: Confidence | G3: Source | H3: Example Match | I3: LLM Prompt Hint | J3: Notes
A4: ID-001 | B4: SF_ | C4: prefix | D4: Spitfire Audio | E4: Vendor | F4: High | G4: Filename | H4: SF_Albion_LongStrings_C3.wav | I4: If filename starts with 'SF_' → Spitfire Audio library | J4: Common Spitfire convention
A5: ID-002 | B5: BOOM_ | C5: prefix | D5: BOOM Library | E5: Vendor | F5: High | G5: Filename | H5: BOOM_CTM_Boom_001.wav | I5: If 'BOOM_' or 'CTM_' or 'CCT_' → BOOM Library cinematic
A6: ID-003 | B6: PSE_ | C6: prefix | D6: Pro Sound Effects | E6: Vendor | F6: High | G6: Filename | H6: PSE_FOOTSTEP_Gravel_01.wav | I6: PSE_ prefix → Pro Sound Effects library
A7: ID-004 | B7: .nki | C7: extension | D7: Kontakt Instrument | E7: Format | F7: Certain | G7: Extension | H7: Damage2_Kit_01.nki | I7: Native Instruments Kontakt instrument patch | J7: Usually paired with .nkc, .nkx
A8: ID-005 | B8: .exs | C8: extension | D8: EXS24 Sampler | E8: Format | F8: Certain | G8: Extension | H8: Strings_Legato.exs | I8: Logic EXS24 sampler instrument
A9: ID-006 | B9: RIFF | C9: magic bytes | D9: WAV/RIFF audio | E9: Audio Container | F9: Certain | G9: First 4 bytes | H9: 52 49 46 46 (RIFF) | I9: Orphan file with no extension → if first 4 bytes = RIFF, treat as WAV | J9: Critical for grep-no-ext detection
A10: ID-007 | B10: FORM | C10: magic bytes | D10: AIFF audio | E10: Audio Container | F10: Certain | G10: First 4 bytes | H10: 46 4F 52 4D (FORM) | I10: Orphan file → if first 4 bytes = FORM, treat as AIFF
A11: ID-008 | B11: OggS | C11: magic bytes | D11: OGG Vorbis | E11: Audio Container | F11: Certain | G11: First 4 bytes | H11: 4F 67 67 53 (OggS) | I11: Orphan file → OGG audio
A12: ID-009 | B12: fLaC | C12: magic bytes | D12: FLAC audio | E12: Audio Container | F12: Certain | G12: First 4 bytes | H12: 66 4C 61 43 (fLaC) | I12: Orphan file → FLAC audio
A13: ID-010 | B13: ID3 | C13: magic bytes | D13: MP3 audio | E13: Audio Container | F13: High | G13: First 3 bytes | H13: 49 44 33 (ID3) | I13: Orphan file → MP3 with ID3 tag
A14: ID-011 | B14: caff | C14: magic bytes | D14: CAF (Apple) | E14: Audio Container | F14: Certain | G14: First 4 bytes | H14: 63 61 66 66 (caff) | I14: Orphan → Core Audio Format (Logic/Apple)
A15: ID-012 | B15: { "version" | C15: magic bytes | D15: JSON metadata | E15: Data | F15: Medium | G15: Text content | H15: { "version": ..., "samples": ... | I15: NOT audio — likely a library manifest, preset, or metadata sidecar | J15: Skip from audio pipeline
A16: ID-013 | B16: [A-G][#b]?[0-9] | C16: regex | D16: Pitched sample | E16: Instrument | F16: High | G16: Filename | H16: Piano_C#3_vel100.wav | I16: Note name in filename → multisample instrument | J16: Use to detect multisamples
A17: ID-014 | B17: [0-9]{2,3}bpm|_[0-9]{2,3}_ | C17: regex | D17: Tempo-locked loop | E17: Loop | F17: High | G17: Filename | H17: Drum_Loop_128bpm.wav OR Loop_140_Am.wav | I17: BPM number in name → set Loop=Y, parse BPM
A18: ID-015 | B18: _RR[0-9]+|_vl[0-9]+|_vel[0-9]+ | C18: regex | D18: Multisample articulation | E18: Instrument | F18: High | G18: Filename | H18: Violin_C3_vel80_RR2.wav | I18: Round-robin or velocity layer → multisample
A19: ID-016 | B19: iXML | C19: embedded chunk | D19: Broadcast WAV metadata | E19: Metadata | F19: Certain | G19: WAV chunk | H19: <BWFXML>...</BWFXML> | I19: Has iXML → read Description, Category, Subcategory | J19: Soundminer/Soundly standard
A20: ID-017 | B20: /Samples/ | C20: path | D20: Generic sample folder | E20: Path | F20: Low | G20: Folder name | H20: /Library/Samples/MyLib/ | I20: Weak hint — use other signals
A21: ID-018 | B21: /Native Instruments/ | C21: path | D21: NI library | E21: Vendor | F21: Certain | G21: Folder path | H21: /Users/.../Native Instruments/Komplete/ | I21: Path contains 'Native Instruments' → NI/Komplete
A22: ID-019 | B22: /Splice/ | C22: path | D22: Splice subscription | E22: Vendor | F22: Certain | G22: Folder path | H22: /Splice/sounds/packs/.../ | I22: Splice cached pack
A23: ID-020 | B23: kick|snare|hat|clap|tom|perc|crash|ride | C23: regex | D23: Drum element | E23: Category | F23: High | G23: Filename keyword | H23: 808_kick_deep.wav | I23: Drum keyword → set Category=Drums + sub
A24: ID-021 | B24: vox|vocal|voice|phrase|chop | C24: regex | D24: Vocal sample | E24: Category | F24: High | G24: Filename keyword | H24: Vox_Chop_Am_120bpm.wav | I24: Vocal keyword → Category=Vocals
A25: ID-022 | B25: fx|sfx|impact|riser|whoosh|sweep|hit | C25: regex | D25: Sound effect | E25: Category | F25: High | G25: Filename keyword | H25: Impact_Cinematic_Big_03.wav | I25: FX keyword → Category=SFX
A26: ID-023 | B26: NOIZYANTHROPIC | C26: contains (case-insensitive) | D26: Brand: NOIZYANTHROPIC | E26: Brand Claim | F26: High | G26: House Brand | H26: NOIZYANTHROPIC_kick_01.wav | I26: If filename/path contains 'NOIZYANTHROPIC' (any case), claim for NOIZYANTHROPIC. Confidence HIGH. | J26: Exact brand match -> auto-route to /Pristine/NOIZYANTHROPIC/
A27: ID-024 | B27: noizy[-_ ]?anthropic | NA_ | anthropic | C27: regex / loose | D27: Brand: NOIZYANTHROPIC (variant) | E27: Brand Claim | F27: Low | G27: House Brand | H27: noizy_anthropic, NA_pad.wav, anthropic_vox | I27: Loose variant of NOIZYANTHROPIC. Flag LOW confidence - send to LLM review before claiming. | J27: Variant catch - review, watch false positives on bare 'anthropic'
A28: ID-025 | B28: NOIZYBEAST | C28: contains (case-insensitive) | D28: Brand: NOIZYBEAST | E28: Brand Claim | F28: High | G28: House Brand | H28: NOIZYBEAST_growl_03.wav | I28: If filename/path contains 'NOIZYBEAST' (any case), claim for NOIZYBEAST. Confidence HIGH. | J28: Exact brand match -> auto-route to /Pristine/NOIZYBEAST/
A29: ID-026 | B29: noizy[-_ ]?beast | NB_ | beast | C29: regex / loose | D29: Brand: NOIZYBEAST (variant) | E29: Brand Claim | F29: Low | G29: House Brand | H29: noizy-beast, NB_sub.wav, beast_layer | I29: Loose variant of NOIZYBEAST. Flag LOW confidence - send to LLM review. 'beast' alone is risky. | J29: Variant catch - review, 'beast' overlaps METABEAST
A30: ID-027 | B30: METABEAST | C30: contains (case-insensitive) | D30: Brand: METABEAST | E30: Brand Claim | F30: High | G30: House Brand | H30: METABEAST_riser_07.wav | I30: If filename/path contains 'METABEAST' (any case), claim for METABEAST. Confidence HIGH. | J30: Exact brand match -> auto-route to /Pristine/METABEAST/
A31: ID-028 | B31: meta[-_ ]?beast | MB_ | metab | C31: regex / loose | D31: Brand: METABEAST (variant) | E31: Brand Claim | F31: Low | G31: House Brand | H31: meta_beast, MB_hit.wav, metabeast | I31: Loose variant of METABEAST. Flag LOW confidence. Disambiguate from NOIZYBEAST when only 'beast' present. | J31: Variant catch - priority: METABEAST only if 'meta' present, else NOIZYBEAST
A32: ID-029 | B32: 52 49 46 46 ... 57 41 56 45 (RIFF....WAVE) | C32: magic-bytes | D32: WAV / BWF audio | E32: Audio Signature | F32: High | G32: Universal | H32: RIFF\x24\x08WAVE | I32: Bytes 0-3 'RIFF', bytes 8-11 'WAVE' = WAV. If 'bext' chunk present it is Broadcast WAV. | J32: Most common orphan-file recovery signature
A33: ID-030 | B33: 46 4F 52 4D ... 41 49 46 46 (FORM....AIFF) | C33: magic-bytes | D33: AIFF audio | E33: Audio Signature | F33: High | G33: Universal | H33: FORM\x00..AIFF | I33: Bytes 0-3 'FORM', bytes 8-11 'AIFF' (or 'AIFC' compressed). | J33: Apple/legacy sampler standard
A34: ID-031 | B34: 66 4C 61 43 (fLaC) | C34: magic-bytes | D34: FLAC lossless | E34: Audio Signature | F34: High | G34: Universal | H34: fLaC | I34: First 4 bytes 'fLaC' = FLAC lossless audio. | J34: Common in archived masters
A35: ID-032 | B35: 4F 67 67 53 (OggS) | C35: magic-bytes | D35: Ogg Vorbis/Opus | E35: Audio Signature | F35: High | G35: Universal | H35: OggS | I35: OggS' = Ogg container (Vorbis or Opus codec inside). | J35: Game-audio common
A36: ID-033 | B36: 49 44 33 (ID3) or FF FB | C36: magic-bytes | D36: MP3 audio | E36: Audio Signature | F36: High | G36: Universal | H36: ID3\x03 or \xFF\xFB | I36: ID3' = MP3 with ID3v2 tag; 0xFFFB = raw MP3 frame sync. | J36: Lossy — flag for re-source
A37: ID-034 | B37: 63 61 66 66 (caff) | C37: magic-bytes | D37: Apple CAF | E37: Audio Signature | F37: High | G37: Apple | H37: caff | I37: caff' = Core Audio Format (Logic/Apple high-res). | J37: Often >4GB stems
... A69: ID-066 | B69: VC_ | C69: prefix | D69: Vibe Code (prefix) | E69: Signature | F69: Low | G69: NoizyArmy | H69: VC_kick_01.wav | I69: VC_' filename prefix — likely Vibe Code; confirm not another VC initialism. | J69: Low-confidence — review

Sheet Tags
A1: TAGS — Taxonomy & Character Descriptors
A2: Controlled vocabulary for tagging — feeds TagSpaces, DEVONthink, Soundly. Hierarchical: Tag Group › Tag › Synonyms.
A3: Tag ID | B3: Tag Group | C3: Tag | D3: Synonyms / Aliases | E3: Parent Tag | F3: Color (Hex) | G3: TagSpaces Tag | H3: DEVONthink Tag | I3: Example | J3: Notes
A4: T-001 | B4: Instrument | C4: Strings | D4: violin, viola, cello, bass, ensemble | F4: #C71585 | G4: instrument-strings | H4: Strings | I4: Spitfire Albion ONE Strings Long | J4: Orchestral string family
A5: T-002 | B5: Instrument | C5: Brass | D5: trumpet, trombone, horn, tuba | F5: #FFD700 | G5: instrument-brass | H5: Brass | I5: Hollywood Brass Sus
A6: T-003 | B6: Instrument | C6: Drums | D6: kick, snare, hat, percussion | F6: #8B0000 | G6: instrument-drums | H6: Drums | I6: BOOM Drum Kick 808
A7: T-004 | B7: Instrument | C7: Synth | D7: analog, digital, FM, wavetable | F7: #00CED1 | G7: instrument-synth | H7: Synth | I7: Serum Preset Lead
A8: T-005 | B8: Instrument | C8: Vocal | D8: vox, voice, chop, ah, oh | F8: #FF69B4 | G8: instrument-vocal | H8: Vocal | I8: Splice Vocal Chop F#
A9: T-006 | B9: Category | C9: SFX | D9: sound effect, foley, impact, whoosh | F9: #FF8C00 | G9: category-sfx | H9: SFX | I9: BOOM Cinematic Whoosh
A10: T-007 | B10: Category | C10: Foley | D10: footsteps, cloth, props | E10: SFX | F10: #FFA500 | G10: category-foley | H10: Foley | I10: PSE Footstep Concrete
A11: T-008 | B11: Character | C11: Dark | D11: ominous, sinister, moody | F11: #2F2F2F | G11: char-dark | H11: Dark | I11: Damage 2 Sub Drone
A12: T-009 | B12: Character | C12: Bright | D12: shiny, glassy, crystalline | F12: #FFFACD | G12: char-bright | H12: Bright | I12: Omnisphere Bell Shine
A13: T-010 | B13: Character | C13: Lo-Fi | D13: vintage, tape, dusty, vinyl | F13: #8B4513 | G13: char-lofi | H13: Lo-Fi | I13: Cymatics Vinyl Loop
A14: T-011 | B14: Character | C14: Cinematic | D14: trailer, epic, scoring | F14: #4B0082 | G14: char-cinematic | H14: Cinematic | I14: Heavyocity Damage Hit
A15: T-012 | B15: Format | C15: Loop | D15: looped, beat, groove | F15: #32CD32 | G15: format-loop | H15: Loop | I15: Loopmasters Tech House 124
A16: T-013 | B16: Format | C16: One-Shot | D16: single, hit, stab | F16: #1E90FF | G16: format-oneshot | H16: One-Shot | I16: Cymatics Snare 808
A17: T-014 | B17: Format | C17: Multisample | D17: patch, instrument, sampler | F17: #9370DB | G17: format-multi | H17: Multisample | I17: Kontakt .nki patch
A18: T-015 | B18: Source | C18: Commercial | D18: paid, licensed, vendor | F18: #006400 | G18: source-commercial | H18: Commercial | I18: Spitfire libraries
A19: T-016 | B19: Source | C19: Subscription | D19: splice, soundly, monthly | E19: Commercial | F19: #228B22 | G19: source-sub | H19: Subscription | I19: Splice downloaded
A20: T-017 | B20: Source | C20: Royalty-Free | D20: RF, CC, public domain | F20: #90EE90 | G20: source-rf | H20: Royalty-Free | I20: Freesound CC0
A21: T-018 | B21: Status | C21: Pristine | D21: cleaned, finalized, indexed | F21: #FFFFFF | G21: status-pristine | H21: Pristine | I21: Post-SuperSonic clean
A22: T-019 | B22: Status | C22: Orphan | D22: no extension, unknown, needs review | F22: #FF4500 | G22: status-orphan | H22: Orphan | I22: UNKNOWN_FILE_001
A23: T-020 | B23: Status | C23: Duplicate | D23: dup, copy, identical | F23: #DC143C | G23: status-dup | H23: Duplicate | I23: SHA256 collision

Sheet Catalog
A1: Master Library Inventory | Z1: ROLL-UP (live)
Z2: Total libraries | AA2: =COUNTA($A$4:$A$200) -> 20
A3: Lib ID | B3: Library Name | C3: Vendor / Developer | D3: Product Line | E3: Version | F3: Category | G3: Sub-Category | H3: Sample Format | I3: License Type | J3: Serial / Key | K3: Original Path | L3: Pristine Path | M3: Size (GB) | N3: # Files | O3: Has Metadata? | P3: Tagging System | Q3: Commercial? | R3: Date Acquired | S3: Date Scanned | T3: Date Processed | U3: Status | V3: DEVONthink DB | W3: TagSpaces Tagged? | X3: Notes | Z3: Commercial | AA3: =COUNTIF($Q$4:$Q$200,"Y") -> 20
A4: LIB-001 | B4: Albion ONE | C4: Spitfire Audio | D4: Albion | E4: 1.6 | F4: Orchestral | G4: Cinematic Strings/Brass/Perc | H4: Kontakt | I4: Commercial | Q4: Y | U4: Untouched | Z4: Untouched | AA4: =COUNTIF($U$4:$U$200,"Untouched") -> 20
A5: LIB-002 | B5: Damage 2 | C5: Heavyocity | D5: Damage | E5: 2 | F5: Cinematic Percussion | G5: Epic Drums | H5: Kontakt | I5: Commercial | Q5: Y | U5: Untouched | Z5: Total size (GB) | AA5: =SUM($M$4:$M$200) -> 0
A6: LIB-003 | B6: Komplete 14 Ultimate | C6: Native Instruments | D6: Komplete | E6: 14 | F6: Bundle | G6: Multi (Synths/Instruments/Effects) | H6: Kontakt / NKS | I6: Commercial | Q6: Y | U6: Untouched | Z6: Total files | AA6: =SUM($N$4:$N$200) -> 0
A7: LIB-004 | B7: Analog Brass & Winds | C7: Output | D7: Analog | E7: 1 | F7: Hybrid | G7: Brass/Winds | H7: Kontakt Player | I7: Commercial | Q7: Y | U7: Untouched
A8: LIB-005 | B8: BOOM Cinematic Trailers | C8: BOOM Library | D8: Cinematic | F8: SFX | G8: Trailer / Risers / Impacts | H8: WAV | I8: Royalty-Free | O8: Y | P8: BWAV iXML / Soundminer | Q8: Y | U8: Untouched
A9: LIB-006 | B9: Pro Sound Effects Library | C9: Pro Sound Effects | D9: Master Library | F9: SFX | G9: Foley / Ambience / Designed | H9: WAV / BWF | I9: Commercial | O9: Y | P9: BWAV iXML / UCS | Q9: Y | U9: Untouched
A10: LIB-007 | B10: Sound Ideas General Series 6000 | C10: Sound Ideas | D10: General | E10: 6000 | F10: SFX | G10: General Effects | H10: WAV / AIFF | I10: Commercial | O10: Y | P10: CSV Catalog | Q10: Y | U10: Untouched
A11: LIB-008 | B11: Splice Sounds (Subscription) | C11: Splice | D11: Sounds | F11: Loops / One-Shots | G11: Multi-Genre | H11: WAV | I11: Subscription / Royalty-Free | O11: Partial | P11: Filename Convention | Q11: Y | U11: Untouched
A12: LIB-009 | B12: Loopmasters Sample Packs | C12: Loopmasters | D12: Various | F12: Loops / One-Shots | G12: Multi-Genre | H12: WAV / REX2 / Apple Loops | I12: Royalty-Free | Q12: Y | U12: Untouched
A13: LIB-010 | B13: Cymatics Sample Packs | C13: Cymatics | F13: Loops / One-Shots / Presets | G13: EDM / Hip-Hop / Trap | H13: WAV / MIDI / Serum | I13: Royalty-Free | Q13: Y | U13: Untouched
A14: LIB-011 | B14: 8Dio Adagio Strings | C14: 8Dio | D14: Adagio | F14: Orchestral | G14: Strings | H14: Kontakt | I14: Commercial | Q14: Y | U14: Untouched
A15: LIB-012 | B15: Berlin Strings | C15: Orchestral Tools | D15: Berlin Series | F15: Orchestral | G15: Strings | H15: Kontakt / SINE | I15: Commercial | Q15: Y | U15: Untouched
A16: LIB-013 | B16: Symphobia | C16: ProjectSAM | D16: Symphobia | F16: Orchestral | G16: Ensemble / Effects | H16: Kontakt | I16: Commercial | Q16: Y | U16: Untouched
A17: LIB-014 | B17: Olympus Elements | C17: Soundiron | D17: Olympus | F17: Choir | G17: Vocal Ensemble | H17: Kontakt | I17: Commercial | Q17: Y | U17: Untouched
A18: LIB-015 | B18: Vengeance Essential House | C18: Vengeance Sound | D18: Essential | F18: Loops / One-Shots | G18: House / EDM | H18: WAV | I18: Royalty-Free | Q18: Y | U18: Untouched
A19: LIB-016 | B19: Soundly Pro | C19: Soundly | D19: Cloud Library | F19: SFX | G19: Multi | H19: WAV / BWF | I19: Subscription | O19: Y | P19: BWAV iXML | Q19: Y | U19: Untouched
A20: LIB-017 | B20: Performance Samples - Con Moto | C20: Performance Samples | D20: Con Moto | F20: Orchestral | G20: Strings | H20: Kontakt | I20: Commercial | Q20: Y | U20: Untouched
A21: LIB-018 | B21: EastWest Hollywood Orchestra | C21: EastWest / Quantum Leap | D21: Hollywood Series | F21: Orchestral | G21: Full Orchestra | H21: PLAY / Opus | I21: Commercial | Q21: Y | U21: Untouched
A22: LIB-019 | B22: Omnisphere Library | C22: Spectrasonics | D22: Omnisphere | E22: 2 | F22: Synth | G22: Hybrid / Atmospheric | H22: STEAM Engine | I22: Commercial | Q22: Y | U22: Untouched
A23: LIB-020 | B23: Serum Presets (Various) | C23: Xfer Records | D23: Serum | F23: Synth Presets | G23: Wavetable | H23: .fxp / .wav | I23: Mixed | Q23: Y | U23: Untouched

Sheet Brands
A1: BRAND REGISTRY — Claim Rules & Distribution Routing
A2: House brands claim matching audio first (by priority); client/project brands route to their own destinations. Grep rules feed the Scan Queue auto-classifier.
A3: Brand ID | B3: Brand Name | C3: Type | D3: Exact Grep (high conf) | E3: Loose Variants (low conf) | F3: Filename Prefix | G3: Claim Priority | H3: Clients / Projects | I3: Default Destination | J3: Tag Color | K3: Notes
A4: BR-001 | B4: NOIZYANTHROPIC | C4: House Brand | D4: NOIZYANTHROPIC | E4: noizy_anthropic | noizy-anthropic | NA_ | NZYANTH | n.anthropic | F4: NA_ | G4: 1 | H4: (flagship / core catalog) | I4: /Pristine/NOIZYANTHROPIC/ | J4: #7B2D8E | K4: Highest claim priority — wins ties over other brands
A5: BR-002 | B5: NOIZYBEAST | C5: House Brand | D5: NOIZYBEAST | E5: noizy_beast | noizy-beast | NB_ | NZYBST | n.beast | F5: NB_ | G5: 2 | H5: (beats / loops / construction kits) | I5: /Pristine/NOIZYBEAST/ | J5: #C00000 | K5: Claims after NOIZYANTHROPIC
A6: BR-003 | B6: METABEAST | C6: House Brand | D6: METABEAST | E6: meta_beast | meta-beast | meta beast | MB_ | MTBST | F6: MB_ | G6: 3 | H6: (meta / AI-processed / derivative works) | I6: /Pristine/METABEAST/ | J6: #1F6FC0 | K6: Catches AI-rebuilt / derivative audio
A7: BR-100 | B7: (client slot) | C7: Client | D7: CLIENTNAME | E7: client_variants_here | F7: CL_ | G7: 10 | H7: Project A / Project B | I7: /Pristine/Clients/CLIENTNAME/ | K7: Duplicate this row per client
A8: BR-101 | B8: Gabriel | C8: Collaborator | D8: Gabriel | E8: gabriel | gab_ | gbrl | GAB_ | F8: GAB_ | G8: 4 | H8: Vibe Code sessions, co-productions | I8: /Pristine/_Collaborators/Gabriel/ | J8: #0F9D8C | K8: Genius collaborator — grep all sessions & stems for credit + grouping
A9: BR-102 | B9: Lucy | C9: Collaborator | D9: Lucy | E9: lucy | lcy | LUCY_ | F9: LUCY_ | G9: 4 | H9: Vibe Code sessions, co-productions | I9: /Pristine/_Collaborators/Lucy/ | J9: #E84B8A | K9: Genius collaborator — grep all sessions & stems for credit + grouping
A10: BR-103 | B10: Vibe Code | C10: Signature / Project | D10: VibeCode | E10: vibe[-_ ]?code | vibecode | VC_ | F10: VC_ | G10: 3 | H10: Gabriel + Lucy genius sessions | I10: /Pristine/_VibeCode/ | J10: #E6B400 | K10: The signature sound — catch every variant spelling across all drives

Sheet Distribution
A1: DISTRIBUTION NETWORK — Target Locations, Capacity & Redundancy
A2: Where pristine audio lands after processing. Free/%, redundancy, and sync-partner tracking. Capacity is manual-entry (this sheet can't read live disk).
A3: Dest ID | B3: Location Name | C3: Type | D3: Path / Mount | E3: Brand Assignment | F3: Capacity (GB) | G3: Used (GB) | H3: Free (GB) | I3: % Full | J3: Redundancy | K3: Sync Partner | L3: Priority | M3: Status | N3: Last Verified | O3: Notes
A4: DST-001 | B4: Pristine Masters (Primary) | C4: Primary | D4: /Volumes/PRISTINE/Masters/ | E4: ALL | F4: 8000 | G4: 0 | H4: =F4-G4 -> 8000 | I4: =IF(F4=0,0,G4/F4) -> 0 | J4: RAID-5 | K4: DST-003 | L4: 1 | M4: Online | O4: Authoritative copy — never edited in place
A5: DST-002 | B5: Working / Processing | C5: Working | D5: /Volumes/WORK/Staging/ | E5: ALL | F5: 4000 | G5: 0 | H5: =F5-G5 -> 4000 | I5: =IF(F5=0,0,G5/F5) -> 0 | J5: Single | K5: — | L5: 2 | M5: Online | O5: SuperSonic scratch — cleared after pristine move
A6: DST-003 | B6: Backup Mirror (Offsite) | C6: Backup | D6: /Volumes/BACKUP/Mirror/ | E6: ALL | F6: 8000 | G6: 0 | H6: =F6-G6 -> 8000 | I6: =IF(F6=0,0,G6/F6) -> 0 | J6: Mirror | K6: DST-001 | L6: 1 | M6: Online | O6: 1:1 mirror of DST-001
A7: DST-004 | B7: Cloud Archive | C7: Archive | D7: s3://noizy-archive/pristine/ | E7: ALL | F7: 100000 | G7: 0 | H7: =F7-G7 -> 100000 | I7: =IF(F7=0,0,G7/F7) -> 0 | J7: Cloud-sync | K7: DST-001 | L7: 3 | M7: Online | O7: Cold storage — deep archive tier
A8: DST-010 | B8: NOIZYANTHROPIC Pristine | C8: Primary | D8: /Volumes/PRISTINE/Masters/NOIZYANTHROPIC/ | E8: NOIZYANTHROPIC | F8: 2000 | G8: 0 | H8: =F8-G8 -> 2000 | I8: =IF(F8=0,0,G8/F8) -> 0 | J8: RAID-5 | K8: DST-003 | L8: 1 | M8: Online | O8: Brand subfolder of DST-001
A9: DST-011 | B9: NOIZYBEAST Pristine | C9: Primary | D9: /Volumes/PRISTINE/Masters/NOIZYBEAST/ | E9: NOIZYBEAST | F9: 2000 | G9: 0 | H9: =F9-G9 -> 2000 | I9: =IF(F9=0,0,G9/F9) -> 0 | J9: RAID-5 | K9: DST-003 | L9: 1 | M9: Online | O9: Brand subfolder of DST-001
A10: DST-012 | B10: METABEAST Pristine | C10: Primary | D10: /Volumes/PRISTINE/Masters/METABEAST/ | E10: METABEAST | F10: 2000 | G10: 0 | H10: =F10-G10 -> 2000 | I10: =IF(F10=0,0,G10/F10) -> 0 | J10: RAID-5 | K10: DST-003 | L10: 1 | M10: Online | O10: Brand subfolder of DST-001
A11: TOTAL | F11: =SUM(F4:F10) -> 126000 | G11: =SUM(G4:G10) -> 0 | H11: =SUM(H4:H10) -> 126000 | I11: =IF(F11=0,0,G11/F11) -> 0

Sheet Integrity
A1: INTEGRITY & DEDUPLICATION — Hash Verification, Duplicate Detection & Audio Rebuild Tracking | Z1: ROLL-UP (live)
A2: Scanner writes SHA256 + size per file. Same hash = exact dup. Same audio-fingerprint, different hash = re-encode/near-dup. Corrupt/headerless files flagged for SuperSonic rebuild. | Z2: Total tracked | AA2: =COUNTA($A$4:$A$500) -> 5
A3: Integrity ID | B3: Sample ID | C3: Filename | D3: SHA256 Hash | E3: Size (bytes) | F3: Duplicate? | G3: Duplicate Of | H3: Detection Method | I3: Integrity Status | J3: Rebuild Needed? | K3: Rebuild Method | L3: Bit-Exact? | M3: Last Verified | N3: Verified By | O3: Notes | P3: Q-Grade | Z3: Duplicates | AA3: =COUNTIF($F$4:$F$500,"Y") -> 1
A4: INT-000001 | B4: SMP-000001 | C4: SF_Albion_ONE_Strings_Sus_C2_RR1.wav | D4: a3f5c9e1b7d2...8f4e (64-char) | E4: 28311552 | F4: N | H4: hash | I4: Verified | J4: N | L4: Y | M4: 45672 | N4: Desktop Commander | O4: Master copy — unique | P4: QA | Z4: Corrupt | AA4: =COUNTIF($I$4:$I$500,"Corrupt") -> 1
A5: INT-000002 | B5: SMP-000007 | C5: Footstep_Gravel_01.wav | D5: a3f5c9e1b7d2...8f4e (64-char) | E5: 28311552 | F5: Y | G5: INT-000001 | H5: hash | I5: Verified | J5: N | L5: Y | M5: 45672 | N5: Desktop Commander | O5: EXACT dup of INT-000001 — same SHA256. Safe to delete, keep master. | P5: QA | Z5: Rebuild needed | AA5: =COUNTIF($J$4:$J$500,"Y") -> 1
A6: INT-000003 | B6: SMP-000003 | C6: Vox_Chop_Am_128bpm.wav | D6: c8b1f0a4...2e9d (64-char) | E6: 5242880 | F6: Near | G6: INT-000003-src | H6: audio-fingerprint | I6: Verified | J6: N | L6: N | M6: 45673 | N6: SuperSonic | O6: Same audio, different encode (MP3→WAV). Keep highest-quality source. | P6: QB | Z6: Verified OK | AA6: =COUNTIF($I$4:$I$500,"Verified") -> 3
A7: INT-000004 | B7: SMP-000005 | C7: UNKNOWN_FILE_001 (no ext) | D7: f1e2d3c4...9a0b (64-char) | E7: 44100000 | F7: N | I7: Corrupt | J7: Y | K7: Repair WAV header (RIFF detected, no ext) | L7: ? | M7: 45673 | N7: SuperSonic | O7: Orphan w/ RIFF magic bytes but broken header — rebuild + re-extension to .wav | P7: QX
A8: INT-000005 | B8: SMP-000006 | C8: data_blob_4429 (no ext) | D8: 0a1b2c3d...4e5f (64-char) | E8: 8192 | F8: N | I8: Not Audio | J8: N | L8: n/a | M8: 45673 | N8: Desktop Commander | O8: JSON magic bytes — metadata sidecar, not audio. Route to data, skip rebuild. | P8: — | Z8: Q-GRADE DIST
Z9: QA pristine | AA9: =COUNTIF($P$4:$P$500,"QA") -> 2
Z10: QB good | AA10: =COUNTIF($P$4:$P$500,"QB") -> 1
Z11: QC usable | AA11: =COUNTIF($P$4:$P$500,"QC") -> 0
Z12: QX rebuild | AA12: =COUNTIF($P$4:$P$500,"QX") -> 1

Sheet Scan Queue
A1: SCAN QUEUE — Paste Scanner Output Below (cols A–G) · Auto-Classify Runs in H–T | U1: ROLL-UP (live)
A2: WORKFLOW: Desktop Commander / your scanner writes raw file data into A–G. Formulas in H–T auto-detect brand, destination, type, duplicates, and project grouping. Then filter/sort and dispatch. | U2: Total queued | V2: =COUNTA($B$4:$B$1000) -> 4 | W2: set Y only after Clone Status confirms this file's source drive is 3-2-1
A3: Q ID | B3: Filename (paste) | C3: Full Path (paste) | D3: Size bytes (paste) | E3: Ext (paste) | F3: Modified (paste) | G3: SHA256 (paste) | H3: Has Ext? | I3: Detected Brand | J3: Brand Conf | K3: Project/Product | L3: Suspected Type | M3: Target Destination | N3: Dup Count | O3: Dup Status | P3: Files in Project | Q3: Action | R3: Status | S3: Notes | U3: NOIZYANTHROPIC | V3: =COUNTIF($I$4:$I$1000,"NOIZYANTHROPIC") -> 2 | W3: Src 3-2-1 OK? | X3: Backup Guard
A4: Q-0001 | B4: NOIZYANTHROPIC_Kick_01.wav | C4: /Vol/Audio/NOIZYANTHROPIC/DrumKit_Vol1/NOIZYANTHROPIC_Kick_01.wav | D4: 480000 | E4: .wav | F4: 45301 | G4: HASHAAA111 | H4: =IF($B4="","",IF(E4="","N","Y")) -> Y | I4: =IF($B4="","",IF(ISNUMBER(SEARCH("NOIZYANTHROPIC",B4&C4)),"NOIZYANTHROPIC",IF(ISNUMBER(SEARCH("METABEAST",B4&C4)),"METABEAST",IF(ISNUMBER(SEARCH("META",B4&C4)),"METABEAST",IF(ISNUMBER(SEARCH("NOIZYBEAST",B4&C4)),"NOIZYBEAST",IF(ISNUMBER(SEARCH("BEAST",B4&C4)),"NOIZYBEAST",IF(ISNUMBER(SEARCH("NA_",B4&C4)),"NOIZYANTHROPIC",IF(ISNUMBER(SEARCH("NB_",B4&C4)),"NOIZYBEAST",IF(ISNUMBER(SEARCH("MB_",B4&C4)),"METABEAST","—"))))))))) -> NOIZYANTHROPIC | J4: =IF($B4="","",IF(OR(ISNUMBER(SEARCH("NOIZYANTHROPIC",B4&C4)),ISNUMBER(SEARCH("METABEAST",B4&C4)),ISNUMBER(SEARCH("NOIZYBEAST",B4&C4))),"High",IF(I4="—","—","Low"))) -> High | K4: DrumKit_Vol1 | L4: =IF($B4="","",IF(OR(ISNUMBER(SEARCH(".wav",B4)),ISNUMBER(SEARCH(".aif",B4)),ISNUMBER(SEARCH(".flac",B4)),ISNUMBER(SEARCH(".mp3",B4)),ISNUMBER(SEARCH(".ogg",B4)),ISNUMBER(SEARCH(".caf",B4))),"Audio",IF(H4="N","Orphan-Review","Data"))) -> Audio | M4: =IF($B4="","",IF(I4="NOIZYANTHROPIC","/Pristine/NOIZYANTHROPIC/",IF(I4="NOIZYBEAST","/Pristine/NOIZYBEAST/",IF(I4="METABEAST","/Pristine/METABEAST/","/Pristine/_UNSORTED/")))) -> /Pristine/NOIZYANTHROPIC/ | N4: =IF($B4="","",IF(G4="","",COUNTIF($G$4:$G$1000,G4))) -> 2 | O4: =IF($B4="","",IF(G4="","",IF(N4>1,"DUP","unique"))) -> DUP | P4: =IF($B4="","",IF(K4="","",COUNTIF($K$4:$K$1000,K4))) -> 2 | U4: NOIZYBEAST | V4: =COUNTIF($I$4:$I$1000,"NOIZYBEAST") -> 0 | X4: =IF($B4="","",IF($W4="Y","✅ SAFE TO MOVE","🔒 DO NOT DELETE — not 3-2-1")) -> 🔒 DO NOT DELETE — not 3-2-1
A5: Q-0002 | B5: MB_Riser_FX.wav | C5: /Vol/Audio/METABEAST/TrailerPack/MB_Riser_FX.wav | D5: 960000 | E5: .wav | F5: 45323 | G5: HASHBBB222 | H5: =IF($B5="","",IF(E5="","N","Y")) -> Y | I5: =IF($B5="","",IF(ISNUMBER(SEARCH("NOIZYANTHROPIC",B5&C5)),"NOIZYANTHROPIC",IF(ISNUMBER(SEARCH("METABEAST",B5&C5)),"METABEAST",IF(ISNUMBER(SEARCH("META",B5&C5)),"METABEAST",IF(ISNUMBER(SEARCH("NOIZYBEAST",B5&C5)),"NOIZYBEAST",IF(ISNUMBER(SEARCH("BEAST",B5&C5)),"NOIZYBEAST",IF(ISNUMBER(SEARCH("NA_",B5&C5)),"NOIZYANTHROPIC",IF(ISNUMBER(SEARCH("NB_",B5&C5)),"NOIZYBEAST",IF(ISNUMBER(SEARCH("MB_",B5&C5)),"METABEAST","—"))))))))) -> METABEAST | J5: =IF($B5="","",IF(OR(ISNUMBER(SEARCH("NOIZYANTHROPIC",B5&C5)),ISNUMBER(SEARCH("METABEAST",B5&C5)),ISNUMBER(SEARCH("NOIZYBEAST",B5&C5))),"High",IF(I5="—","—","Low"))) -> High | K5: TrailerPack | L5: =IF($B5="","",IF(OR(ISNUMBER(SEARCH(".wav",B5)),ISNUMBER(SEARCH(".aif",B5)),ISNUMBER(SEARCH(".flac",B5)),ISNUMBER(SEARCH(".mp3",B5)),ISNUMBER(SEARCH(".ogg",B5)),ISNUMBER(SEARCH(".caf",B5))),"Audio",IF(H5="N","Orphan-Review","Data"))) -> Audio | M5: =IF($B5="","",IF(I5="NOIZYANTHROPIC","/Pristine/NOIZYANTHROPIC/",IF(I5="NOIZYBEAST","/Pristine/NOIZYBEAST/",IF(I5="METABEAST","/Pristine/METABEAST/","/Pristine/_UNSORTED/")))) -> /Pristine/METABEAST/ | N5: =IF($B5="","",IF(G5="","",COUNTIF($G$4:$G$1000,G5))) -> 1 | O5: =IF($B5="","",IF(G5="","",IF(N5>1,"DUP","unique"))) -> unique | P5: =IF($B5="","",IF(K5="","",COUNTIF($K$4:$K$1000,K5))) -> 1 | U5: METABEAST | V5: =COUNTIF($I$4:$I$1000,"METABEAST") -> 1 | X5: =IF($B5="","",IF($W5="Y","✅ SAFE TO MOVE","🔒 DO NOT DELETE — not 3-2-1")) -> 🔒 DO NOT DELETE — not 3-2-1
A6: Q-0003 | B6: UNKNOWN_FILE_88 | C6: /Vol/Audio/_dump/UNKNOWN_FILE_88 | D6: 480000 | F6: 45265 | G6: HASHAAA111 | H6: =IF($B6="","",IF(E6="","N","Y")) -> N | I6: =IF($B6="","",IF(ISNUMBER(SEARCH("NOIZYANTHROPIC",B6&C6)),"NOIZYANTHROPIC",IF(ISNUMBER(SEARCH("METABEAST",B6&C6)),"METABEAST",IF(ISNUMBER(SEARCH("META",B6&C6)),"METABEAST",IF(ISNUMBER(SEARCH("NOIZYBEAST",B6&C6)),"NOIZYBEAST",IF(ISNUMBER(SEARCH("BEAST",B6&C6)),"NOIZYBEAST",IF(ISNUMBER(SEARCH("NA_",B6&C6)),"NOIZYANTHROPIC",IF(ISNUMBER(SEARCH("NB_",B6&C6)),"NOIZYBEAST",IF(ISNUMBER(SEARCH("MB_",B6&C6)),"METABEAST","—"))))))))) -> — | J6: =IF($B6="","",IF(OR(ISNUMBER(SEARCH("NOIZYANTHROPIC",B6&C6)),ISNUMBER(SEARCH("METABEAST",B6&C6)),ISNUMBER(SEARCH("NOIZYBEAST",B6&C6))),"High",IF(I6="—","—","Low"))) -> — | L6: =IF($B6="","",IF(OR(ISNUMBER(SEARCH(".wav",B6)),ISNUMBER(SEARCH(".aif",B6)),ISNUMBER(SEARCH(".flac",B6)),ISNUMBER(SEARCH(".mp3",B6)),ISNUMBER(SEARCH(".ogg",B6)),ISNUMBER(SEARCH(".caf",B6))),"Audio",IF(H6="N","Orphan-Review","Data"))) -> Orphan-Review | M6: =IF($B6="","",IF(I6="NOIZYANTHROPIC","/Pristine/NOIZYANTHROPIC/",IF(I6="NOIZYBEAST","/Pristine/NOIZYBEAST/",IF(I6="METABEAST","/Pristine/METABEAST/","/Pristine/_UNSORTED/")))) -> /Pristine/_UNSORTED/ | N6: =IF($B6="","",IF(G6="","",COUNTIF($G$4:$G$1000,G6))) -> 2 | O6: =IF($B6="","",IF(G6="","",IF(N6>1,"DUP","unique"))) -> DUP | P6: =IF($B6="","",IF(K6="","",COUNTIF($K$4:$K$1000,K6))) | U6: Unsorted / unknown | V6: =COUNTIF($I$4:$I$1000,"—") -> 1 | X6: =IF($B6="","",IF($W6="Y","✅ SAFE TO MOVE","🔒 DO NOT DELETE — not 3-2-1")) -> 🔒 DO NOT DELETE — not 3-2-1
A7: Q-0004 | B7: NOIZYANTHROPIC_Snare_01.wav | C7: /Vol/Audio/NOIZYANTHROPIC/DrumKit_Vol1/NOIZYANTHROPIC_Snare_01.wav | D7: 300000 | E7: .wav | F7: 45301 | G7: HASHCCC333 | H7: =IF($B7="","",IF(E7="","N","Y")) -> Y | I7: =IF($B7="","",IF(ISNUMBER(SEARCH("NOIZYANTHROPIC",B7&C7)),"NOIZYANTHROPIC",IF(ISNUMBER(SEARCH("METABEAST",B7&C7)),"METABEAST",IF(ISNUMBER(SEARCH("META",B7&C7)),"METABEAST",IF(ISNUMBER(SEARCH("NOIZYBEAST",B7&C7)),"NOIZYBEAST",IF(ISNUMBER(SEARCH("BEAST",B7&C7)),"NOIZYBEAST",IF(ISNUMBER(SEARCH("NA_",B7&C7)),"NOIZYANTHROPIC",IF(ISNUMBER(SEARCH("NB_",B7&C7)),"NOIZYBEAST",IF(ISNUMBER(SEARCH("MB_",B7&C7)),"METABEAST","—"))))))))) -> NOIZYANTHROPIC | J7: =IF($B7="","",IF(OR(ISNUMBER(SEARCH("NOIZYANTHROPIC",B7&C7)),ISNUMBER(SEARCH("METABEAST",B7&C7)),ISNUMBER(SEARCH("NOIZYBEAST",B7&C7))),"High",IF(I7="—","—","Low"))) -> High | K7: DrumKit_Vol1 | L7: =IF($B7="","",IF(OR(ISNUMBER(SEARCH(".wav",B7)),ISNUMBER(SEARCH(".aif",B7)),ISNUMBER(SEARCH(".flac",B7)),ISNUMBER(SEARCH(".mp3",B7)),ISNUMBER(SEARCH(".ogg",B7)),ISNUMBER(SEARCH(".caf",B7))),"Audio",IF(H7="N","Orphan-Review","Data"))) -> Audio | M7: =IF($B7="","",IF(I7="NOIZYANTHROPIC","/Pristine/NOIZYANTHROPIC/",IF(I7="NOIZYBEAST","/Pristine/NOIZYBEAST/",IF(I7="METABEAST","/Pristine/METABEAST/","/Pristine/_UNSORTED/")))) -> /Pristine/NOIZYANTHROPIC/ | N7: =IF($B7="","",IF(G7="","",COUNTIF($G$4:$G$1000,G7))) -> 1 | O7: =IF($B7="","",IF(G7="","",IF(N7>1,"DUP","unique"))) -> unique | P7: =IF($B7="","",IF(K7="","",COUNTIF($K$4:$K$1000,K7))) -> 2 | U7: Audio files | V7: =COUNTIF($L$4:$L$1000,"Audio") -> 3 | X7: =IF($B7="","",IF($W7="Y","✅ SAFE TO MOVE","🔒 DO NOT DELETE — not 3-2-1")) -> 🔒 DO NOT DELETE — not 3-2-1
H8: =IF($B8="","",IF(E8="","N","Y")) | I8: =IF($B8="","",IF(ISNUMBER(SEARCH("NOIZYANTHROPIC",B8&C8)),"NOIZYANTHROPIC",IF(ISNUMBER(SEARCH("METABEAST",B8&C8)),"METABEAST",IF(ISNUMBER(SEARCH("META",B8&C8)),"METABEAST",IF(ISNUMBER(SEARCH("NOIZYBEAST",B8&C8)),"NOIZYBEAST",IF(ISNUMBER(SEARCH("BEAST",B8&C8)),"NOIZYBEAST",IF(ISNUMBER(SEARCH("NA_",B8&C8)),"NOIZYANTHROPIC",IF(ISNUMBER(SEARCH("NB_",B8&C8)),"NOIZYBEAST",IF(ISNUMBER(SEARCH("MB_",B8&C8)),"METABEAST","—"))))))))) | J8: =IF($B8="","",IF(OR(ISNUMBER(SEARCH("NOIZYANTHROPIC",B8&C8)),ISNUMBER(SEARCH("METABEAST",B8&C8)),ISNUMBER(SEARCH("NOIZYBEAST",B8&C8))),"High",IF(I8="—","—","Low"))) | L8: =IF($B8="","",IF(OR(ISNUMBER(SEARCH(".wav",B8)),ISNUMBER(SEARCH(".aif",B8)),ISNUMBER(SEARCH(".flac",B8)),ISNUMBER(SEARCH(".mp3",B8)),ISNUMBER(SEARCH(".ogg",B8)),ISNUMBER(SEARCH(".caf",B8))),"Audio",IF(H8="N","Orphan-Review","Data"))) | M8: =IF($B8="","",IF(I8="NOIZYANTHROPIC","/Pristine/NOIZYANTHROPIC/",IF(I8="NOIZYBEAST","/Pristine/NOIZYBEAST/",IF(I8="METABEAST","/Pristine/METABEAST/","/Pristine/_UNSORTED/")))) | N8: =IF($B8="","",IF(G8="","",COUNTIF($G$4:$G$1000,G8))) | O8: =IF($B8="","",IF(G8="","",IF(N8>1,"DUP","unique"))) | P8: =IF($B8="","",IF(K8="","",COUNTIF($K$4:$K$1000,K8))) | U8: Orphans (review) | V8: =COUNTIF($L$4:$L$1000,"Orphan-Review") -> 1 | X8: =IF($B8="","",IF($W8="Y","✅ SAFE TO MOVE","🔒 DO NOT DELETE — not 3-2-1"))
H9: =IF($B9="","",IF(E9="","N","Y")) | I9: =IF($B9="","",IF(ISNUMBER(SEARCH("NOIZYANTHROPIC",B9&C9)),"NOIZYANTHROPIC",IF(ISNUMBER(SEARCH("METABEAST",B9&C9)),"METABEAST",IF(ISNUMBER(SEARCH("META",B9&C9)),"METABEAST",IF(ISNUMBER(SEARCH("NOIZYBEAST",B9&C9)),"NOIZYBEAST",IF(ISNUMBER(SEARCH("BEAST",B9&C9)),"NOIZYBEAST",IF(ISNUMBER(SEARCH("NA_",B9&C9)),"NOIZYANTHROPIC",IF(ISNUMBER(SEARCH("NB_",B9&C9)),"NOIZYBEAST",IF(ISNUMBER(SEARCH("MB_",B9&C9)),"METABEAST","—"))))))))) | J9: =IF($B9="","",IF(OR(ISNUMBER(SEARCH("NOIZYANTHROPIC",B9&C9)),ISNUMBER(SEARCH("METABEAST",B9&C9)),ISNUMBER(SEARCH("NOIZYBEAST",B9&C9))),"High",IF(I9="—","—","Low"))) | L9: =IF($B9="","",IF(OR(ISNUMBER(SEARCH(".wav",B9)),ISNUMBER(SEARCH(".aif",B9)),ISNUMBER(SEARCH(".flac",B9)),ISNUMBER(SEARCH(".mp3",B9)),ISNUMBER(SEARCH(".ogg",B9)),ISNUMBER(SEARCH(".caf",B9))),"Audio",IF(H9="N","Orphan-Review","Data"))) | M9: =IF($B9="","",IF(I9="NOIZYANTHROPIC","/Pristine/NOIZYANTHROPIC/",IF(I9="NOIZYBEAST","/Pristine/NOIZYBEAST/",IF(I9="METABEAST","/Pristine/METABEAST/","/Pristine/_UNSORTED/")))) | N9: =IF($B9="","",IF(G9="","",COUNTIF($G$4:$G$1000,G9))) | O9: =IF($B9="","",IF(G9="","",IF(N9>1,"DUP","unique"))) | P9: =IF($B9="","",IF(K9="","",COUNTIF($K$4:$K$1000,K9))) | U9: Duplicates | V9: =COUNTIF($O$4:$O$1000,"DUP") -> 2 | X9: =IF($B9="","",IF($W9="Y","✅ SAFE TO MOVE","🔒 DO NOT DELETE — not 3-2-1"))
H10: =IF($B10="","",IF(E10="","N","Y")) | I10: =IF($B10="","",IF(ISNUMBER(SEARCH("NOIZYANTHROPIC",B10&C10)),"NOIZYANTHROPIC",IF(ISNUMBER(SEARCH("METABEAST",B10&C10)),"METABEAST",IF(ISNUMBER(SEARCH("META",B10&C10)),"METABEAST",IF(ISNUMBER(SEARCH("NOIZYBEAST",B10&C10)),"NOIZYBEAST",IF(ISNUMBER(SEARCH("BEAST",B10&C10)),"NOIZYBEAST",IF(ISNUMBER(SEARCH("NA_",B10&C10)),"NOIZYANTHROPIC",IF(ISNUMBER(SEARCH("NB_",B10&C10)),"NOIZYBEAST",IF(ISNUMBER(SEARCH("MB_",B10&C10)),"METABEAST","—"))))))))) | J10: =IF($B10="","",IF(OR(ISNUMBER(SEARCH("NOIZYANTHROPIC",B10&C10)),ISNUMBER(SEARCH("METABEAST",B10&C10)),ISNUMBER(SEARCH("NOIZYBEAST",B10&C10))),"High",IF(I10="—","—","Low"))) | L10: =IF($B10="","",IF(OR(ISNUMBER(SEARCH(".wav",B10)),ISNUMBER(SEARCH(".aif",B10)),ISNUMBER(SEARCH(".flac",B10)),ISNUMBER(SEARCH(".mp3",B10)),ISNUMBER(SEARCH(".ogg",B10)),ISNUMBER(SEARCH(".caf",B10))),"Audio",IF(H10="N","Orphan-Review","Data"))) | M10: =IF($B10="","",IF(I10="NOIZYANTHROPIC","/Pristine/NOIZYANTHROPIC/",IF(I10="NOIZYBEAST","/Pristine/NOIZYBEAST/",IF(I10="METABEAST","/Pristine/METABEAST/","/Pristine/_UNSORTED/")))) | N10: =IF($B10="","",IF(G10="","",COUNTIF($G$4:$G$1000,G10))) | O10: =IF($B10="","",IF(G10="","",IF(N10>1,"DUP","unique"))) | P10: =IF($B10="","",IF(K10="","",COUNTIF($K$4:$K$1000,K10))) | U10: Unique | V10: =COUNTIF($O$4:$O$1000,"unique") -> 2 | X10: =IF($B10="","",IF($W10="Y","✅ SAFE TO MOVE","🔒 DO NOT DELETE — not 3-2-1"))
H11: =IF($B11="","",IF(E11="","N","Y")) | I11: =IF($B11="","",IF(ISNUMBER(SEARCH("NOIZYANTHROPIC",B11&C11)),"NOIZYANTHROPIC",IF(ISNUMBER(SEARCH("METABEAST",B11&C11)),"METABEAST",IF(ISNUMBER(SEARCH("META",B11&C11)),"METABEAST",IF(ISNUMBER(SEARCH("NOIZYBEAST",B11&C11)),"NOIZYBEAST",IF(ISNUMBER(SEARCH("BEAST",B11&C11)),"NOIZYBEAST",IF(ISNUMBER(SEARCH("NA_",B11&C11)),"NOIZYANTHROPIC",IF(ISNUMBER(SEARCH("NB_",B11&C11)),"NOIZYBEAST",IF(ISNUMBER(SEARCH("MB_",B11&C11)),"METABEAST","—"))))))))) | J11: =IF($B11="","",IF(OR(ISNUMBER(SEARCH("NOIZYANTHROPIC",B11&C11)),ISNUMBER(SEARCH("METABEAST",B11&C11)),ISNUMBER(SEARCH("NOIZYBEAST",B11&C11))),"High",IF(I11="—","—","Low"))) | L11: =IF($B11="","",IF(OR(ISNUMBER(SEARCH(".wav",B11)),ISNUMBER(SEARCH(".aif",B11)),ISNUMBER(SEARCH(".flac",B11)),ISNUMBER(SEARCH(".mp3",B11)),ISNUMBER(SEARCH(".ogg",B11)),ISNUMBER(SEARCH(".caf",B11))),"Audio",IF(H11="N","Orphan-Review","Data"))) | M11: =IF($B11="","",IF(I11="NOIZYANTHROPIC","/Pristine/NOIZYANTHROPIC/",IF(I11="NOIZYBEAST","/Pristine/NOIZYBEAST/",IF(I11="METABEAST","/Pristine/METABEAST/","/Pristine/_UNSORTED/")))) | N11: =IF($B11="","",IF(G11="","",COUNTIF($G$4:$G$1000,G11))) | O11: =IF($B11="","",IF(G11="","",IF(N11>1,"DUP","unique"))) | P11: =IF($B11="","",IF(K11="","",COUNTIF($K$4:$K$1000,K11))) | X11: =IF($B11="","",IF($W11="Y","✅ SAFE TO MOVE","🔒 DO NOT DELETE — not 3-2-1"))
H12: =IF($B12="","",IF(E12="","N","Y")) | I12: =IF($B12="","",IF(ISNUMBER(SEARCH("NOIZYANTHROPIC",B12&C12)),"NOIZYANTHROPIC",IF(ISNUMBER(SEARCH("METABEAST",B12&C12)),"METABEAST",IF(ISNUMBER(SEARCH("META",B12&C12)),"METABEAST",IF(ISNUMBER(SEARCH("NOIZYBEAST",B12&C12)),"NOIZYBEAST",IF(ISNUMBER(SEARCH("BEAST",B12&C12)),"NOIZYBEAST",IF(ISNUMBER(SEARCH("NA_",B12&C12)),"NOIZYANTHROPIC",IF(ISNUMBER(SEARCH("NB_",B12&C12)),"NOIZYBEAST",IF(ISNUMBER(SEARCH("MB_",B12&C12)),"METABEAST","—"))))))))) | J12: =IF($B12="","",IF(OR(ISNUMBER(SEARCH("NOIZYANTHROPIC",B12&C12)),ISNUMBER(SEARCH("METABEAST",B12&C12)),ISNUMBER(SEARCH("NOIZYBEAST",B12&C12))),"High",IF(I12="—","—","Low"))) | L12: =IF($B12="","",IF(OR(ISNUMBER(SEARCH(".wav",B12)),ISNUMBER(SEARCH(".aif",B12)),ISNUMBER(SEARCH(".flac",B12)),ISNUMBER(SEARCH(".mp3",B12)),ISNUMBER(SEARCH(".ogg",B12)),ISNUMBER(SEARCH(".caf",B12))),"Audio",IF(H12="N","Orphan-Review","Data"))) | M12: =IF($B12="","",IF(I12="NOIZYANTHROPIC","/Pristine/NOIZYANTHROPIC/",IF(I12="NOIZYBEAST","/Pristine/NOIZYBEAST/",IF(I12="METABEAST","/Pristine/METABEAST/","/Pristine/_UNSORTED/")))) | N12: =IF($B12="","",IF(G12="","",COUNTIF($G$4:$G$1000,G12))) | O12: =IF($B12="","",IF(G12="","",IF(N12>1,"DUP","unique"))) | P12: =IF($B12="","",IF(K12="","",COUNTIF($K$4:$K$1000,K12))) | X12: =IF($B12="","",IF($W12="Y","✅ SAFE TO MOVE","🔒 DO NOT DELETE — not 3-2-1"))
H13: =IF($B13="","",IF(E13="","N","Y")) | I13: =IF($B13="","",IF(ISNUMBER(SEARCH("NOIZYANTHROPIC",B13&C13)),"NOIZYANTHROPIC",IF(ISNUMBER(SEARCH("METABEAST",B13&C13)),"METABEAST",IF(ISNUMBER(SEARCH("META",B13&C13)),"METABEAST",IF(ISNUMBER(SEARCH("NOIZYBEAST",B13&C13)),"NOIZYBEAST",IF(ISNUMBER(SEARCH("BEAST",B13&C13)),"NOIZYBEAST",IF(ISNUMBER(SEARCH("NA_",B13&C13)),"NOIZYANTHROPIC",IF(ISNUMBER(SEARCH("NB_",B13&C13)),"NOIZYBEAST",IF(ISNUMBER(SEARCH("MB_",B13&C13)),"METABEAST","—"))))))))) | J13: =IF($B13="","",IF(OR(ISNUMBER(SEARCH("NOIZYANTHROPIC",B13&C13)),ISNUMBER(SEARCH("METABEAST",B13&C13)),ISNUMBER(SEARCH("NOIZYBEAST",B13&C13))),"High",IF(I13="—","—","Low"))) | L13: =IF($B13="","",IF(OR(ISNUMBER(SEARCH(".wav",B13)),ISNUMBER(SEARCH(".aif",B13)),ISNUMBER(SEARCH(".flac",B13)),ISNUMBER(SEARCH(".mp3",B13)),ISNUMBER(SEARCH(".ogg",B13)),ISNUMBER(SEARCH(".caf",B13))),"Audio",IF(H13="N","Orphan-Review","Data"))) | M13: =IF($B13="","",IF(I13="NOIZYANTHROPIC","/Pristine/NOIZYANTHROPIC/",IF(I13="NOIZYBEAST","/Pristine/NOIZYBEAST/",IF(I13="METABEAST","/Pristine/METABEAST/","/Pristine/_UNSORTED/")))) | N13: =IF($B13="","",IF(G13="","",COUNTIF($G$4:$G$1000,G13))) | O13: =IF($B13="","",IF(G13="","",IF(N13>1,"DUP","unique"))) | P13: =IF($B13="","",IF(K13="","",COUNTIF($K$4:$K$1000,K13))) | X13: =IF($B13="","",IF($W13="Y","✅ SAFE TO MOVE","🔒 DO NOT DELETE — not 3-2-1"))
H14: =IF($B14="","",IF(E14="","N","Y")) | I14: =IF($B14="","",IF(ISNUMBER(SEARCH("NOIZYANTHROPIC",B14&C14)),"NOIZYANTHROPIC",IF(ISNUMBER(SEARCH("METABEAST",B14&C14)),"METABEAST",IF(ISNUMBER(SEARCH("META",B14&C14)),"METABEAST",IF(ISNUMBER(SEARCH("NOIZYBEAST",B14&C14)),"NOIZYBEAST",IF(ISNUMBER(SEARCH("BEAST",B14&C14)),"NOIZYBEAST",IF(ISNUMBER(SEARCH("NA_",B14&C14)),"NOIZYANTHROPIC",IF(ISNUMBER(SEARCH("NB_",B14&C14)),"NOIZYBEAST",IF(ISNUMBER(SEARCH("MB_",B14&C14)),"METABEAST","—"))))))))) | J14: =IF($B14="","",IF(OR(ISNUMBER(SEARCH("NOIZYANTHROPIC",B14&C14)),ISNUMBER(SEARCH("METABEAST",B14&C14)),ISNUMBER(SEARCH("NOIZYBEAST",B14&C14))),"High",IF(I14="—","—","Low"))) | L14: =IF($B14="","",IF(OR(ISNUMBER(SEARCH(".wav",B14)),ISNUMBER(SEARCH(".aif",B14)),ISNUMBER(SEARCH(".flac",B14)),ISNUMBER(SEARCH(".mp3",B14)),ISNUMBER(SEARCH(".ogg",B14)),ISNUMBER(SEARCH(".caf",B14))),"Audio",IF(H14="N","Orphan-Review","Data"))) | M14: =IF($B14="","",IF(I14="NOIZYANTHROPIC","/Pristine/NOIZYANTHROPIC/",IF(I14="NOIZYBEAST","/Pristine/NOIZYBEAST/",IF(I14="METABEAST","/Pristine/METABEAST/","/Pristine/_UNSORTED/")))) | N14: =IF($B14="","",IF(G14="","",COUNTIF($G$4:$G$1000,G14))) | O14: =IF($B14="","",IF(G14="","",IF(N14>1,"DUP","unique"))) | P14: =IF($B14="","",IF(K14="","",COUNTIF($K$4:$K$1000,K14))) | X14: =IF($B14="","",IF($W14="Y","✅ SAFE TO MOVE","🔒 DO NOT DELETE — not 3-2-1"))
H15: =IF($B15="","",IF(E15="","N","Y")) | I15: =IF($B15="","",IF(ISNUMBER(SEARCH("NOIZYANTHROPIC",B15&C15)),"NOIZYANTHROPIC",IF(ISNUMBER(SEARCH("METABEAST",B15&C15)),"METABEAST",IF(ISNUMBER(SEARCH("META",B15&C15)),"METABEAST",IF(ISNUMBER(SEARCH("NOIZYBEAST",B15&C15)),"NOIZYBEAST",IF(ISNUMBER(SEARCH("BEAST",B15&C15)),"NOIZYBEAST",IF(ISNUMBER(SEARCH("NA_",B15&C15)),"NOIZYANTHROPIC",IF(ISNUMBER(SEARCH("NB_",B15&C15)),"NOIZYBEAST",IF(ISNUMBER(SEARCH("MB_",B15&C15)),"METABEAST","—"))))))))) | J15: =IF($B15="","",IF(OR(ISNUMBER(SEARCH("NOIZYANTHROPIC",B15&C15)),ISNUMBER(SEARCH("METABEAST",B15&C15)),ISNUMBER(SEARCH("NOIZYBEAST",B15&C15))),"High",IF(I15="—","—","Low"))) | L15: =IF($B15="","",IF(OR(ISNUMBER(SEARCH(".wav",B15)),ISNUMBER(SEARCH(".aif",B15)),ISNUMBER(SEARCH(".flac",B15)),ISNUMBER(SEARCH(".mp3",B15)),ISNUMBER(SEARCH(".ogg",B15)),ISNUMBER(SEARCH(".caf",B15))),"Audio",IF(H15="N","Orphan-Review","Data"))) | M15: =IF($B15="","",IF(I15="NOIZYANTHROPIC","/Pristine/NOIZYANTHROPIC/",IF(I15="NOIZYBEAST","/Pristine/NOIZYBEAST/",IF(I15="METABEAST","/Pristine/METABEAST/","/Pristine/_UNSORTED/")))) | N15: =IF($B15="","",IF(G15="","",COUNTIF($G$4:$G$1000,G15))) | O15: =IF($B15="","",IF(G15="","",IF(N15>1,"DUP","unique"))) | P15: =IF($B15="","",IF(K15="","",COUNTIF($K$4:$K$1000,K15))) | X15: =IF($B15="","",IF($W15="Y","✅ SAFE TO MOVE","🔒 DO NOT DELETE — not 3-2-1"))
H16: =IF($B16="","",IF(E16="","N","Y")) | I16: =IF($B16="","",IF(ISNUMBER(SEARCH("NOIZYANTHROPIC",B16&C16)),"NOIZYANTHROPIC",IF(ISNUMBER(SEARCH("METABEAST",B16&C16)),"METABEAST",IF(ISNUMBER(SEARCH("META",B16&C16)),"METABEAST",IF(ISNUMBER(SEARCH("NOIZYBEAST",B16&C16)),"NOIZYBEAST",IF(ISNUMBER(SEARCH("BEAST",B16&C16)),"NOIZYBEAST",IF(ISNUMBER(SEARCH("NA_",B16&C16)),"NOIZYANTHROPIC",IF(ISNUMBER(SEARCH("NB_",B16&C16)),"NOIZYBEAST",IF(ISNUMBER(SEARCH("MB_",B16&C16)),"METABEAST","—"))))))))) | J16: =IF($B16="","",IF(OR(ISNUMBER(SEARCH("NOIZYANTHROPIC",B16&C16)),ISNUMBER(SEARCH("METABEAST",B16&C16)),ISNUMBER(SEARCH("NOIZYBEAST",B16&C16))),"High",IF(I16="—","—","Low"))) | L16: =IF($B16="","",IF(OR(ISNUMBER(SEARCH(".wav",B16)),ISNUMBER(SEARCH(".aif",B16)),ISNUMBER(SEARCH(".flac",B16)),ISNUMBER(SEARCH(".mp3",B16)),ISNUMBER(SEARCH(".ogg",B16)),ISNUMBER(SEARCH(".caf",B16))),"Audio",IF(H16="N","Orphan-Review","Data"))) | M16: =IF($B16="","",IF(I16="NOIZYANTHROPIC","/Pristine/NOIZYANTHROPIC/",IF(I16="NOIZYBEAST","/Pristine/NOIZYBEAST/",IF(I16="METABEAST","/Pristine/METABEAST/","/Pristine/_UNSORTED/")))) | N16: =IF($B16="","",IF(G16="","",COUNTIF($G$4:$G$1000,G16))) | O16: =IF($B16="","",IF(G16="","",IF(N16>1,"DUP","unique"))) | P16: =IF($B16="","",IF(K16="","",COUNTIF($K$4:$K$1000,K16))) | X16: =IF($B16="","",IF($W16="Y","✅ SAFE TO MOVE","🔒 DO NOT DELETE — not 3-2-1"))
H17: =IF($B17="","",IF(E17="","N","Y")) | I17: =IF($B17="","",IF(ISNUMBER(SEARCH("NOIZYANTHROPIC",B17&C17)),"NOIZYANTHROPIC",IF(ISNUMBER(SEARCH("METABEAST",B17&C17)),"METABEAST",IF(ISNUMBER(SEARCH("META",B17&C17)),"METABEAST",IF(ISNUMBER(SEARCH("NOIZYBEAST",B17&C17)),"NOIZYBEAST",IF(ISNUMBER(SEARCH("BEAST",B17&C17)),"NOIZYBEAST",IF(ISNUMBER(SEARCH("NA_",B17&C17)),"NOIZYANTHROPIC",IF(ISNUMBER(SEARCH("NB_",B17&C17)),"NOIZYBEAST",IF(ISNUMBER(SEARCH("MB_",B17&C17)),"METABEAST","—"))))))))) | J17: =IF($B17="","",IF(OR(ISNUMBER(SEARCH("NOIZYANTHROPIC",B17&C17)),ISNUMBER(SEARCH("METABEAST",B17&C17)),ISNUMBER(SEARCH("NOIZYBEAST",B17&C17))),"High",IF(I17="—","—","Low"))) | L17: =IF($B17="","",IF(OR(ISNUMBER(SEARCH(".wav",B17)),ISNUMBER(SEARCH(".aif",B17)),ISNUMBER(SEARCH(".flac",B17)),ISNUMBER(SEARCH(".mp3",B17)),ISNUMBER(SEARCH(".ogg",B17)),ISNUMBER(SEARCH(".caf",B17))),"Audio",IF(H17="N","Orphan-Review","Data"))) | M17: =IF($B17="","",IF(I17="NOIZYANTHROPIC","/Pristine/NOIZYANTHROPIC/",IF(I17="NOIZYBEAST","/Pristine/NOIZYBEAST/",IF(I17="METABEAST","/Pristine/METABEAST/","/Pristine/_UNSORTED/")))) | N17: =IF($B17="","",IF(G17="","",COUNTIF($G$4:$G$1000,G17))) | O17: =IF($B17="","",IF(G17="","",IF(N17>1,"DUP","unique"))) | P17: =IF($B17="","",IF(K17="","",COUNTIF($K$4:$K$1000,K17))) | X17: =IF($B17="","",IF($W17="Y","✅ SAFE TO MOVE","🔒 DO NOT DELETE — not 3-2-1"))
H18: =IF($B18="","",IF(E18="","N","Y")) | I18: =IF($B18="","",IF(ISNUMBER(SEARCH("NOIZYANTHROPIC",B18&C18)),"NOIZYANTHROPIC",IF(ISNUMBER(SEARCH("METABEAST",B18&C18)),"METABEAST",IF(ISNUMBER(SEARCH("META",B18&C18)),"METABEAST",IF(ISNUMBER(SEARCH("NOIZYBEAST",B18&C18)),"NOIZYBEAST",IF(ISNUMBER(SEARCH("BEAST",B18&C18)),"NOIZYBEAST",IF(ISNUMBER(SEARCH("NA_",B18&C18)),"NOIZYANTHROPIC",IF(ISNUMBER(SEARCH("NB_",B18&C18)),"NOIZYBEAST",IF(ISNUMBER(SEARCH("MB_",B18&C18)),"METABEAST","—"))))))))) | J18: =IF($B18="","",IF(OR(ISNUMBER(SEARCH("NOIZYANTHROPIC",B18&C18)),ISNUMBER(SEARCH("METABEAST",B18&C18)),ISNUMBER(SEARCH("NOIZYBEAST",B18&C18))),"High",IF(I18="—","—","Low"))) | L18: =IF($B18="","",IF(OR(ISNUMBER(SEARCH(".wav",B18)),ISNUMBER(SEARCH(".aif",B18)),ISNUMBER(SEARCH(".flac",B18)),ISNUMBER(SEARCH(".mp3",B18)),ISNUMBER(SEARCH(".ogg",B18)),ISNUMBER(SEARCH(".caf",B18))),"Audio",IF(H18="N","Orphan-Review","Data"))) | M18: =IF($B18="","",IF(I18="NOIZYANTHROPIC","/Pristine/NOIZYANTHROPIC/",IF(I18="NOIZYBEAST","/Pristine/NOIZYBEAST/",IF(I18="METABEAST","/Pristine/METABEAST/","/Pristine/_UNSORTED/")))) | N18: =IF($B18="","",IF(G18="","",COUNTIF($G$4:$G$1000,G18))) | O18: =IF($B18="","",IF(G18="","",IF(N18>1,"DUP","unique"))) | P18: =IF($B18="","",IF(K18="","",COUNTIF($K$4:$K$1000,K18))) | X18: =IF($B18="","",IF($W18="Y","✅ SAFE TO MOVE","🔒 DO NOT DELETE — not 3-2-1"))
H19: =IF($B19="","",IF(E19="","N","Y")) | I19: =IF($B19="","",IF(ISNUMBER(SEARCH("NOIZYANTHROPIC",B19&C19)),"NOIZYANTHROPIC",IF(ISNUMBER(SEARCH("METABEAST",B19&C19)),"METABEAST",IF(ISNUMBER(SEARCH("META",B19&C19)),"METABEAST",IF(ISNUMBER(SEARCH("NOIZYBEAST",B19&C19)),"NOIZYBEAST",IF(ISNUMBER(SEARCH("BEAST",B19&C19)),"NOIZYBEAST",IF(ISNUMBER(SEARCH("NA_",B19&C19)),"NOIZYANTHROPIC",IF(ISNUMBER(SEARCH("NB_",B19&C19)),"NOIZYBEAST",IF(ISNUMBER(SEARCH("MB_",B19&C19)),"METABEAST","—"))))))))) | J19: =IF($B19="","",IF(OR(ISNUMBER(SEARCH("NOIZYANTHROPIC",B19&C19)),ISNUMBER(SEARCH("METABEAST",B19&C19)),ISNUMBER(SEARCH("NOIZYBEAST",B19&C19))),"High",IF(I19="—","—","Low"))) | L19: =IF($B19="","",IF(OR(ISNUMBER(SEARCH(".wav",B19)),ISNUMBER(SEARCH(".aif",B19)),ISNUMBER(SEARCH(".flac",B19)),ISNUMBER(SEARCH(".mp3",B19)),ISNUMBER(SEARCH(".ogg",B19)),ISNUMBER(SEARCH(".caf",B19))),"Audio",IF(H19="N","Orphan-Review","Data"))) | M19: =IF($B19="","",IF(I19="NOIZYANTHROPIC","/Pristine/NOIZYANTHROPIC/",IF(I19="NOIZYBEAST","/Pristine/NOIZYBEAST/",IF(I19="METABEAST","/Pristine/METABEAST/","/Pristine/_UNSORTED/")))) | N19: =IF($B19="","",IF(G19="","",COUNTIF($G$4:$G$1000,G19))) | O19: =IF($B19="","",IF(G19="","",IF(N19>1,"DUP","unique"))) | P19: =IF($B19="","",IF(K19="","",COUNTIF($K$4:$K$1000,K19))) | X19: =IF($B19="","",IF($W19="Y","✅ SAFE TO MOVE","🔒 DO NOT DELETE — not 3-2-1"))
H20: =IF($B20="","",IF(E20="","N","Y")) | I20: =IF($B20="","",IF(ISNUMBER(SEARCH("NOIZYANTHROPIC",B20&C20)),"NOIZYANTHROPIC",IF(ISNUMBER(SEARCH("METABEAST",B20&C20)),"METABEAST",IF(ISNUMBER(SEARCH("META",B20&C20)),"METABEAST",IF(ISNUMBER(SEARCH("NOIZYBEAST",B20&C20)),"NOIZYBEAST",IF(ISNUMBER(SEARCH("BEAST",B20&C20)),"NOIZYBEAST",IF(ISNUMBER(SEARCH("NA_",B20&C20)),"NOIZYANTHROPIC",IF(ISNUMBER(SEARCH("NB_",B20&C20)),"NOIZYBEAST",IF(ISNUMBER(SEARCH("MB_",B20&C20)),"METABEAST","—"))))))))) | J20: =IF($B20="","",IF(OR(ISNUMBER(SEARCH("NOIZYANTHROPIC",B20&C20)),ISNUMBER(SEARCH("METABEAST",B20&C20)),ISNUMBER(SEARCH("NOIZYBEAST",B20&C20))),"High",IF(I20="—","—","Low"))) | L20: =IF($B20="","",IF(OR(ISNUMBER(SEARCH(".wav",B20)),ISNUMBER(SEARCH(".aif",B20)),ISNUMBER(SEARCH(".flac",B20)),ISNUMBER(SEARCH(".mp3",B20)),ISNUMBER(SEARCH(".ogg",B20)),ISNUMBER(SEARCH(".caf",B20))),"Audio",IF(H20="N","Orphan-Review","Data"))) | M20: =IF($B20="","",IF(I20="NOIZYANTHROPIC","/Pristine/NOIZYANTHROPIC/",IF(I20="NOIZYBEAST","/Pristine/NOIZYBEAST/",IF(I20="METABEAST","/Pristine/METABEAST/","/Pristine/_UNSORTED/")))) | N20: =IF($B20="","",IF(G20="","",COUNTIF($G$4:$G$1000,G20))) | O20: =IF($B20="","",IF(G20="","",IF(N20>1,"DUP","unique"))) | P20: =IF($B20="","",IF(K20="","",COUNTIF($K$4:$K$1000,K20))) | X20: =IF($B20="","",IF($W20="Y","✅ SAFE TO MOVE","🔒 DO NOT DELETE — not 3-2-1"))
H21: =IF($B21="","",IF(E21="","N","Y")) | I21: =IF($B21="","",IF(ISNUMBER(SEARCH("NOIZYANTHROPIC",B21&C21)),"NOIZYANTHROPIC",IF(ISNUMBER(SEARCH("METABEAST",B21&C21)),"METABEAST",IF(ISNUMBER(SEARCH("META",B21&C21)),"METABEAST",IF(ISNUMBER(SEARCH("NOIZYBEAST",B21&C21)),"NOIZYBEAST",IF(ISNUMBER(SEARCH("BEAST",B21&C21)),"NOIZYBEAST",IF(ISNUMBER(SEARCH("NA_",B21&C21)),"NOIZYANTHROPIC",IF(ISNUMBER(SEARCH("NB_",B21&C21)),"NOIZYBEAST",IF(ISNUMBER(SEARCH("MB_",B21&C21)),"METABEAST","—"))))))))) | J21: =IF($B21="","",IF(OR(ISNUMBER(SEARCH("NOIZYANTHROPIC",B21&C21)),ISNUMBER(SEARCH("METABEAST",B21&C21)),ISNUMBER(SEARCH("NOIZYBEAST",B21&C21))),"High",IF(I21="—","—","Low"))) | L21: =IF($B21="","",IF(OR(ISNUMBER(SEARCH(".wav",B21)),ISNUMBER(SEARCH(".aif",B21)),ISNUMBER(SEARCH(".flac",B21)),ISNUMBER(SEARCH(".mp3",B21)),ISNUMBER(SEARCH(".ogg",B21)),ISNUMBER(SEARCH(".caf",B21))),"Audio",IF(H21="N","Orphan-Review","Data"))) | M21: =IF($B21="","",IF(I21="NOIZYANTHROPIC","/Pristine/NOIZYANTHROPIC/",IF(I21="NOIZYBEAST","/Pristine/NOIZYBEAST/",IF(I21="METABEAST","/Pristine/METABEAST/","/Pristine/_UNSORTED/")))) | N21: =IF($B21="","",IF(G21="","",COUNTIF($G$4:$G$1000,G21))) | O21: =IF($B21="","",IF(G21="","",IF(N21>1,"DUP","unique"))) | P21: =IF($B21="","",IF(K21="","",COUNTIF($K$4:$K$1000,K21))) | X21: =IF($B21="","",IF($W21="Y","✅ SAFE TO MOVE","🔒 DO NOT DELETE — not 3-2-1"))
H22: =IF($B22="","",IF(E22="","N","Y")) | I22: =IF($B22="","",IF(ISNUMBER(SEARCH("NOIZYANTHROPIC",B22&C22)),"NOIZYANTHROPIC",IF(ISNUMBER(SEARCH("METABEAST",B22&C22)),"METABEAST",IF(ISNUMBER(SEARCH("META",B22&C22)),"METABEAST",IF(ISNUMBER(SEARCH("NOIZYBEAST",B22&C22)),"NOIZYBEAST",IF(ISNUMBER(SEARCH("BEAST",B22&C22)),"NOIZYBEAST",IF(ISNUMBER(SEARCH("NA_",B22&C22)),"NOIZYANTHROPIC",IF(ISNUMBER(SEARCH("NB_",B22&C22)),"NOIZYBEAST",IF(ISNUMBER(SEARCH("MB_",B22&C22)),"METABEAST","—"))))))))) | J22: =IF($B22="","",IF(OR(ISNUMBER(SEARCH("NOIZYANTHROPIC",B22&C22)),ISNUMBER(SEARCH("METABEAST",B22&C22)),ISNUMBER(SEARCH("NOIZYBEAST",B22&C22))),"High",IF(I22="—","—","Low"))) | L22: =IF($B22="","",IF(OR(ISNUMBER(SEARCH(".wav",B22)),ISNUMBER(SEARCH(".aif",B22)),ISNUMBER(SEARCH(".flac",B22)),ISNUMBER(SEARCH(".mp3",B22)),ISNUMBER(SEARCH(".ogg",B22)),ISNUMBER(SEARCH(".caf",B22))),"Audio",IF(H22="N","Orphan-Review","Data"))) | M22: =IF($B22="","",IF(I22="NOIZYANTHROPIC","/Pristine/NOIZYANTHROPIC/",IF(I22="NOIZYBEAST","/Pristine/NOIZYBEAST/",IF(I22="METABEAST","/Pristine/METABEAST/","/Pristine/_UNSORTED/")))) | N22: =IF($B22="","",IF(G22="","",COUNTIF($G$4:$G$1000,G22))) | O22: =IF($B22="","",IF(G22="","",IF(N22>1,"DUP","unique"))) | P22: =IF($B22="","",IF(K22="","",COUNTIF($K$4:$K$1000,K22))) | X22: =IF($B22="","",IF($W22="Y","✅ SAFE TO MOVE","🔒 DO NOT DELETE — not 3-2-1"))
... H200: =IF($B200="","",IF(E200="","N","Y")) | I200: =IF($B200="","",IF(ISNUMBER(SEARCH("NOIZYANTHROPIC",B200&C200)),"NOIZYANTHROPIC",IF(ISNUMBER(SEARCH("METABEAST",B200&C200)),"METABEAST",IF(ISNUMBER(SEARCH("META",B200&C200)),"METABEAST",IF(ISNUMBER(SEARCH("NOIZYBEAST",B200&C200)),"NOIZYBEAST",IF(ISNUMBER(SEARCH("BEAST",B200&C200)),"NOIZYBEAST",IF(ISNUMBER(SEARCH("NA_",B200&C200)),"NOIZYANTHROPIC",IF(ISNUMBER(SEARCH("NB_",B200&C200)),"NOIZYBEAST",IF(ISNUMBER(SEARCH("MB_",B200&C200)),"METABEAST","—"))))))))) | J200: =IF($B200="","",IF(OR(ISNUMBER(SEARCH("NOIZYANTHROPIC",B200&C200)),ISNUMBER(SEARCH("METABEAST",B200&C200)),ISNUMBER(SEARCH("NOIZYBEAST",B200&C200))),"High",IF(I200="—","—","Low"))) | L200: =IF($B200="","",IF(OR(ISNUMBER(SEARCH(".wav",B200)),ISNUMBER(SEARCH(".aif",B200)),ISNUMBER(SEARCH(".flac",B200)),ISNUMBER(SEARCH(".mp3",B200)),ISNUMBER(SEARCH(".ogg",B200)),ISNUMBER(SEARCH(".caf",B200))),"Audio",IF(H200="N","Orphan-Review","Data"))) | M200: =IF($B200="","",IF(I200="NOIZYANTHROPIC","/Pristine/NOIZYANTHROPIC/",IF(I200="NOIZYBEAST","/Pristine/NOIZYBEAST/",IF(I200="METABEAST","/Pristine/METABEAST/","/Pristine/_UNSORTED/")))) | N200: =IF($B200="","",IF(G200="","",COUNTIF($G$4:$G$1000,G200))) | O200: =IF($B200="","",IF(G200="","",IF(N200>1,"DUP","unique"))) | P200: =IF($B200="","",IF(K200="","",COUNTIF($K$4:$K$1000,K200))) | X200: =IF($B200="","",IF($W200="Y","✅ SAFE TO MOVE","🔒 DO NOT DELETE — not 3-2-1"))

Sheet Search Hub
A1: SEARCH HUB — Wiki-Guided Query Builder
A2: Fill the yellow facet cells → ready-to-run search commands generate automatically below. Leave a facet blank to ignore it.
A3: 1 · SEARCH FACETS
A4: Brand | B4: NOIZYANTHROPIC
A5: Category / Type | B5: Drums
A6: Sub-Category | B6: Kick
A7: Character / Tag | B7: Punchy
A8: Vendor
A9: Project / Product | B9: DrumKit_Vol1
A10: BPM min
A11: BPM max
A12: Key
A13: Extension / Format | B13: wav
A14: License
A15: Free-text keyword
A16: Search root path | B16: /Volumes/Audio
A18: 2 · GENERATED QUERIES (copy → run)
A19: ripgrep | B19: ="rg -i --glob '*."&IF(B13="","*",B13)&"' -e "&_xlfn.TEXTJOIN(" -e ",TRUE,B4,B8,B9,B6,B15)&" "&B16 -> rg -i --glob '*.wav' -e NOIZYANTHROPIC -e DrumKit_Vol1 -e Kick /Volumes/Audio
A20: regex pattern | B20: =_xlfn.TEXTJOIN("|",TRUE,B4,B8,B9,B6,B15) -> NOIZYANTHROPIC|DrumKit_Vol1|Kick
A21: find | B21: ="find "&B16&" -type f"&IF(B13="",""," -iname '*."&B13&"'")&IF(B4="",""," -ipath '*"&B4&"*'")&IF(B9="",""," -ipath '*"&B9&"*'") -> find /Volumes/Audio -type f -iname '*.wav' -ipath '*NOIZYANTHROPIC*' -ipath '*DrumKit_Vol1*'
A22: DEVONsphere / DEVONthink | B22: =_xlfn.TEXTJOIN(" AND ",TRUE,IF(B4="","","name:"&B4),IF(B5="","","tag:"&B5),IF(B6="","","tag:"&B6),IF(B7="","","tag:"&B7),IF(B14="","","tag:"&B14),IF(B8="","","kind:"&B8)) -> name:NOIZYANTHROPIC AND tag:Drums AND tag:Kick AND tag:Punchy
A23: SQL WHERE | B23: ="SELECT * FROM samples WHERE 1=1"&IF(B4="",""," AND brand='"&B4&"'")&IF(B5="",""," AND category='"&B5&"'")&IF(B6="",""," AND subcategory='"&B6&"'")&IF(B7="",""," AND tags LIKE '%"&B7&"%'")&IF(B8="",""," AND vendor='"&B8&"'")&IF(B9="",""," AND project='"&B9&"'")&IF(B10="",""," AND bpm>="&B10)&IF(B11="",""," AND bpm<="&B11)&IF(B12="",""," AND key='"&B12&"'")&IF(B13="",""," AND ext='"&B13&"'")&IF(B14="",""," AND license='"&B14&"'") -> SELECT * FROM samples WHERE 1=1 AND brand='NOIZYANTHROPIC' AND category='Drums' AND subcategory='Kick' AND tags LIKE '%Punchy%' AND project='DrumKit_Vol1' AND ext='wav'
A24: Soundminer / Basehead | B24: =_xlfn.TEXTJOIN(" ",TRUE,B4,B6,B7,B15) -> NOIZYANTHROPIC Kick Punchy
A25: mdfind (Spotlight) | B25: ="mdfind -onlyin "&B16&" "&CHAR(34)&_xlfn.TEXTJOIN(" && ",TRUE,IF(B15="","","kMDItemTextContent == '*"&B15&"*'"),IF(B4="","","kMDItemFSName == '*"&B4&"*'"))&CHAR(34) -> mdfind -onlyin /Volumes/Audio "kMDItemFSName == '*NOIZYANTHROPIC*'"
A27: 3 · WIKI SEARCH RECIPES (pre-built — copy the command)
A28: Recipe | B28: What it finds | C28: Ready-to-run command
A29: Orphans (no extension) | B29: Files with no ext needing magic-byte ID | C29: rg --files /Volumes/Audio | rg -v '\.'
A30: Cross-folder duplicates | B30: Byte-identical files in different folders | C30: fdupes -r /Volumes/Audio
A31: Brand masters | B31: All pristine files for one brand | C31: find /Volumes/Audio/Pristine/NOIZYANTHROPIC -type f
A32: Untagged audio | B32: Audio missing embedded metadata | C32: exiftool -if 'not $iXML' -r /Volumes/Audio
A33: Vendor catalog | B33: Every file under a vendor path | C33: find /Volumes/Audio -ipath '*Spitfire*'
A34: Corrupt WAVs | B34: Files failing a header/decode check | C34: for f in **/*.wav; do sox --i "$f" >/dev/null 2>&1 || echo "$f"; done
A35: Recently modified | B35: New/changed files in last 7 days | C35: find /Volumes/Audio -type f -mtime -7
A36: Foley & SFX | B36: Sound-effect content across brands | C36: rg -i -e foley -e sfx -e ambience /Volumes/Audio
A37: BPM-tagged loops | B37: Filenames carrying a BPM token | C37: rg -io '[0-9]{2,3} bpm' /Volumes/Audio
A38: Sampler patches | B38: Kontakt / EXS instrument files | C38: find /Volumes/Audio -iname '*.nki' -o -iname '*.exs'
A39: Zero-byte junk | B39: Empty files to purge | C39: find /Volumes/Audio -type f -size 0
A40: Data blobs among audio | B40: Sidecar/data files mixed in | C40: rg --files /Volumes/Audio | rg -i '\.(json|txt|xml|cue|md5)$'

Sheet Dashboard
A1: MC96 ECOUNIVERSE — CONTROL CENTER
A2: Live roll-up across all catalog sheets · figures update as the Scan Queue fills
A4: SCAN QUEUE / PIPELINE
B5: Files Queued | D5: Audio Files | F5: Orphans to Review | H5: Duplicates
B6: ='Scan Queue'!V2 -> 4 | D6: ='Scan Queue'!V7 -> 3 | F6: ='Scan Queue'!V8 -> 1 | H6: ='Scan Queue'!V9 -> 2
A8: BY BRAND
B9: NOIZYANTHROPIC | D9: NOIZYBEAST | F9: METABEAST | H9: Unsorted
B10: ='Scan Queue'!V3 -> 2 | D10: ='Scan Queue'!V4 -> 0 | F10: ='Scan Queue'!V5 -> 1 | H10: ='Scan Queue'!V6 -> 1
A12: LIBRARY INVENTORY
B13: Total Libraries | D13: Commercial | F13: Untouched
B14: ='Library Index'!AA2 -> 20 | D14: ='Library Index'!AA3 -> 20 | F14: ='Library Index'!AA4 -> 20
A16: INTEGRITY & DEDUP
B17: Files Tracked | D17: Duplicates | F17: Corrupt | H17: Rebuild Needed
B18: =Integrity!AA2 -> 5 | D18: =Integrity!AA3 -> 1 | F18: =Integrity!AA4 -> 1 | H18: =Integrity!AA5 -> 1
B19: Verified
B20: =Integrity!AA6 -> 3
A22: STORAGE / DISTRIBUTION
B23: Capacity (GB) | D23: Used (GB) | F23: Free (GB) | H23: % Full
B24: =Distribution!F11 -> 126000 | D24: =Distribution!G11 -> 0 | F24: =Distribution!H11 -> 126000 | H24: =IF(Distribution!F11=0,0,Distribution!G11/Distribution!F11) -> 0

Sheet Rights & Licensing
A1: RIGHTS & LICENSING REGISTER
A2: Clearance & usage rights per library / brand — the legal backbone for commercial release, resale, and redistribution
A3: Rights ID | B3: Asset / Lib ID | C3: Asset / Library Name | D3: License Type | E3: Rights Holder | F3: Commercial Use? | G3: Redistribute? | H3: Resale? | I3: Attribution? | J3: Exclusive? | K3: Territory | L3: Term | M3: Royalty / Fee | N3: Clearance Status | O3: Contract / Doc Ref | P3: Acquired From | Q3: Date Acquired | R3: Notes
A4: RT-001 | B4: BR-001 | C4: NOIZYANTHROPIC (house brand) | D4: Proprietary / Owned | E4: NOIZYANTHROPIC | F4: Y | G4: Y | H4: Y | I4: N | J4: Y | K4: Worldwide | L4: Perpetual | M4: — | N4: Cleared | O4: Internal / self-produced | P4: In-house | Q4: — | R4: Full ownership — all rights reserved, freely sellable
A5: RT-002 | B5: BR-002 | C5: NOIZYBEAST (house brand) | D5: Proprietary / Owned | E5: NOIZYBEAST | F5: Y | G5: Y | H5: Y | I5: N | J5: Y | K5: Worldwide | L5: Perpetual | M5: — | N5: Cleared | O5: Internal / self-produced | P5: In-house | Q5: — | R5: Full ownership — all rights reserved, freely sellable
A6: RT-003 | B6: BR-003 | C6: METABEAST (house brand) | D6: Proprietary / Owned | E6: METABEAST | F6: Y | G6: Y | H6: Y | I6: N | J6: Y | K6: Worldwide | L6: Perpetual | M6: — | N6: Cleared | O6: Internal / self-produced | P6: In-house | Q6: — | R6: Full ownership — all rights reserved, freely sellable
A7: RT-010 | B7: LIB-001 | C7: Spitfire Albion ONE | D7: Commercial EULA | E7: Spitfire Audio | F7: Y | G7: N | H7: N | I7: N | J7: N | K7: Worldwide | L7: Perpetual | M7: Paid (one-time) | N7: Cleared | O7: Spitfire EULA | P7: Spitfire Audio | Q7: 45078 | R7: Use in productions OK; sample resale/redistribution PROHIBITED
A8: RT-011 | B8: LIB-005 | C8: BOOM Cinematic Trailers | D8: Royalty-Free | E8: BOOM Library | F8: Y | G8: N | H8: N | I8: N | J8: N | K8: Worldwide | L8: Perpetual | M8: Paid (one-time) | N8: Cleared | O8: BOOM RF License | P8: BOOM Library | Q8: 45184 | R8: Royalty-free in productions; cannot be redistributed as samples
A9: RT-012 | B9: LIB-008 | C9: Splice Sounds | D9: Subscription | E9: Splice | F9: Y | G9: N | H9: N | I9: N | J9: N | K9: Worldwide | L9: While subscribed | M9: Monthly sub | N9: Conditional | O9: Splice ToS | P9: Splice | Q9: ongoing | R9: Downloaded sounds stay licensed; verify active sub for new content
A10: RT-013 | B10: LIB-010 | C10: Cymatics Premium | D10: Royalty-Free | E10: Cymatics | F10: Y | G10: N | H10: N | I10: N | J10: N | K10: Worldwide | L10: Perpetual | M10: Paid / free packs | N10: Cleared | O10: Cymatics License | P10: Cymatics | Q10: 45311 | R10: RF in productions; no resale of raw samples
A11: RT-014 | B11: LIB-100 | C11: Client Project (work-for-hire) | D11: Work-for-Hire | E11: Client (per contract) | F11: Y | G11: N | H11: N | I11: N | J11: Y | K11: Per contract | L11: Per contract | M11: Project fee | N11: Restricted | O11: Client MSA / SOW | P11: Client | Q11: varies | R11: Ownership may transfer to client — confirm before reuse in brand catalog
A13: RULE: House brands (NOIZYANTHROPIC / NOIZYBEAST / METABEAST) = full ownership, freely sellable. Licensed/RF/Subscription content = usable in productions but NEVER resold or redistributed as raw samples. Work-for-hire may belong to the client.

Sheet System Wiki
A1: MC96 ECOUNIVERSE — SYSTEM WIKI
A2: The operating manual for this catalog & distribution workbook. Start here.
A4: 1 · WHAT THIS IS
A5: A single-source brain that catalogs every audio asset across NOIZYANTHROPIC, NOIZYBEAST & METABEAST (plus client work), routes each file to a pristine destination, tracks integrity & duplicates, records usage rights, and generates ready-to-run search commands. The workbook does NOT touch your drives — your scanner (Desktop Commander), SuperSonic IDE, LM Studio, TagSpaces & the DEVON suite do the file I/O; this workbook is the index, the router and the audit trail.
A7: 2 · SHEET DIRECTORY
A8: Sheet | B8: Purpose | C8: Key columns / features
A9: Dashboard | B9: Control-center cockpit — live KPI cards | C9: Pipeline, by-brand, library, integrity & storage roll-ups (pull single cells cross-sheet)
A10: Scan Queue | B10: Landing zone — paste scanner output here | C10: Paste A-G; auto-classify brand/dest/dup/project in H-P via same-row formulas
A11: Library Index | B11: Master inventory — one row per library | C11: 20 starter libs; roll-up helpers in AA col feed the Dashboard
A12: Samples | B12: Per-file catalog (granular) | C12: 41 cols incl orphan-detection (Has Ext?, magic bytes) + LLM hint cols
A13: Processing | B13: 10-stage pipeline tracker | C13: Stage checkboxes, tool/model used, % complete
A14: Integrity | B14: Hash, dedup & rebuild tracking | C14: SHA256, duplicate-of, corrupt/rebuild flags
A15: Distribution | B15: Target drives & capacity | C15: Free/used formulas, redundancy, per-brand destinations
A16: Brands | B16: Brand & client registry | C16: Grep patterns, prefixes, claim priority, destinations
A17: Identifiers | B17: Grep / signature pattern library (60 patterns) | C17: Magic bytes, formats, metadata chunks, naming tokens, exclusions — feeds LM Studio
A18: Tags | B18: Tag taxonomy | C18: TagSpaces slugs + DEVONthink labels per tag
A19: Vendors | B19: Commercial vendor reference | C19: Path/filename signatures, DRM type
... A22: System Wiki | B22: This manual | C22: Directory, pipeline, tool chain, conventions, gotchas
A24: 3 · THE PIPELINE (10 STAGES)
A25: Stage | B25: What happens | C25: Tool
A26: 1 Discover | B26: Walk drives, list every file (incl extensionless) | C26: Desktop Commander
A27: 2 Scan | B27: Read size, dates, extension; paste into Scan Queue | C27: Desktop Commander
A28: 3 Magic Bytes | B28: Identify orphan/extensionless files by signature | C28: Identifiers sheet + file/hexdump
A29: 4 LLM Name | B29: Suggest a human name + brand from path/content | C29: LM Studio (local model)
A30: 5 Tag | B30: Apply taxonomy tags (instrument/character/etc.) | C30: TagSpaces + Tags sheet
A31: 6 Clean / Rebuild | B31: Repair headers, re-encode, normalize | C31: SuperSonic IDE
A32: 7 Pristine Move | B32: Copy verified file to /Pristine/<brand>/ | C32: Desktop Commander + Distribution sheet
A33: 8 Index | B33: Add to knowledge base & full-text index | C33: DEVONthink / DEVONsphere
A34: 9 Cross-tag | B34: Sync tags across systems | C34: TagSpaces ↔ DEVONthink
A35: 10 Publish | B35: Make searchable in the working library | C35: Soundly / Soundminer
A37: 4 · TOOL CHAIN
A38: Desktop Commander = file I/O (walk, hash, move). SuperSonic IDE = audio clean/repair/learn. LM Studio = local LLM for naming & classification. TagSpaces = portable file tagging. DEVONthink/DEVONagent Pro/DEVONsphere = index, research, semantic search. Soundly/Soundminer = working sound library + metadata search. This workbook ties them together with shared IDs, grep patterns and destinations.
A40: 5 · CONVENTIONS
A41: ID schemes | B41: LIB-### libraries · SMP-###### samples · INT-###### integrity · RT-### rights · BR-### brands · DST-### destinations · ID-### identifiers · Q-#### scan-queue
A42: Brand codes | B42: NOIZYANTHROPIC (NA_, priority 1) · NOIZYBEAST (NB_, priority 2) · METABEAST (MB_, priority 3). METABEAST is matched before BEAST so it never misfiles as NOIZYBEAST.
A43: Destinations | B43: /Pristine/<brand>/ for claimed files · /Pristine/_UNSORTED/ for unknowns awaiting review
A44: Color coding | B44: Yellow = input cell you edit · Green header = paste/raw scanner data · Red = orphan / restricted / duplicate · Amber = needs review / conditional · Navy/blue = computed or reference
A45: Confidence | B45: High = exact brand/format match · Low = loose variant or prefix only (route to LLM review)
A47: 6 · GOTCHAS & RULES (READ BEFORE EDITING STRUCTURE)
A48: NEVER RENAME A SHEET | B48: On this Excel-for-Mac build, renaming a worksheet permanently breaks every cross-sheet formula that points at it (returns #REF!). Always create a sheet with its FINAL name. This is why the library tab is called 'Library Index', not 'Libraries' — the name 'Libraries' is permanently poisoned by an un-deletable hidden ghost sheet.
A49: NO cross-sheet COUNTIF | B49: COUNTIF / SUMPRODUCT / VLOOKUP across sheets fail here. Workaround in use: compute counts ON the source sheet (same-sheet COUNTIF works) in a helper column, then the Dashboard pulls that single result cell (single-cell cross-sheet refs DO work).
A50: Same-row formulas are safe | B50: Scan Queue brand/dest/type detection uses same-row SEARCH — 100% reliable. Dedup & project counts use same-sheet COUNTIF — also reliable.
A51: Hidden ghost sheets | B51: Libraries_OLD, Catalog, Library Catalog are broken, un-deletable remnants — left hidden (veryHidden). Ignore them; do not unhide or reference them.
A52: Manual steps | B52: Freeze panes occasionally needs doing by hand (View > Freeze Panes). The Project column on Scan Queue is a manual/LLM input, not a formula.
A54: 7 · ENGINE CONFIG — M2 ULTRA + LM STUDIO
A55: Hardware | B55: Mac Studio M2 Ultra, 192GB unified memory. Apple Silicon shares RAM across CPU/GPU/Neural Engine — the whole 192GB is addressable by the model.
A56: LM Studio backend | B56: Use the MLX runtime (Apple-Silicon native) over llama.cpp/GGUF for best tokens/sec. Set GPU offload to MAX (all layers).
A57: Model | B57: Run a large local model: Qwen2.5-72B-Instruct or Llama-3.3-70B (MLX 4-8bit). ~40-80GB resident — leaves ample headroom in 192GB for big context.
A58: Context window | B58: Push 16k-32k tokens. Feed the Identifiers 'LLM Prompt Hint' column as system context so the model knows every signature, prefix and naming token.
A59: Memory budget | B59: Keep model + context under ~150GB; leave ~40GB for the OS, scanner and DEVON suite running alongside. Do NOT swap.
A60: Role in pipeline | B60: LM Studio = Stage 4 (LLM Name) + Stage 5 (Tag): names orphan files from magic-bytes + path, proposes brand/category/character tags, grades audio quality (Q-Grade), writes its model name into the Samples 'LLM Model' + Naming Standard integrity stamp.
A61: Throughput tip | B61: Batch files in groups; keep the model resident (don't reload per file). Pin one model, stream filenames + Identifier hints as a single long prompt per batch.
A63: 8 · HOW TO CONNECT ME TO YOUR DRIVES (researched 2026-06-30)
A64: The problem | B64: This Excel session is sandboxed. Confirmed by live scans: Google Drive, Adobe Creative Cloud & Gmail all = 0 audio/video. Your media lives ONLY on local drives (12RB, MAG4TB, /Volumes/Audio) which no tool here can reach.
A65: The bridge: MCP | B65: Model Context Protocol — Anthropic's open standard, the 'USB-C port for AI'. A small server runs on YOUR Mac and gives Claude scoped, approval-gated access to your filesystem + terminal.
A66: Option A — Desktop Commander | B66: Most powerful (~25 tools: read/write/search files, run shell). Install: npx -y @wonderwhy-er/desktop-commander setup. NEW remote mode lets web/browser Claude reach your Mac: npx @wonderwhy-er/desktop-commander@latest remote + OAuth login.
A67: Option B — Filesystem MCP | B67: Official, simpler, no shell. Read/write scoped to folders you allow: @modelcontextprotocol/server-filesystem /Volumes/Audio
A68: Option C — Claude Desktop | B68: The host app (Mac/Win) that runs the above local servers. + menu -> Connectors -> add server, restart, approve each action.
A69: Option D — Claude Code | B69: Anthropic's CLI agent with full filesystem access, no MCP setup. Point it at /Volumes/Audio, run the scan, export the listing into this workbook's Scan Queue.
A70: Recommended for NoizyArmy | B70: Desktop Commander remote/OAuth so THIS assistant reaches your Mac directly — OR run the scan in Claude Desktop/Code and drop the file list into the Scan Queue. Either way the catalog, dedup, brand-routing & Clone ledger auto-fill.
A71: Security | B71: Every MCP action is approval-gated. Scope the server to ONLY /Volumes/Audio. Never expose a filesystem/shell MCP on a public port — OAuth or local stdio only.

Sheet Library Catalog
A1: Master Library Inventory | Z1: ROLL-UP
Z2: Total Libraries | AA2: =COUNTA(A4:A100) -> 20
A3: Lib ID | B3: Library Name | C3: Vendor / Developer | D3: Product Line | E3: Version | F3: Category | G3: Sub-Category | H3: Sample Format | I3: License Type | J3: Serial / Key | K3: Original Path | L3: Pristine Path | M3: Size (GB) | N3: # Files | O3: Has Metadata? | P3: Tagging System | Q3: Commercial? | R3: Date Acquired | S3: Date Scanned | T3: Date Processed | U3: Status | V3: DEVONthink DB | W3: TagSpaces Tagged? | X3: Notes | Z3: Commercial | AA3: =COUNTIF(Q4:Q100,"Y") -> 20
A4: LIB-001 | B4: Albion ONE | C4: Spitfire Audio | D4: Albion | E4: 1.6 | F4: Orchestral | G4: Cinematic Strings/Brass/Perc | H4: Kontakt | I4: Commercial | Q4: Y | U4: Untouched | Z4: Untouched | AA4: =COUNTIF(U4:U100,"Untouched") -> 20
A5: LIB-002 | B5: Damage 2 | C5: Heavyocity | D5: Damage | E5: 2 | F5: Cinematic Percussion | G5: Epic Drums | H5: Kontakt | I5: Commercial | Q5: Y | U5: Untouched | Z5: Total GB | AA5: =SUM(M4:M100) -> 0
A6: LIB-003 | B6: Komplete 14 Ultimate | C6: Native Instruments | D6: Komplete | E6: 14 | F6: Bundle | G6: Multi (Synths/Instruments/Effects) | H6: Kontakt / NKS | I6: Commercial | Q6: Y | U6: Untouched | Z6: Total Files | AA6: =SUM(N4:N100) -> 0
A7: LIB-004 | B7: Analog Brass & Winds | C7: Output | D7: Analog | E7: 1 | F7: Hybrid | G7: Brass/Winds | H7: Kontakt Player | I7: Commercial | Q7: Y | U7: Untouched
A8: LIB-005 | B8: BOOM Cinematic Trailers | C8: BOOM Library | D8: Cinematic | F8: SFX | G8: Trailer / Risers / Impacts | H8: WAV | I8: Royalty-Free | O8: Y | P8: BWAV iXML / Soundminer | Q8: Y | U8: Untouched
A9: LIB-006 | B9: Pro Sound Effects Library | C9: Pro Sound Effects | D9: Master Library | F9: SFX | G9: Foley / Ambience / Designed | H9: WAV / BWF | I9: Commercial | O9: Y | P9: BWAV iXML / UCS | Q9: Y | U9: Untouched
A10: LIB-007 | B10: Sound Ideas General Series 6000 | C10: Sound Ideas | D10: General | E10: 6000 | F10: SFX | G10: General Effects | H10: WAV / AIFF | I10: Commercial | O10: Y | P10: CSV Catalog | Q10: Y | U10: Untouched
A11: LIB-008 | B11: Splice Sounds (Subscription) | C11: Splice | D11: Sounds | F11: Loops / One-Shots | G11: Multi-Genre | H11: WAV | I11: Subscription / Royalty-Free | O11: Partial | P11: Filename Convention | Q11: Y | U11: Untouched
A12: LIB-009 | B12: Loopmasters Sample Packs | C12: Loopmasters | D12: Various | F12: Loops / One-Shots | G12: Multi-Genre | H12: WAV / REX2 / Apple Loops | I12: Royalty-Free | Q12: Y | U12: Untouched
A13: LIB-010 | B13: Cymatics Sample Packs | C13: Cymatics | F13: Loops / One-Shots / Presets | G13: EDM / Hip-Hop / Trap | H13: WAV / MIDI / Serum | I13: Royalty-Free | Q13: Y | U13: Untouched
A14: LIB-011 | B14: 8Dio Adagio Strings | C14: 8Dio | D14: Adagio | F14: Orchestral | G14: Strings | H14: Kontakt | I14: Commercial | Q14: Y | U14: Untouched
A15: LIB-012 | B15: Berlin Strings | C15: Orchestral Tools | D15: Berlin Series | F15: Orchestral | G15: Strings | H15: Kontakt / SINE | I15: Commercial | Q15: Y | U15: Untouched
A16: LIB-013 | B16: Symphobia | C16: ProjectSAM | D16: Symphobia | F16: Orchestral | G16: Ensemble / Effects | H16: Kontakt | I16: Commercial | Q16: Y | U16: Untouched
A17: LIB-014 | B17: Olympus Elements | C17: Soundiron | D17: Olympus | F17: Choir | G17: Vocal Ensemble | H17: Kontakt | I17: Commercial | Q17: Y | U17: Untouched
A18: LIB-015 | B18: Vengeance Essential House | C18: Vengeance Sound | D18: Essential | F18: Loops / One-Shots | G18: House / EDM | H18: WAV | I18: Royalty-Free | Q18: Y | U18: Untouched
A19: LIB-016 | B19: Soundly Pro | C19: Soundly | D19: Cloud Library | F19: SFX | G19: Multi | H19: WAV / BWF | I19: Subscription | O19: Y | P19: BWAV iXML | Q19: Y | U19: Untouched
A20: LIB-017 | B20: Performance Samples - Con Moto | C20: Performance Samples | D20: Con Moto | F20: Orchestral | G20: Strings | H20: Kontakt | I20: Commercial | Q20: Y | U20: Untouched
A21: LIB-018 | B21: EastWest Hollywood Orchestra | C21: EastWest / Quantum Leap | D21: Hollywood Series | F21: Orchestral | G21: Full Orchestra | H21: PLAY / Opus | I21: Commercial | Q21: Y | U21: Untouched
A22: LIB-019 | B22: Omnisphere Library | C22: Spectrasonics | D22: Omnisphere | E22: 2 | F22: Synth | G22: Hybrid / Atmospheric | H22: STEAM Engine | I22: Commercial | Q22: Y | U22: Untouched
A23: LIB-020 | B23: Serum Presets (Various) | C23: Xfer Records | D23: Serum | F23: Synth Presets | G23: Wavetable | H23: .fxp / .wav | I23: Mixed | Q23: Y | U23: Untouched

Sheet Library Index
A1: Master Library Inventory | Z1: ROLL-UP
Z2: Total Libraries | AA2: =COUNTA(A4:A100) -> 20
A3: Lib ID | B3: Library Name | C3: Vendor / Developer | D3: Product Line | E3: Version | F3: Category | G3: Sub-Category | H3: Sample Format | I3: License Type | J3: Serial / Key | K3: Original Path | L3: Pristine Path | M3: Size (GB) | N3: # Files | O3: Has Metadata? | P3: Tagging System | Q3: Commercial? | R3: Date Acquired | S3: Date Scanned | T3: Date Processed | U3: Status | V3: DEVONthink DB | W3: TagSpaces Tagged? | X3: Notes | Z3: Commercial | AA3: =COUNTIF(Q4:Q100,"Y") -> 20
A4: LIB-001 | B4: Albion ONE | C4: Spitfire Audio | D4: Albion | E4: 1.6 | F4: Orchestral | G4: Cinematic Strings/Brass/Perc | H4: Kontakt | I4: Commercial | Q4: Y | U4: Untouched | Z4: Untouched | AA4: =COUNTIF(U4:U100,"Untouched") -> 20
A5: LIB-002 | B5: Damage 2 | C5: Heavyocity | D5: Damage | E5: 2 | F5: Cinematic Percussion | G5: Epic Drums | H5: Kontakt | I5: Commercial | Q5: Y | U5: Untouched | Z5: Total GB | AA5: =SUM(M4:M100) -> 0
A6: LIB-003 | B6: Komplete 14 Ultimate | C6: Native Instruments | D6: Komplete | E6: 14 | F6: Bundle | G6: Multi (Synths/Instruments/Effects) | H6: Kontakt / NKS | I6: Commercial | Q6: Y | U6: Untouched | Z6: Total Files | AA6: =SUM(N4:N100) -> 0
A7: LIB-004 | B7: Analog Brass & Winds | C7: Output | D7: Analog | E7: 1 | F7: Hybrid | G7: Brass/Winds | H7: Kontakt Player | I7: Commercial | Q7: Y | U7: Untouched
A8: LIB-005 | B8: BOOM Cinematic Trailers | C8: BOOM Library | D8: Cinematic | F8: SFX | G8: Trailer / Risers / Impacts | H8: WAV | I8: Royalty-Free | O8: Y | P8: BWAV iXML / Soundminer | Q8: Y | U8: Untouched
A9: LIB-006 | B9: Pro Sound Effects Library | C9: Pro Sound Effects | D9: Master Library | F9: SFX | G9: Foley / Ambience / Designed | H9: WAV / BWF | I9: Commercial | O9: Y | P9: BWAV iXML / UCS | Q9: Y | U9: Untouched
A10: LIB-007 | B10: Sound Ideas General Series 6000 | C10: Sound Ideas | D10: General | E10: 6000 | F10: SFX | G10: General Effects | H10: WAV / AIFF | I10: Commercial | O10: Y | P10: CSV Catalog | Q10: Y | U10: Untouched
A11: LIB-008 | B11: Splice Sounds (Subscription) | C11: Splice | D11: Sounds | F11: Loops / One-Shots | G11: Multi-Genre | H11: WAV | I11: Subscription / Royalty-Free | O11: Partial | P11: Filename Convention | Q11: Y | U11: Untouched
A12: LIB-009 | B12: Loopmasters Sample Packs | C12: Loopmasters | D12: Various | F12: Loops / One-Shots | G12: Multi-Genre | H12: WAV / REX2 / Apple Loops | I12: Royalty-Free | Q12: Y | U12: Untouched
A13: LIB-010 | B13: Cymatics Sample Packs | C13: Cymatics | F13: Loops / One-Shots / Presets | G13: EDM / Hip-Hop / Trap | H13: WAV / MIDI / Serum | I13: Royalty-Free | Q13: Y | U13: Untouched
A14: LIB-011 | B14: 8Dio Adagio Strings | C14: 8Dio | D14: Adagio | F14: Orchestral | G14: Strings | H14: Kontakt | I14: Commercial | Q14: Y | U14: Untouched
A15: LIB-012 | B15: Berlin Strings | C15: Orchestral Tools | D15: Berlin Series | F15: Orchestral | G15: Strings | H15: Kontakt / SINE | I15: Commercial | Q15: Y | U15: Untouched
A16: LIB-013 | B16: Symphobia | C16: ProjectSAM | D16: Symphobia | F16: Orchestral | G16: Ensemble / Effects | H16: Kontakt | I16: Commercial | Q16: Y | U16: Untouched
A17: LIB-014 | B17: Olympus Elements | C17: Soundiron | D17: Olympus | F17: Choir | G17: Vocal Ensemble | H17: Kontakt | I17: Commercial | Q17: Y | U17: Untouched
A18: LIB-015 | B18: Vengeance Essential House | C18: Vengeance Sound | D18: Essential | F18: Loops / One-Shots | G18: House / EDM | H18: WAV | I18: Royalty-Free | Q18: Y | U18: Untouched
A19: LIB-016 | B19: Soundly Pro | C19: Soundly | D19: Cloud Library | F19: SFX | G19: Multi | H19: WAV / BWF | I19: Subscription | O19: Y | P19: BWAV iXML | Q19: Y | U19: Untouched
A20: LIB-017 | B20: Performance Samples - Con Moto | C20: Performance Samples | D20: Con Moto | F20: Orchestral | G20: Strings | H20: Kontakt | I20: Commercial | Q20: Y | U20: Untouched
A21: LIB-018 | B21: EastWest Hollywood Orchestra | C21: EastWest / Quantum Leap | D21: Hollywood Series | F21: Orchestral | G21: Full Orchestra | H21: PLAY / Opus | I21: Commercial | Q21: Y | U21: Untouched
A22: LIB-019 | B22: Omnisphere Library | C22: Spectrasonics | D22: Omnisphere | E22: 2 | F22: Synth | G22: Hybrid / Atmospheric | H22: STEAM Engine | I22: Commercial | Q22: Y | U22: Untouched
A23: LIB-020 | B23: Serum Presets (Various) | C23: Xfer Records | D23: Serum | F23: Synth Presets | G23: Wavetable | H23: .fxp / .wav | I23: Mixed | Q23: Y | U23: Untouched

Sheet Naming Standard
A1: 2026 PLOWMAN STANDARD — NOIZYARMY NAMING & INTEGRITY CONVENTION
A2: The permanent, trackable filename law for every pristine asset. Generate compliant names below — copy the result onto the file.
A4: 1 · THE TEMPLATE
A5: BRAND_PROJECT_CATEGORY_DESCRIPTOR_KEY_BPM_VARIANT_QGRADE_vVERSION.ext
A6: Example: | B6: NA_DrumKitVol1_KICK_Punchy_Cmin_128_RR01_QA_v2.wav
A8: 2 · TOKEN DICTIONARY
A9: # | B9: Token | C9: Required | D9: Format Rule | E9: Allowed Values / Examples
A10: 1 | B10: BRAND | C10: YES | D10: 2-4 char UPPER code | E10: NA / NB / MB / client code (GAB, LUC)
A11: 2 | B11: PROJECT | C11: YES | D11: PascalCase, no spaces | E11: DrumKitVol1, TrailerPack, VibeCode
A12: 3 | B12: CATEGORY | C12: YES | D12: UPPER, from Tags sheet | E12: KICK / SNARE / VOX / FX / FOLEY / PAD
A13: 4 | B13: DESCRIPTOR | C13: rec. | D13: PascalCase character tag | E13: Punchy / Dark / Bright / LoFi / Cinematic
A14: 5 | B14: KEY | C14: if tonal | D14: Note+maj/min | E14: Cmin / F#maj / Amaj
A15: 6 | B15: BPM | C15: if rhythmic | D15: 2-3 digits | E15: 90 / 128 / 174
A16: 7 | B16: VARIANT | C16: opt. | D16: RR##/Vel##/Mic | E16: RR01 / Vel80 / MicClose / Amb
A17: 8 | B17: QGRADE | C17: YES | D17: Q + A/B/C/X | E17: QA=pristine, QB=good, QC=usable, QX=needs rebuild
A18: 9 | B18: VERSION | C18: YES | D18: v + integer | E18: v1 / v2 / v3
A20: 3 · LIVE FILENAME GENERATOR
A21: Brand code | B21: NA
A22: Project | B22: DrumKitVol1
A23: Category | B23: KICK
A24: Descriptor | B24: Punchy
A25: Key | B25: Cmin
A26: BPM | B26: 128
A27: Variant | B27: RR01
A28: Q-Grade | B28: QA
A29: Version | B29: 2
A30: Extension | B30: wav
A31: GENERATED FILENAME → | B31: =B21&"_"&B22&"_"&B23&IF(B24="","","_"&B24)&IF(B25="","","_"&B25)&IF(B26="","","_"&B26)&IF(B27="","","_"&B27)&"_"&B28&"_v"&B29&"."&B30 -> NA_DrumKitVol1_KICK_Punchy_Cmin_128_RR01_QA_v2.wav
A33: 4 · INTEGRITY STAMP
A34: SHA256 | B34: a3f5e9c1b7d2840f6e1a9c3b5d7f2048
A35: Verified date | B35: 46203
A36: Q-Grade | B36: QA
A37: Learned by (model) | B37: LMStudio-Qwen2.5-72B
A38: INTEGRITY STAMP → | B38: ="#"&B36&" | sha256:"&LEFT(B34,12)&"… | verified "&TEXT(B35,"yyyy-mm-dd")&" | learned:"&B37 -> #QA | sha256:a3f5e9c1b7d2… | verified 2026-06-30 | learned:LMStudio-Qwen2.5-72B
A40: 5 · THE LAW (RULES)
A41: 1. Underscores _ separate tokens. NEVER use spaces. Dots only before the extension.
A42: 2. BRAND and CATEGORY are ALWAYS UPPERCASE. PROJECT and DESCRIPTOR are PascalCase.
A43: 3. Allowed characters: A-Z a-z 0-9 underscore. The integrity stamp may also use # : | . and …
A44: 4. Q-Grade reflects SuperSonic-learned quality (QA pristine → QX needs rebuild). Re-grade after every clean pass.
A45: 5. Version bumps on EVERY edit. The highest v in a group is the pristine master; lower versions archive.
A46: 6. Every pristine file carries the integrity stamp — as a sidecar .txt or embedded BWF/iXML comment.
A47: 7. Filename + stamp together make every asset self-describing, greppable, and audit-proof forever.

Sheet Scoreboard
A1: NOIZYARMY — MISSION SCOREBOARD
A2: Live game state — moves automatically as the Scan Queue fills. Find fast, process clean, learn deep.
A4: MISSION PROGRESS
A5: % to Pristine | B5: =IFERROR(Integrity!AA6/'Scan Queue'!V2,0) -> 0.75
A6: Total Score | B6: ='Scan Queue'!V2*1+'Scan Queue'!V7*2+Integrity!AA6*25+'Scan Queue'!V9*5 -> 95
A7: Level | B7: =IF(B6>=1000,"5 — LEGEND",IF(B6>=500,"4 — MASTER",IF(B6>=200,"3 — PRO",IF(B6>=50,"2 — RISING","1 — RECRUIT")))) -> 2 — RISING
A9: LIVE COUNTERS | D9: BRAND LEADERBOARD
A10: Files Found | B10: ='Scan Queue'!V2 -> 4 | D10: NOIZYANTHROPIC | E10: ='Scan Queue'!V3 -> 2
A11: Audio Identified | B11: ='Scan Queue'!V7 -> 3 | D11: NOIZYBEAST | E11: ='Scan Queue'!V4 -> 0
A12: Pristine / Verified | B12: =Integrity!AA6 -> 3 | D12: METABEAST | E12: ='Scan Queue'!V5 -> 1
A13: Orphans to Crack | B13: ='Scan Queue'!V8 -> 1 | D13: Unsorted | E13: ='Scan Queue'!V6 -> 1
A14: Dupes Purged | B14: ='Scan Queue'!V9 -> 2
A15: Needs Rebuild | B15: =Integrity!AA5 -> 1
A17: ACHIEVEMENTS | D17: DAILY LOG (manual)
A18: First Blood (1st file) | B18: =IF('Scan Queue'!V2>=1,"🏆 UNLOCKED","🔒 locked") -> 🏆 UNLOCKED | D18: Today's date
A19: Century (100 found) | B19: =IF('Scan Queue'!V2>=100,"🏆 UNLOCKED","🔒 "&'Scan Queue'!V2&"/100") -> 🔒 4/100 | D19: Files today
A20: Orphan Slayer (0 left) | B20: =IF(AND('Scan Queue'!V2>0,'Scan Queue'!V8=0),"🏆 UNLOCKED","🔒 "&'Scan Queue'!V8&" left") -> 🔒 1 left | D20: Day streak
A21: Dedup Demon (50 purged) | B21: =IF('Scan Queue'!V9>=50,"🏆 UNLOCKED","🔒 "&'Scan Queue'!V9&"/50") -> 🔒 2/50 | D21: Best session
A22: Pristine Pilgrim (100 clean) | B22: =IF(Integrity!AA6>=100,"🏆 UNLOCKED","🔒 "&Integrity!AA6&"/100") -> 🔒 3/100
A23: Full Sweep (100% pristine) | B23: =IF(AND('Scan Queue'!V2>0,Integrity!AA6>='Scan Queue'!V2),"🏆 UNLOCKED","🔒 in progress") -> 🔒 in progress
A25: Q-GRADE DISTRIBUTION | B25: Count | C25: Meter
A26: QA — Pristine | B26: =Integrity!AA9 -> 2 | C26: =REPT("█",Integrity!AA9) -> ██
A27: QB — Good | B27: =Integrity!AA10 -> 1 | C27: =REPT("█",Integrity!AA10) -> █
A28: QC — Usable | B28: =Integrity!AA11 -> 0 | C28: =REPT("█",Integrity!AA11)
A29: QX — Needs Rebuild | B29: =Integrity!AA12 -> 1 | C29: =REPT("█",Integrity!AA12) -> █

Sheet Credit Splits
A1: CREDIT SPLITS & ROYALTY REGISTER
A2: Who made what, and who gets paid — contribution & royalty splits per project, per collaborator. Splits must total 100% per project.
A3: Split ID | B3: Project / Release | C3: Asset / Lib ID | D3: Brand | E3: Collaborator | F3: Role | G3: Contribution % | H3: Royalty % | I3: Agreement Ref | J3: Status | K3: Notes
A4: CS-001 | B4: DrumKitVol1 | C4: LIB-001 | D4: NOIZYANTHROPIC | E4: NoizyArmy | F4: Founder / Producer | G4: 0.7 | H4: 0.7 | I4: MSA-2026 | J4: Agreed | K4: House brand — majority owner
A5: CS-002 | B5: DrumKitVol1 | C5: LIB-001 | D5: NOIZYANTHROPIC | E5: Gabriel | F5: Sound Design | G5: 0.3 | H5: 0.3 | I5: Split-G01 | J5: Agreed | K5: Collaborator BR-101
A6: CS-003 | B6: TrailerPack | C6: LIB-005 | D6: METABEAST | E6: NoizyArmy | F6: Producer | G6: 0.6 | H6: 0.6 | I6: MSA-2026 | J6: Agreed
A7: CS-004 | B7: TrailerPack | C7: LIB-005 | D7: METABEAST | E7: Lucy | F7: Vocals / Topline | G7: 0.4 | H7: 0.4 | I7: Split-L01 | J7: Pending | K7: Collaborator BR-102 — awaiting sign
A8: CS-005 | B8: VibeCode Signature | C8: VC-001 | D8: Vibe Code | E8: NoizyArmy | F8: Producer | G8: 0.5 | H8: 0.5 | I8: MSA-2026 | J8: Agreed
A9: CS-006 | B9: VibeCode Signature | C9: VC-001 | D9: Vibe Code | E9: Gabriel | F9: Code / Design | G9: 0.25 | H9: 0.25 | I9: Split-G02 | J9: Agreed
A10: CS-007 | B10: VibeCode Signature | C10: VC-001 | D10: Vibe Code | E10: Lucy | F10: Vocals | G10: 0.25 | H10: 0.25 | I10: Split-L02 | J10: Pending
A12: PROJECT BALANCE CHECK — splits must total 100%
A13: DrumKitVol1 | B13: =SUMIF($B$4:$B$10,A13,$G$4:$G$10) -> 1 | C13: =IF(ROUND(B13,2)=1,"✓ balanced","⚠ fix "&TEXT(B13,"0%")) -> ✓ balanced
A14: TrailerPack | B14: =SUMIF($B$4:$B$10,A14,$G$4:$G$10) -> 1 | C14: =IF(ROUND(B14,2)=1,"✓ balanced","⚠ fix "&TEXT(B14,"0%")) -> ✓ balanced
A15: VibeCode Signature | B15: =SUMIF($B$4:$B$10,A15,$G$4:$G$10) -> 1 | C15: =IF(ROUND(B15,2)=1,"✓ balanced","⚠ fix "&TEXT(B15,"0%")) -> ✓ balanced
A17: PER-COLLABORATOR TOTALS
A18: Gabriel | B18: =SUMIF($E$4:$E$10,A18,$G$4:$G$10) -> 0.55
A19: Lucy | B19: =SUMIF($E$4:$E$10,A19,$G$4:$G$10) -> 0.65
A20: NoizyArmy | B20: =SUMIF($E$4:$E$10,A20,$G$4:$G$10) -> 1.8

Sheet Clone Status
A1: CLONE & REDUNDANCY LEDGER — 3-2-1 BACKUP VERIFICATION | V1: ROLL-UP
A2: Confirms every source drive's contents are cloneable + actually cloned (local + offsite cloud). Logged by scanner / backup tool; formulas flag at-risk single-copy data. | V2: Drives tracked | W2: =COUNTA($B$8:$B$19) -> 2
V3: Confirmed 3-2-1 | W3: =COUNTIF($P$8:$P$500,"✓ 3-2-1") -> 0
A4: ="CONFIRMATION: "&W3&" of "&W2&" drives confirmed 3-2-1 | "&W4&" CRITICAL single-copy | "&W5&" pending verification" -> CONFIRMATION: 0 of 2 drives confirmed 3-2-1 | 2 CRITICAL single-copy | 2 pending verification | V4: CRITICAL (single copy) | W4: =COUNTIF($Q$8:$Q$500,"CRITICAL") -> 2
V5: Pending verify | W5: =COUNTIF($S$8:$S$500,"PENDING VERIFY") -> 2
A6: SOURCE DRIVE CLONE LEDGER | V6: Total capacity GB | W6: =SUM($E$8:$E$500) -> 16000
A7: Clone ID | B7: Source Drive / Volume | C7: Type | D7: Content Scope | E7: Capacity GB | F7: Used GB | G7: Cloneable? | H7: Local Clone? | I7: Local Clone Path | J7: Local Verified | K7: Cloud Clone? | L7: Cloud Provider | M7: Cloud Verified | N7: Clone Method | O7: Copies | P7: 3-2-1? | Q7: Risk | R7: Last Full Verify | S7: Status | T7: Notes
A8: CLN-001 | B8: 12RB | C8: Origin Master | D8: NOIZYANTHROPIC + NOIZYBEAST masters (scope TBC) | E8: 12000 | F8: ? | G8: Y | H8: ? | K8: ? | N8: TBD | O8: =1+IF(H8="Y",1,0)+IF(K8="Y",1,0) -> 1 | P8: =IF(AND(O8>=3,K8="Y"),"✓ 3-2-1",IF(O8=2,"partial (2 copies)","✗ single copy")) -> ✗ single copy | Q8: =IF(O8>=3,"SAFE",IF(O8=2,"WARN","CRITICAL")) -> CRITICAL | S8: =IF(AND(H8="Y",K8="Y"),"Confirmed",IF(OR(H8="?",K8="?",H8="",K8=""),"PENDING VERIFY","Partial")) -> PENDING VERIFY | T8: Awaiting scanner + backup-tool verification
A9: CLN-002 | B9: MAG4TB | C9: Origin / Archive | D9: Project archives + foley/SFX (scope TBC) | E9: 4000 | F9: ? | G9: Y | H9: ? | K9: ? | N9: TBD | O9: =1+IF(H9="Y",1,0)+IF(K9="Y",1,0) -> 1 | P9: =IF(AND(O9>=3,K9="Y"),"✓ 3-2-1",IF(O9=2,"partial (2 copies)","✗ single copy")) -> ✗ single copy | Q9: =IF(O9>=3,"SAFE",IF(O9=2,"WARN","CRITICAL")) -> CRITICAL | S9: =IF(AND(H9="Y",K9="Y"),"Confirmed",IF(OR(H9="?",K9="?",H9="",K9=""),"PENDING VERIFY","Partial")) -> PENDING VERIFY | T9: Awaiting scanner + backup-tool verification
A10: CLN-003 | O10: =IF($B10="","",1+IF(H10="Y",1,0)+IF(K10="Y",1,0)) | P10: =IF($B10="","",IF(AND(O10>=3,K10="Y"),"✓ 3-2-1",IF(O10=2,"partial (2 copies)","✗ single copy"))) | Q10: =IF($B10="","",IF(O10>=3,"SAFE",IF(O10=2,"WARN","CRITICAL"))) | S10: =IF($B10="","",IF(AND(H10="Y",K10="Y"),"Confirmed","PENDING VERIFY"))
A11: CLN-004 | O11: =IF($B11="","",1+IF(H11="Y",1,0)+IF(K11="Y",1,0)) | P11: =IF($B11="","",IF(AND(O11>=3,K11="Y"),"✓ 3-2-1",IF(O11=2,"partial (2 copies)","✗ single copy"))) | Q11: =IF($B11="","",IF(O11>=3,"SAFE",IF(O11=2,"WARN","CRITICAL"))) | S11: =IF($B11="","",IF(AND(H11="Y",K11="Y"),"Confirmed","PENDING VERIFY"))
A12: CLN-005 | O12: =IF($B12="","",1+IF(H12="Y",1,0)+IF(K12="Y",1,0)) | P12: =IF($B12="","",IF(AND(O12>=3,K12="Y"),"✓ 3-2-1",IF(O12=2,"partial (2 copies)","✗ single copy"))) | Q12: =IF($B12="","",IF(O12>=3,"SAFE",IF(O12=2,"WARN","CRITICAL"))) | S12: =IF($B12="","",IF(AND(H12="Y",K12="Y"),"Confirmed","PENDING VERIFY"))
A13: CLN-006 | O13: =IF($B13="","",1+IF(H13="Y",1,0)+IF(K13="Y",1,0)) | P13: =IF($B13="","",IF(AND(O13>=3,K13="Y"),"✓ 3-2-1",IF(O13=2,"partial (2 copies)","✗ single copy"))) | Q13: =IF($B13="","",IF(O13>=3,"SAFE",IF(O13=2,"WARN","CRITICAL"))) | S13: =IF($B13="","",IF(AND(H13="Y",K13="Y"),"Confirmed","PENDING VERIFY"))
A14: CLN-007 | O14: =IF($B14="","",1+IF(H14="Y",1,0)+IF(K14="Y",1,0)) | P14: =IF($B14="","",IF(AND(O14>=3,K14="Y"),"✓ 3-2-1",IF(O14=2,"partial (2 copies)","✗ single copy"))) | Q14: =IF($B14="","",IF(O14>=3,"SAFE",IF(O14=2,"WARN","CRITICAL"))) | S14: =IF($B14="","",IF(AND(H14="Y",K14="Y"),"Confirmed","PENDING VERIFY"))
A15: CLN-008 | O15: =IF($B15="","",1+IF(H15="Y",1,0)+IF(K15="Y",1,0)) | P15: =IF($B15="","",IF(AND(O15>=3,K15="Y"),"✓ 3-2-1",IF(O15=2,"partial (2 copies)","✗ single copy"))) | Q15: =IF($B15="","",IF(O15>=3,"SAFE",IF(O15=2,"WARN","CRITICAL"))) | S15: =IF($B15="","",IF(AND(H15="Y",K15="Y"),"Confirmed","PENDING VERIFY"))
A16: CLN-009 | O16: =IF($B16="","",1+IF(H16="Y",1,0)+IF(K16="Y",1,0)) | P16: =IF($B16="","",IF(AND(O16>=3,K16="Y"),"✓ 3-2-1",IF(O16=2,"partial (2 copies)","✗ single copy"))) | Q16: =IF($B16="","",IF(O16>=3,"SAFE",IF(O16=2,"WARN","CRITICAL"))) | S16: =IF($B16="","",IF(AND(H16="Y",K16="Y"),"Confirmed","PENDING VERIFY"))
A17: CLN-010 | O17: =IF($B17="","",1+IF(H17="Y",1,0)+IF(K17="Y",1,0)) | P17: =IF($B17="","",IF(AND(O17>=3,K17="Y"),"✓ 3-2-1",IF(O17=2,"partial (2 copies)","✗ single copy"))) | Q17: =IF($B17="","",IF(O17>=3,"SAFE",IF(O17=2,"WARN","CRITICAL"))) | S17: =IF($B17="","",IF(AND(H17="Y",K17="Y"),"Confirmed","PENDING VERIFY"))
A18: CLN-011 | O18: =IF($B18="","",1+IF(H18="Y",1,0)+IF(K18="Y",1,0)) | P18: =IF($B18="","",IF(AND(O18>=3,K18="Y"),"✓ 3-2-1",IF(O18=2,"partial (2 copies)","✗ single copy"))) | Q18: =IF($B18="","",IF(O18>=3,"SAFE",IF(O18=2,"WARN","CRITICAL"))) | S18: =IF($B18="","",IF(AND(H18="Y",K18="Y"),"Confirmed","PENDING VERIFY"))
A19: CLN-012 | O19: =IF($B19="","",1+IF(H19="Y",1,0)+IF(K19="Y",1,0)) | P19: =IF($B19="","",IF(AND(O19>=3,K19="Y"),"✓ 3-2-1",IF(O19=2,"partial (2 copies)","✗ single copy"))) | Q19: =IF($B19="","",IF(O19>=3,"SAFE",IF(O19=2,"WARN","CRITICAL"))) | S19: =IF($B19="","",IF(AND(H19="Y",K19="Y"),"Confirmed","PENDING VERIFY"))
A22: TOOL-VERIFIED AUDIT LOG
A23: Date | B23: Tool Used | C23: Scope Scanned | D23: Result | E23: Conclusion
A24: 46203 | B24: Google Drive (MCP connector) | C24: audio/* MIME; titles *.wav/.aif/.flac; names NOIZY/METABEAST/Sample | D24: 0 files found (3 scans, all empty) | E24: No audio in Google Drive — cloud-clone tier is EMPTY. 3-2-1 offsite copy NOT in place via Drive.
A25: 46203 | B25: Connector + agent audit | C25: All MCP connectors + connected agents | D25: No tool can reach local drives (12RB, MAG4TB, /Volumes/Audio) | E25: Desktop Commander NOT connected. Local-drive scan requires it running on the Mac.
A26: 46203 | B26: Adobe Creative Cloud (MCP) | C26: CC assets: audio / music / sound effects / samples | D26: 0 found | E26: No audio in Adobe Creative Cloud.
A27: 46203 | B27: Gmail (MCP) | C27: Attachments: .wav/.aif/.mp3/.mov/.mp4 | D27: 0 found | E27: No audio/video email attachments.
A28: 46203 | B28: Excel add-in JS sandbox | C28: fetch / XMLHttpRequest / WebSocket -> LM Studio localhost:1234 | D28: ALL undefined — no network stack in this context | E28: Cannot initiate LM Studio API call from this Excel add-in. Connection must start LOCALLY.
A29: PATH FWD | B29: LM Studio + filesystem MCP, or Desktop Commander | C29: DC has native .xlsx read/write — can scan + write INTO this workbook on disk | D29: Local orchestration → results imported here | E29: Run scan locally; upload listing to me OR let Desktop Commander write rows into this file directly.
A30: 46203 | B30: Google Drive broad scan (owner=me) | C30: Account identity + what's consuming storage | D30: Connected account = rsp@noizy.ai (2 small Sheets + 1 folder only; video=0, archives=0) | E30: WRONG ACCOUNT. The 250GB + cloud audio are NOT in rsp@noizy.ai. Reconnect as rsplowman@gmail.com (single 'p' — NOT rspplowman) and re-scan.
A31: 46203 | B31: Account correction (user) | C31: Target Google account for media + 250GB | D31: Correct = rsplowman@gmail.com (single p). 'rspplowman' was a typo; rsp@noizy.ai is the wrong/empty Workspace acct. | E31: ACTION: connect rsplowman@gmail.com, then re-run all cloud scans.

Sheet Scan Commands
A1: LOCAL SCAN PLAYBOOK — get your drives into this workbook
A2: Copy-paste commands for macOS (M2 Ultra). Output maps straight into the Scan Queue paste columns B–G. Run in Terminal, then upload the CSV to me.
A4: METHOD A · FAST FILE LISTING (no hashing — seconds, run this first)
A5: Run per drive. Outputs: Filename, Full Path, Size(bytes), Extension, Modified(epoch) → Scan Queue cols B,C,D,E,F.
A6: find /Volumes/Audio -type f -print0 | while IFS= read -r -d '' f; do n=$(basename "$f"); echo "\"$n\",\"$f\",$(stat -f%z "$f"),\"${n##*.}\",$(stat -f%m "$f")"; done > ~/Desktop/audio_scan.csv
A7: Repeat for your other drives — swap the path and output name:
A8: find /Volumes/12RB -type f -print0 | while IFS= read -r -d '' f; do n=$(basename "$f"); echo "\"$n\",\"$f\",$(stat -f%z "$f"),\"${n##*.}\",$(stat -f%m "$f")"; done > ~/Desktop/12RB_scan.csv
A9: find /Volumes/MAG4TB -type f -print0 | while IFS= read -r -d '' f; do n=$(basename "$f"); echo "\"$n\",\"$f\",$(stat -f%z "$f"),\"${n##*.}\",$(stat -f%m "$f")"; done > ~/Desktop/MAG4TB_scan.csv
A11: METHOD B · FULL LISTING WITH SHA256 (enables dedup — slower, run overnight on big drives)
A12: Adds the SHA256 hash → Scan Queue col G. Powers the Dup Count / DUP detection automatically.
A13: find /Volumes/Audio -type f -print0 | while IFS= read -r -d '' f; do n=$(basename "$f"); h=$(shasum -a 256 "$f" | cut -d' ' -f1); echo "\"$n\",\"$f\",$(stat -f%z "$f"),\"${n##*.}\",$(stat -f%m "$f"),$h"; done > ~/Desktop/audio_scan_hashed.csv
A15: METHOD C · LM STUDIO (your M2 Ultra does the work — needs a filesystem MCP loaded in LM Studio)
... A35: afinfo "/Volumes/Audio/yourfile.wav"

Sheet Global Data Map
A1: GLOBAL DATA MAP — every location, every tier, audited | Q1: GLOBAL AUDIT
A2: Master atlas of where NoizyArmy data lives worldwide — local drives, cloud accounts & services. Reachability + scan + audit status per location. | Q2: Locations tracked | R2: =COUNTA($B$4:$B$200) -> 9
A3: Loc ID | B3: Location | C3: Tier | D3: Host / Account | E3: Path / URL | F3: Capacity GB | G3: Used GB | H3: Reachable by AI? | I3: Scan Status | J3: Files Found | K3: Audit Status | L3: Last Audited | M3: Clone / Redundancy | N3: Risk | O3: Notes | Q3: Audited | R3: =COUNTIF($K$4:$K$200,"Audited*") -> 3
A4: LOC-001 | B4: Audio Master Volume | C4: Local Drive | D4: M2 Ultra (Mac) | E4: /Volumes/Audio | H4: No — sandbox | I4: Pending | J4: — | K4: Not audited | M4: TBC | N4: CRITICAL | O4: Primary working masters | Q4: Pending scan | R4: =COUNTIF($I$4:$I$200,"Pending") -> 6
A5: LOC-002 | B5: 12RB | C5: Local Drive | D5: M2 Ultra (Mac) | E5: /Volumes/12RB | F5: 12000 | H5: No — sandbox | I5: Pending | J5: — | K5: Not audited | M5: CLN-001 | N5: CRITICAL | O5: NA + NB masters (assumed 12TB) | Q5: Unreachable (local) | R5: =COUNTIF($H$4:$H$200,"No*") -> 6
A6: LOC-003 | B6: MAG4TB | C6: Local Drive | D6: M2 Ultra (Mac) | E6: /Volumes/MAG4TB | F6: 4000 | H6: No — sandbox | I6: Pending | J6: — | K6: Not audited | M6: CLN-002 | N6: CRITICAL | O6: Project archives + foley (assumed 4TB) | Q6: CRITICAL risk | R6: =COUNTIF($N$4:$N$200,"CRITICAL") -> 3
A7: LOC-010 | B7: Google Drive (Workspace) | C7: Cloud Acct | D7: rsp@noizy.ai | E7: drive.google.com | G7: 0 | H7: Yes — Drive MCP | I7: Scanned | J7: 0 audio | K7: Audited ✓ | M7: — | N7: LOW | O7: Near-empty; wrong account | Q7: Capacity GB (sum) | R7: =SUM($F$4:$F$200) -> 124000
A8: LOC-011 | B8: Google Drive (personal) | C8: Cloud Acct | D8: rsplowman@gmail.com | E8: drive.google.com | G8: 250 | H8: NOT connected | I8: Pending | J8: ? | K8: Not audited | M8: — | N8: UNKNOWN | O8: CONNECT THIS — holds the ~250GB | Q8: Used GB (sum) | R8: =SUM($G$4:$G$200) -> 250
A9: LOC-012 | B9: Gmail attachments | C9: Cloud Service | D9: rsp@noizy.ai | E9: mail.google.com | H9: Yes — Gmail MCP | I9: Scanned | J9: 0 media | K9: Audited ✓ | M9: — | N9: LOW | O9: Wrong account
A10: LOC-013 | B10: Adobe Creative Cloud | C10: Cloud Service | D10: Adobe ID | E10: assets.adobe.com | H10: Yes — Adobe MCP | I10: Scanned | J10: 0 audio | K10: Audited ✓ | M10: — | N10: LOW | O10: No audio assets
A11: LOC-020 | B11: Pristine Masters (target) | C11: Destination | D11: TBD drive | E11: /Pristine/ | F11: 8000 | G11: 0 | H11: No — sandbox | I11: Pending | J11: 0 | K11: Not audited | M11: DST-001 | N11: WARN | O11: Empty; awaiting routed files
A12: LOC-021 | B12: Cloud Archive (offsite) | C12: Destination | D12: TBD provider | E12: s3 / Backblaze | F12: 100000 | G12: 0 | H12: No — sandbox | I12: Pending | J12: 0 | K12: Not audited | M12: DST-004 | N12: WARN | O12: Offsite 3-2-1 target — not set up

Sheet Master Monitor
A1: MASTER MONITOR — NoizyArmy mission control | J1: ="Refreshed: "&TEXT(NOW(),"yyyy-mm-dd hh:mm") -> Refreshed: 2026-07-01 14:46
A2: Live status board (auto-pulls every sheet's roll-up) + worker/agent registry + integration map. One screen, whole operation.
A3: ="🔴 ACTION NEEDED — "&'Global Data Map'!R4&" locations pending | "&'Clone Status'!W4&" drives CRITICAL | NEXT: connect rsplowman@gmail.com + run Method-A scan" -> 🔴 ACTION NEEDED — 6 locations pending | 2 drives CRITICAL | NEXT: connect rsplowman@gmail.com + run Method-A scan
A4: LIVE STATUS BOARD
A5: PIPELINE | D5: BRANDS / LIBS | G5: INTEGRITY | J5: HEALTH GAUGES
A6: Files in Queue | B6: ='Scan Queue'!V2 -> 4 | D6: NOIZYANTHROPIC | E6: ='Scan Queue'!V3 -> 2 | G6: Tracked | H6: =Integrity!AA2 -> 5 | J6: Audited % | K6: =IFERROR('Global Data Map'!R3/'Global Data Map'!R2,0) -> 0.33333333 | L6: =REPT("█",ROUND(K6*10,0)) -> ███
A7: Audio Files | B7: ='Scan Queue'!V7 -> 3 | D7: NOIZYBEAST | E7: ='Scan Queue'!V4 -> 0 | G7: Verified | H7: =Integrity!AA6 -> 3 | J7: Workers Active % | K7: =IFERROR(K12/SUM($K$12:$K$14),0) -> 0.35714286 | L7: =REPT("█",ROUND(K7*10,0)) -> ████
A8: Orphans | B8: ='Scan Queue'!V8 -> 1 | D8: METABEAST | E8: ='Scan Queue'!V5 -> 1 | G8: Corrupt | H8: =Integrity!AA4 -> 1 | J8: Backup 3-2-1 % | K8: =IFERROR('Clone Status'!W3/'Clone Status'!W2,0) -> 0 | L8: =REPT("█",ROUND(K8*10,0))
A9: Duplicates | B9: ='Scan Queue'!V9 -> 2 | D9: Libraries | E9: ='Library Index'!AA2 -> 20 | G9: QA grade | H9: =Integrity!AA9 -> 2 | J9: Pristine % | K9: =IFERROR(Integrity!AA6/'Scan Queue'!V2,0) -> 0.75 | L9: =REPT("█",ROUND(K9*10,0)) -> ████████
A11: STORAGE & CLONES | D11: GLOBAL MAP | G11: SCORE | J11: WORKER COUNTS
A12: Drives (clone ledger) | B12: ='Clone Status'!W2 -> 2 | D12: Locations | E12: ='Global Data Map'!R2 -> 9 | G12: Total Score | H12: =Scoreboard!B6 -> 95 | J12: Active / Connected | K12: =COUNTIF($D$18:$D$31,"Active")+COUNTIF($D$18:$D$31,"Connected") -> 5
A13: 3-2-1 OK | B13: ='Clone Status'!W3 -> 0 | D13: Audited | E13: ='Global Data Map'!R3 -> 3 | G13: Level | H13: =Scoreboard!B7 -> 2 — RISING | J13: Blocked (not connected) | K13: =COUNTIF($D$18:$D$31,"Not connected")+COUNTIF($D$18:$D$31,"Not wired") -> 5
A14: CRITICAL single-copy | B14: ='Clone Status'!W4 -> 2 | D14: Pending | E14: ='Global Data Map'!R4 -> 6 | G14: Capacity GB (global) | H14: ='Global Data Map'!R7 -> 124000 | J14: Needs attention | K14: =COUNTIF($D$18:$D$31,"Idle")+COUNTIF($D$18:$D$31,"Manual")+COUNTIF($D$18:$D$31,"Available")+COUNTIF($D$18:$D$31,"Connected (wrong acct)") -> 4
A16: WORKER & AGENT REGISTRY
A17: Worker | B17: Type | C17: Role in Pipeline | D17: Status | E17: Reachable Via | F17: Last Activity | G17: Next Action
A18: LM Studio (M2 Ultra) | B18: Local LLM | C18: Stage 4-5: name / tag / Q-grade | D18: Idle | E18: Local REST :1234 (not from add-in) | F18: — | G18: Load filesystem MCP + 70B model
A19: Desktop Commander | B19: Local agent | C19: Scan / hash / move / write .xlsx | D19: Not connected | E19: Local stdio / OAuth remote | F19: — | G19: npx -y @wonderwhy-er/desktop-commander setup
A20: SuperSonic IDE | B20: Local tool | C20: Stage 6: clean / rebuild audio | D20: Manual | E20: Local app | F20: — | G20: Run on QX-grade files
A21: Filesystem MCP | B21: Local bridge | C21: Read /Volumes/Audio | D21: Not connected | E21: stdio (Claude Desktop / LM Studio) | F21: — | G21: Add server, scope to /Volumes/Audio
A22: Google Drive | B22: Cloud connector | C22: Cloud audio scan | D22: Connected (wrong acct) | E22: Drive MCP | F22: 46203 | G22: Reconnect rsplowman@gmail.com
A23: Gmail | B23: Cloud connector | C23: Email media scan | D23: Connected | E23: Gmail MCP | F23: 46203 | G23: —
A24: Adobe Creative Cloud | B24: Cloud connector | C24: CC asset scan | D24: Connected | E24: Adobe MCP | F24: 46203 | G24: —
A25: Gabriel | B25: Collaborator | C25: Sound design (BR-101) | D25: Active | E25: Credit Splits / Brands | F25: — | G25: Tag contributions per project
A26: Lucy | B26: Collaborator | C26: Vocals (BR-102) | D26: Active | E26: Credit Splits / Brands | F26: — | G26: Tag contributions per project
A27: Excel (this workbook) | B27: Microsoft | C27: Catalog brain + monitor | D27: ACTIVE | E27: native | F27: live | G27: —
A28: Power Automate | B28: Microsoft | C28: Webhook / flow automation | D28: Not wired | E28: HTTP webhook trigger | F28: — | G28: Flow: file drop → append Scan Queue row
A29: MS Graph API | B29: Microsoft | C29: OneDrive / SharePoint scan | D29: Not wired | E29: Graph REST + OAuth | F29: — | G29: Auth to scan MS cloud tiers
A30: Copilot (Excel) | B30: Microsoft | C30: In-sheet AI assist | D30: Available | E30: native | F30: — | G30: Optional — formula / analysis help
A31: Azure Blob Storage | B31: Microsoft | C31: Cloud archive tier | D31: Not wired | E31: Azure SDK / rclone | F31: — | G31: Candidate 3-2-1 offsite (LOC-021)
A33: INTEGRATION & WEBHOOK MAP — wiring targets (built off-workbook, tracked here)
A34: 1. INGEST WEBHOOK | B34: Power Automate 'When a file is created' (Desktop/scan folder) → parse CSV → add rows to Scan Queue B:G. The hands-free import path.
A35: 2. LOCAL SCAN CALL | B35: LM Studio POST /api/v1/chat with filesystem MCP → returns classified CSV. Driven by a local script, not this add-in.
A36: 3. DC BOOTSTRAP | B36: Desktop Commander writes rows straight into this .xlsx on disk — no upload, no webhook. Most direct.
A37: 4. CLOUD SYNC | B37: MS Graph (OneDrive/SharePoint) or Google Drive MCP → mirror pristine masters offsite for the 3-2-1 tier.
A38: NOTE | B38: This add-in's sandbox has no network — it cannot fire these calls itself. They run off-workbook (local agent / Power Automate / script); this sheet is the registry + status board that monitors them.

Sheet Blend & Merge Plan
A1: BLEND & MERGE PLAN — unify all cloud + local into one pristine library
A2: Consolidation strategy: scan every source → normalize names → dedupe by hash → route to brand pristine → verify 3-2-1. Conflict rules below.
A4: 1 · SOURCE INVENTORY (what merges, what's ignored)
A5: Source | B5: Tier | C5: Reachable | D5: Known Content | E5: Merge Role
A6: /Volumes/Audio | B6: Local | C6: No — scan locally | D6: Working masters (TBC) | E6: PRIMARY SOURCE
A7: 12RB | B7: Local | C7: No — scan locally | D7: NA + NB masters | E7: PRIMARY SOURCE
A8: MAG4TB | B8: Local | C8: No — scan locally | D8: Project archives + foley | E8: SECONDARY SOURCE
A9: rsplowman@gmail.com | B9: Cloud | C9: NOT connected | D9: ~250GB — unknown until connected | E9: CLOUD SOURCE — CONNECT
A10: rsp@noizy.ai | B10: Cloud | C10: Yes | D10: 3 objects, ~5KB, 0 media (exhaustive) | E10: IGNORE — empty
A11: Adobe Creative Cloud | B11: Cloud | C11: Yes | D11: 0 audio | E11: IGNORE — empty
A12: Gmail attachments | B12: Cloud | C12: Yes | D12: 0 media | E12: IGNORE — empty
A14: 2 · CONFLICT RESOLUTION (same file in 2+ sources — which wins)
A15: Scenario | B15: Detection | C15: Resolution Rule
A16: Identical file, multiple sources | B16: SHA256 match | C16: Keep ONE canonical in pristine; log the rest as clones (Clone Status). Delete dupes ONLY after 3-2-1 confirmed.
A17: Same name, different content | B17: name match, hash differs | C17: Canonical = highest Q-Grade, tie-break newest modified. Archive the other as _v2/_v3 (never delete).
A18: Lossy vs lossless, same audio | B18: format compare (wav vs mp3) | C18: Lossless (WAV/FLAC) is canonical. Flag the lossy copy 'RE-SOURCE' — do not ship.
A19: Cloud copy vs local master | B19: source tier compare | C19: LOCAL master = canonical source of truth. Cloud copy becomes the offsite 3-2-1 clone.
A20: Orphan (no extension) | B20: magic bytes (Identifiers) | C20: Identify type, rename per Plowman Standard, THEN merge. Never merge an unidentified blob.
A21: Same name, different brand path | B21: name match, brand differs | C21: Flag MANUAL REVIEW — possible misfile. Do not auto-route.
A23: 3 · MERGE WORKFLOW (run in order — nothing deletes until Phase 6)
A24: Phase 1 · DISCOVER | B24: Scan every PRIMARY/SECONDARY/CLOUD source (Scan Commands sheet) → every file lands in Scan Queue with path, size, hash.
A25: Phase 2 · NORMALIZE | B25: Apply 2026 Plowman naming. Identify orphans via magic bytes. Brand-detect via SEARCH formulas (already live).
A26: Phase 3 · DEDUPE | B26: SHA256 across ALL sources at once. Mark DUP. Pick canonical per the conflict rules above. This is where cloud+local truly blend.
A27: Phase 4 · ROUTE | B27: Move canonical to /Pristine/<brand>/. Collaborator work → /Pristine/_Collaborators/. Unsorted → _UNSORTED for review.
A28: Phase 5 · VERIFY | B28: Hash-verify the pristine copy matches source. Set Q-Grade. Log to Integrity sheet. Stamp with integrity tag.
A29: Phase 6 · CLONE & RECLAIM | B29: Replicate pristine → backup drive + cloud offsite. Confirm 3-2-1 in Clone Status. ONLY THEN may source dupes be deleted (Backup Guard flips to SAFE TO MOVE).
A31: 4 · MERGE PROGRESS (update Status — bar auto-fills)
A32: Phase | B32: Status | C32: Owner / Tool
A33: 1 Discover | B33: Not started | C33: Scan Commands / local agent
A34: 2 Normalize | B34: Not started | C34: Plowman Standard / Identifiers
A35: 3 Dedupe | B35: Not started | C35: SHA256 / Scan Queue
A36: 4 Route | B36: Not started | C36: Brand pristine folders
A37: 5 Verify | B37: Not started | C37: Integrity / Q-Grade
A38: 6 Clone & Reclaim | B38: Not started | C38: Clone Status / 3-2-1
A40: PROGRESS | B40: =TEXT(COUNTIF(B33:B38,"Done")/6,"0%") -> 0% | C40: =REPT("█",COUNTIF(B33:B38,"Done"))&REPT("░",6-COUNTIF(B33:B38,"Done")) -> ░░░░░░

Sheet Dedupe Sim
A1: DEDUPE SIMULATION — the conflict engine, proven on colliding files
A2: Sample collisions across sources. Canonical pick & action are FORMULA-DRIVEN per the Blend & Merge rules — this is how cloud+local actually merge.
A3: File | B3: Source | C3: SHA256 | D3: Format | E3: Q-Grade | F3: Q-Score | G3: Group | H3: Scenario | I3: Canonical? | J3: Action (auto)
A4: Kick_01.wav | B4: /Volumes/Audio | C4: a3f5e9..AAA | D4: WAV | E4: QA | F4: =IF(E4="QA",4,IF(E4="QB",3,IF(E4="QC",2,IF(E4="QX",1,0)))) -> 4 | G4: G1 | H4: Identical | I4: =IF(H4="Orphan","— identify first",IF(AND($F4=_xlfn.MAXIFS($F$4:$F$12,$G$4:$G$12,$G4),COUNTIFS($G$4:$G4,$G4,$F$4:$F4,$F4)=1),"✓ CANONICAL","subordinate")) -> ✓ CANONICAL | J4: =IF(H4="Orphan","Identify via magic bytes first",IF(I4="✓ CANONICAL","→ KEEP master in /Pristine/",IF(H4="Identical","↪ Log as clone; delete after 3-2-1",IF(H4="Lossy-vs-lossless","↪ Flag RE-SOURCE (lossy)","↪ Archive as _v2 (keep)")))) -> → KEEP master in /Pristine/
A5: Kick_01.wav | B5: 12RB | C5: a3f5e9..AAA | D5: WAV | E5: QA | F5: =IF(E5="QA",4,IF(E5="QB",3,IF(E5="QC",2,IF(E5="QX",1,0)))) -> 4 | G5: G1 | H5: Identical | I5: =IF(H5="Orphan","— identify first",IF(AND($F5=_xlfn.MAXIFS($F$4:$F$12,$G$4:$G$12,$G5),COUNTIFS($G$4:$G5,$G5,$F$4:$F5,$F5)=1),"✓ CANONICAL","subordinate")) -> subordinate | J5: =IF(H5="Orphan","Identify via magic bytes first",IF(I5="✓ CANONICAL","→ KEEP master in /Pristine/",IF(H5="Identical","↪ Log as clone; delete after 3-2-1",IF(H5="Lossy-vs-lossless","↪ Flag RE-SOURCE (lossy)","↪ Archive as _v2 (keep)")))) -> ↪ Log as clone; delete after 3-2-1
A6: Riser.wav | B6: /Volumes/Audio | C6: b7d2c1..BBB | D6: WAV | E6: QB | F6: =IF(E6="QA",4,IF(E6="QB",3,IF(E6="QC",2,IF(E6="QX",1,0)))) -> 3 | G6: G2 | H6: Lossy-vs-lossless | I6: =IF(H6="Orphan","— identify first",IF(AND($F6=_xlfn.MAXIFS($F$4:$F$12,$G$4:$G$12,$G6),COUNTIFS($G$4:$G6,$G6,$F$4:$F6,$F6)=1),"✓ CANONICAL","subordinate")) -> ✓ CANONICAL | J6: =IF(H6="Orphan","Identify via magic bytes first",IF(I6="✓ CANONICAL","→ KEEP master in /Pristine/",IF(H6="Identical","↪ Log as clone; delete after 3-2-1",IF(H6="Lossy-vs-lossless","↪ Flag RE-SOURCE (lossy)","↪ Archive as _v2 (keep)")))) -> → KEEP master in /Pristine/
A7: Riser.mp3 | B7: rsplowman cloud | C7: c1e9f4..CCC | D7: MP3 | E7: QC | F7: =IF(E7="QA",4,IF(E7="QB",3,IF(E7="QC",2,IF(E7="QX",1,0)))) -> 2 | G7: G2 | H7: Lossy-vs-lossless | I7: =IF(H7="Orphan","— identify first",IF(AND($F7=_xlfn.MAXIFS($F$4:$F$12,$G$4:$G$12,$G7),COUNTIFS($G$4:$G7,$G7,$F$4:$F7,$F7)=1),"✓ CANONICAL","subordinate")) -> subordinate | J7: =IF(H7="Orphan","Identify via magic bytes first",IF(I7="✓ CANONICAL","→ KEEP master in /Pristine/",IF(H7="Identical","↪ Log as clone; delete after 3-2-1",IF(H7="Lossy-vs-lossless","↪ Flag RE-SOURCE (lossy)","↪ Archive as _v2 (keep)")))) -> ↪ Flag RE-SOURCE (lossy)
A8: Snare.wav | B8: /Volumes/Audio | C8: d4a1b8..DDD | D8: WAV | E8: QA | F8: =IF(E8="QA",4,IF(E8="QB",3,IF(E8="QC",2,IF(E8="QX",1,0)))) -> 4 | G8: G3 | H8: Name-collision | I8: =IF(H8="Orphan","— identify first",IF(AND($F8=_xlfn.MAXIFS($F$4:$F$12,$G$4:$G$12,$G8),COUNTIFS($G$4:$G8,$G8,$F$4:$F8,$F8)=1),"✓ CANONICAL","subordinate")) -> ✓ CANONICAL | J8: =IF(H8="Orphan","Identify via magic bytes first",IF(I8="✓ CANONICAL","→ KEEP master in /Pristine/",IF(H8="Identical","↪ Log as clone; delete after 3-2-1",IF(H8="Lossy-vs-lossless","↪ Flag RE-SOURCE (lossy)","↪ Archive as _v2 (keep)")))) -> → KEEP master in /Pristine/
A9: Snare.wav | B9: rsplowman cloud | C9: e5b2c9..EEE | D9: WAV | E9: QB | F9: =IF(E9="QA",4,IF(E9="QB",3,IF(E9="QC",2,IF(E9="QX",1,0)))) -> 3 | G9: G3 | H9: Name-collision | I9: =IF(H9="Orphan","— identify first",IF(AND($F9=_xlfn.MAXIFS($F$4:$F$12,$G$4:$G$12,$G9),COUNTIFS($G$4:$G9,$G9,$F$4:$F9,$F9)=1),"✓ CANONICAL","subordinate")) -> subordinate | J9: =IF(H9="Orphan","Identify via magic bytes first",IF(I9="✓ CANONICAL","→ KEEP master in /Pristine/",IF(H9="Identical","↪ Log as clone; delete after 3-2-1",IF(H9="Lossy-vs-lossless","↪ Flag RE-SOURCE (lossy)","↪ Archive as _v2 (keep)")))) -> ↪ Archive as _v2 (keep)
A10: Vox_Lead.wav | B10: rsplowman cloud | C10: f6c3da..FFF | D10: WAV | E10: QA | F10: =IF(E10="QA",4,IF(E10="QB",3,IF(E10="QC",2,IF(E10="QX",1,0)))) -> 4 | G10: G4 | H10: Cloud-only | I10: =IF(H10="Orphan","— identify first",IF(AND($F10=_xlfn.MAXIFS($F$4:$F$12,$G$4:$G$12,$G10),COUNTIFS($G$4:$G10,$G10,$F$4:$F10,$F10)=1),"✓ CANONICAL","subordinate")) -> ✓ CANONICAL | J10: =IF(H10="Orphan","Identify via magic bytes first",IF(I10="✓ CANONICAL","→ KEEP master in /Pristine/",IF(H10="Identical","↪ Log as clone; delete after 3-2-1",IF(H10="Lossy-vs-lossless","↪ Flag RE-SOURCE (lossy)","↪ Archive as _v2 (keep)")))) -> → KEEP master in /Pristine/
A11: UNKNOWN_882 | B11: MAG4TB | C11: 0a1b2c..GGG | D11: (none) | E11: ? | F11: =IF(E11="QA",4,IF(E11="QB",3,IF(E11="QC",2,IF(E11="QX",1,0)))) -> 0 | G11: G5 | H11: Orphan | I11: =IF(H11="Orphan","— identify first",IF(AND($F11=_xlfn.MAXIFS($F$4:$F$12,$G$4:$G$12,$G11),COUNTIFS($G$4:$G11,$G11,$F$4:$F11,$F11)=1),"✓ CANONICAL","subordinate")) -> — identify first | J11: =IF(H11="Orphan","Identify via magic bytes first",IF(I11="✓ CANONICAL","→ KEEP master in /Pristine/",IF(H11="Identical","↪ Log as clone; delete after 3-2-1",IF(H11="Lossy-vs-lossless","↪ Flag RE-SOURCE (lossy)","↪ Archive as _v2 (keep)")))) -> Identify via magic bytes first
A12: Loop_120.flac | B12: /Volumes/Audio | C12: 1b2c3d..HHH | D12: FLAC | E12: QA | F12: =IF(E12="QA",4,IF(E12="QB",3,IF(E12="QC",2,IF(E12="QX",1,0)))) -> 4 | G12: G6 | H12: Unique | I12: =IF(H12="Orphan","— identify first",IF(AND($F12=_xlfn.MAXIFS($F$4:$F$12,$G$4:$G$12,$G12),COUNTIFS($G$4:$G12,$G12,$F$4:$F12,$F12)=1),"✓ CANONICAL","subordinate")) -> ✓ CANONICAL | J12: =IF(H12="Orphan","Identify via magic bytes first",IF(I12="✓ CANONICAL","→ KEEP master in /Pristine/",IF(H12="Identical","↪ Log as clone; delete after 3-2-1",IF(H12="Lossy-vs-lossless","↪ Flag RE-SOURCE (lossy)","↪ Archive as _v2 (keep)")))) -> → KEEP master in /Pristine/

Sheet Load Balancer
A1: LOAD BALANCER — rebalance + representation audit
A2: Computes optimal data distribution across all drives + confirms every dataset is on local AND cloud (3-2-1). Yellow = scanner inputs; rest auto-computes.
A4: 1 · DRIVE LOAD & REBALANCE
A5: Drive | B5: Tier | C5: Capacity GB | D5: Used GB | E5: Free GB | F5: % Full | G5: Target % | H5: Rebalance GB | I5: Action
A6: /Volumes/Audio | B6: Local | C6: 16000 | D6: 9000 | E6: =C6-D6 -> 7000 | F6: =IFERROR(D6/C6,0) -> 0.5625 | G6: =IFERROR($D$12/$C$12,0) -> 0.17077465 | H6: =ROUND(D6-C6*$G6,0) -> 6268 | I6: =IF(H6>50,"OFFLOAD "&H6&" GB",IF(H6<-50,"can receive "&-H6&" GB","balanced")) -> OFFLOAD 6268 GB
A7: 12RB | B7: Local | C7: 12000 | D7: 11000 | E7: =C7-D7 -> 1000 | F7: =IFERROR(D7/C7,0) -> 0.91666667 | G7: =IFERROR($D$12/$C$12,0) -> 0.17077465 | H7: =ROUND(D7-C7*$G7,0) -> 8951 | I7: =IF(H7>50,"OFFLOAD "&H7&" GB",IF(H7<-50,"can receive "&-H7&" GB","balanced")) -> OFFLOAD 8951 GB
A8: MAG4TB | B8: Local | C8: 4000 | D8: 3500 | E8: =C8-D8 -> 500 | F8: =IFERROR(D8/C8,0) -> 0.875 | G8: =IFERROR($D$12/$C$12,0) -> 0.17077465 | H8: =ROUND(D8-C8*$G8,0) -> 2817 | I8: =IF(H8>50,"OFFLOAD "&H8&" GB",IF(H8<-50,"can receive "&-H8&" GB","balanced")) -> OFFLOAD 2817 GB
A9: Pristine Masters | B9: Local | C9: 8000 | D9: 500 | E9: =C9-D9 -> 7500 | F9: =IFERROR(D9/C9,0) -> 0.0625 | G9: =IFERROR($D$12/$C$12,0) -> 0.17077465 | H9: =ROUND(D9-C9*$G9,0) -> -866 | I9: =IF(H9>50,"OFFLOAD "&H9&" GB",IF(H9<-50,"can receive "&-H9&" GB","balanced")) -> can receive 866 GB
A10: GDrive (rsplowman) | B10: Cloud | C10: 2000 | D10: 250 | E10: =C10-D10 -> 1750 | F10: =IFERROR(D10/C10,0) -> 0.125 | G10: =IFERROR($D$12/$C$12,0) -> 0.17077465 | H10: =ROUND(D10-C10*$G10,0) -> -92 | I10: =IF(H10>50,"OFFLOAD "&H10&" GB",IF(H10<-50,"can receive "&-H10&" GB","balanced")) -> can receive 92 GB
A11: Cloud Archive (offsite) | B11: Cloud | C11: 100000 | D11: 0 | E11: =C11-D11 -> 100000 | F11: =IFERROR(D11/C11,0) -> 0 | G11: =IFERROR($D$12/$C$12,0) -> 0.17077465 | H11: =ROUND(D11-C11*$G11,0) -> -17077 | I11: =IF(H11>50,"OFFLOAD "&H11&" GB",IF(H11<-50,"can receive "&-H11&" GB","balanced")) -> can receive 17077 GB
A12: TOTAL | C12: =SUM(C6:C11) -> 142000 | D12: =SUM(D6:D11) -> 24250 | E12: =SUM(E6:E11) -> 117750 | F12: =IFERROR(D12/C12,0) -> 0.17077465
A14: 2 · REPRESENTATION AUDIT — is every dataset on local AND cloud?
A15: Dataset | B15: Local Copies | C15: Cloud Copies | D15: Total | E15: 3-2-1 OK? | F15: Gap / Action
A16: NOIZYANTHROPIC | B16: 1 | C16: 0 | D16: =B16+C16 -> 1 | E16: =IF(AND(B16>=2,C16>=1),"✓ 3-2-1",IF(D16>=1,"⚠ under-replicated","✗ no copies")) -> ⚠ under-replicated | F16: =IF(AND(B16>=2,C16>=1),"— fully represented",TRIM(IF(B16<2,"need "&(2-B16)&" more local; ","")&IF(C16<1,"need offsite copy",""))) -> need 1 more local; need offsite copy
A17: NOIZYBEAST | B17: 1 | C17: 0 | D17: =B17+C17 -> 1 | E17: =IF(AND(B17>=2,C17>=1),"✓ 3-2-1",IF(D17>=1,"⚠ under-replicated","✗ no copies")) -> ⚠ under-replicated | F17: =IF(AND(B17>=2,C17>=1),"— fully represented",TRIM(IF(B17<2,"need "&(2-B17)&" more local; ","")&IF(C17<1,"need offsite copy",""))) -> need 1 more local; need offsite copy
A18: METABEAST | B18: 1 | C18: 0 | D18: =B18+C18 -> 1 | E18: =IF(AND(B18>=2,C18>=1),"✓ 3-2-1",IF(D18>=1,"⚠ under-replicated","✗ no copies")) -> ⚠ under-replicated | F18: =IF(AND(B18>=2,C18>=1),"— fully represented",TRIM(IF(B18<2,"need "&(2-B18)&" more local; ","")&IF(C18<1,"need offsite copy",""))) -> need 1 more local; need offsite copy
A19: Collaborators (Gabriel/Lucy) | B19: 1 | C19: 0 | D19: =B19+C19 -> 1 | E19: =IF(AND(B19>=2,C19>=1),"✓ 3-2-1",IF(D19>=1,"⚠ under-replicated","✗ no copies")) -> ⚠ under-replicated | F19: =IF(AND(B19>=2,C19>=1),"— fully represented",TRIM(IF(B19<2,"need "&(2-B19)&" more local; ","")&IF(C19<1,"need offsite copy",""))) -> need 1 more local; need offsite copy
A20: Vendor Libraries | B20: 1 | C20: 0 | D20: =B20+C20 -> 1 | E20: =IF(AND(B20>=2,C20>=1),"✓ 3-2-1",IF(D20>=1,"⚠ under-replicated","✗ no copies")) -> ⚠ under-replicated | F20: =IF(AND(B20>=2,C20>=1),"— fully represented",TRIM(IF(B20<2,"need "&(2-B20)&" more local; ","")&IF(C20<1,"need offsite copy",""))) -> need 1 more local; need offsite copy
A22: REPRESENTATION SCORE | B22: =TEXT(COUNTIF(E16:E20,"✓ 3-2-1")/5,"0%")&" of datasets fully represented (3-2-1)" -> 0% of datasets fully represented (3-2-1)

Sheet M2 Ultra Offload
A1: M2 ULTRA OFFLOAD ANALYSIS — what must stay vs what can leave
A2: Frees your machine: keep only the hot working set local; push cold/archive/dupes to MAG4TB + cloud. Est GB are yellow inputs — scanner fills.
A3: Data Category | B3: Access Freq | C3: Must Stay on M2? | D3: Reason | E3: Offload Target | F3: Est GB
A4: Active project masters (current builds) | B4: Daily | C4: STAY | D4: Low-latency editing | E4: — keep on M2 | F4: 0
A5: SuperSonic working set (in-process) | B5: Daily | C5: STAY | D5: Active cleaning/rebuild | E5: — keep on M2 | F5: 0
A6: LM Studio model + cache | B6: Daily | C6: STAY | D6: Inference engine (70B) | E6: — keep on M2 (~150GB) | F6: 150
A7: Pristine masters (canonical, 1 copy) | B7: Occasional | C7: 1 LOCAL | D7: 3-2-1: 1 local + cloud clone | E7: local + cloud clone | F7: 0
A8: Delivered / released libraries | B8: Rarely | C8: OFFLOAD | D8: Shipped — cold storage | E8: Cloud Archive + MAG4TB | F8: 0
A9: Old project archives (completed) | B9: Rarely | C9: OFFLOAD | D9: Cold — offsite | E9: Cloud Archive (offsite) | F9: 0
A10: Vendor sample libs (commercial, re-downloadable) | B10: Occasional | C10: OFFLOAD | D10: Re-downloadable from vendor | E10: keep index, archive bulk | F10: 0
A11: Duplicate files (post-dedupe) | B11: Never | C11: RECLAIM | D11: Redundant — delete after 3-2-1 | E11: DELETE (guarded) | F11: 0
A12: Orphan / unknown (no extension) | B12: — | C12: QUARANTINE | D12: Identify via magic bytes first | E12: process then route | F12: 0
A14: SUMMARY (live as Est GB fill)
A15: Must stay on M2 (GB) | B15: =SUMIF(C4:C12,"STAY",F4:F12)+SUMIF(C4:C12,"1 LOCAL",F4:F12) -> 150
A16: Offloadable (GB) | B16: =SUMIF(C4:C12,"OFFLOAD",F4:F12) -> 0
A17: Reclaimable via dedupe (GB) | B17: =SUMIF(C4:C12,"RECLAIM",F4:F12) -> 0
A18: Total catalogued (GB) | B18: =SUM(F4:F12) -> 150
A19: % that can leave M2 | B19: =IFERROR((B16+B17)/B18,0) -> 0

Sheet Action Register
A1: ACTION REGISTER — you list, I execute | I1: STATUS
A2: Master fix/task list for the whole operation. Add a row; I take everything I can. P1 = unblocks the mission. | I2: Open | J2: =COUNTIF(F4:F12,"Open") -> 8
A3: ID | B3: Task | C3: Category | D3: Priority | E3: Owner | F3: Status | G3: Notes | I3: Waiting | J3: =COUNTIF(F4:F12,"Waiting") -> 1
A4: ACT-001 | B4: Connect rsplowman@gmail.com (Drive + Gmail) | C4: Cloud | D4: P1 | E4: Robert | F4: Open | G4: Unlocks the 250GB scan | I4: Done | J4: =COUNTIF(F4:F12,"Done") -> 0
A5: ACT-002 | B5: Run Method-A local scan (Scan Commands) | C5: Scan | D5: P1 | E5: Robert + DC | F5: Open | G5: Fills the Scan Queue | I5: P1 urgent | J5: =COUNTIF(D4:D12,"P1") -> 3
A6: ACT-003 | B6: Install Desktop Commander | C6: Setup | D6: P1 | E6: Robert | F6: Open | G6: npx -y @wonderwhy-er/desktop-commander setup
A7: ACT-004 | B7: Load filesystem MCP into LM Studio | C7: Setup | D7: P2 | E7: Robert | F7: Open | G7: Enables Method C scan
A8: ACT-005 | B8: Set up Cloud Archive offsite (3-2-1) | C8: Backup | D8: P2 | E8: Robert | F8: Open | G8: Azure Blob / Backblaze — LOC-021
A9: ACT-006 | B9: Confirm 12RB / MAG4TB real capacities | C9: Data | D9: P3 | E9: Robert | F9: Open | G9: Replace assumed 12TB/4TB
A10: ACT-007 | B10: Re-run all cloud scans after account switch | C10: Scan | D10: P2 | E10: Claude | F10: Waiting | G10: After ACT-001
A11: ACT-008 | B11: Drag Library Index tab to front | C11: Polish | D11: P4 | E11: Robert | F11: Open | G11: Cosmetic
A12: ACT-009 | B12: Enumerate M2 Ultra local macOS users | C12: Admin | D12: P2 | E12: Robert + local agent | F12: Open | G12: Run `dscl . list /Users` or `ls /Users` — needs local agent (not reachable from Excel)
A13: POWERPOINT POWER-UPS (researched 2026 — for when you present/pitch NoizyArmy)
A14: Tool | B14: Best For | C14: Mac? | D14: Note
